day4signed_unsigned_divsion/signed_unsigned_divsion.sv
// Combined divider: instantiates both unsigned and signed 8-bit dividers
// so both can be simulated/synthesized together under one top module.

module divider_unsigned (
    input  wire [7:0] A,
    input  wire [7:0] B,
    output wire [7:0] quotient,
    output wire [7:0] remainder
);
    assign quotient  = (B != 0) ? (A / B) : 8'd0;
    assign remainder = (B != 0) ? (A % B) : 8'd0;

    initial begin
        $dumpfile("divider_unsigned.vcd");
        $dumpvars(0, divider_unsigned);
    end
endmodule

module divider_signed (
    input  wire signed [7:0] A,
    input  wire signed [7:0] B,
    output wire signed [7:0] quotient,
    output wire signed [7:0] remainder
);
    assign quotient  = (B != 0) ? (A / B) : 8'sd0;
    assign remainder = (B != 0) ? (A % B) : 8'sd0;

    initial begin
        $dumpfile("divider_signed.vcd");
        $dumpvars(0, divider_signed);
    end
endmodule

module divider_top (
    input  wire [7:0]        A_u,
    input  wire [7:0]        B_u,
    output wire [7:0]        quotient_u,
    output wire [7:0]        remainder_u,

    input  wire signed [7:0] A_s,
    input  wire signed [7:0] B_s,
    output wire signed [7:0] quotient_s,
    output wire signed [7:0] remainder_s
);
    divider_unsigned u_div_unsigned (
        .A(A_u),
        .B(B_u),
        .quotient(quotient_u),
        .remainder(remainder_u)
    );

    divider_signed u_div_signed (
        .A(A_s),
        .B(B_s),
        .quotient(quotient_s),
        .remainder(remainder_s)
    );

    initial begin
        $dumpfile("divider_top.vcd");
        $dumpvars(0, divider_top);
    end
endmodule

day4signed_unsigned_divsion/divider_unsigned.vcd
$date
	Thu Aug 20 16:20:04 2026
$end
$version
	Icarus Verilog
$end
$timescale
	1ps
$end
$scope module divider_top $end
$scope module u_div_unsigned $end
$var wire 8 ! A [7:0] $end
$var wire 8 " B [7:0] $end
$var wire 8 # remainder [7:0] $end
$var wire 8 $ quotient [7:0] $end
$upscope $end
$upscope $end
$scope module divider_top $end
$scope module u_div_signed $end
$var wire 8 % A [7:0] $end
$var wire 8 & B [7:0] $end
$var wire 8 ' remainder [7:0] $end
$var wire 8 ( quotient [7:0] $end
$upscope $end
$upscope $end
$scope module divider_top $end
$var wire 8 ) A_s [7:0] $end
$var wire 8 * A_u [7:0] $end
$var wire 8 + B_s [7:0] $end
$var wire 8 , B_u [7:0] $end
$var wire 8 - remainder_u [7:0] $end
$var wire 8 . remainder_s [7:0] $end
$var wire 8 / quotient_u [7:0] $end
$var wire 8 0 quotient_s [7:0] $end
$scope module u_div_signed $end
$upscope $end
$scope module u_div_unsigned $end
$upscope $end
$upscope $end
$enddefinitions $end
#0
$dumpvars
bx 0
b0 /
bx .
b0 -
b101 ,
bz +
b0 *
bz )
bx (
bx '
bz &
bz %
b0 $
b0 #
b101 "
b0 !
$end
#1000
b1 #
b1 -
b11 $
b11 /
b11 "
b11 ,
b1010 !
b1010 *
#2000
b11111111 $
b11111111 /
b0 #
b0 -
b1 "
b1 ,
b11111111 !
b11111111 *
#3000
b1 $
b1 /
b11111111 "
b11111111 ,
#4000
b1110 $
b1110 /
b10 #
b10 -
b111 "
b111 ,
b1100100 !
b1100100 *
#5000
b0 $
b0 /
b111 #
b111 -
b1100100 "
b1100100 ,
b111 !
b111 *
#6000
b1000010 $
b1000010 /
b10 #
b10 -
b11 "
b11 ,
b11001000 !
b11001000 *
#7000
b0 $
b0 /
b0 #
b0 -
b0 "
b0 ,
b0 !
b0 *
#8000
b110010 !
b110010 *
#9000
b0 (
b0 0
b0 '
b0 .
b101 &
b101 +
b0 %
b0 )
#10000
b1 '
b1 .
b11 (
b11 0
b11 &
b11 +
b1010 %
b1010 )
#11000
b11111101 (
b11111101 0
b11111111 '
b11111111 .
b11110110 %
b11110110 )
#12000
b1 '
b1 .
b11111101 &
b11111101 +
b1010 %
b1010 )
#13000
b11 (
b11 0
b11111111 '
b11111111 .
b11110110 %
b11110110 )
#14000
b1111111 (
b1111111 0
b0 '
b0 .
b1 &
b1 +
b1111111 %
b1111111 )
#15000
b10000000 (
b10000000 0
b10000000 %
b10000000 )
#16000
b11111111 &
b11111111 +
#17000
b111 '
b111 .
b0 (
b0 0
b1100100 &
b1100100 +
b111 %
b111 )
#18000
b11111001 '
b11111001 .
b11111001 %
b11111001 )
#19000
b0 '
b0 .
b0 &
b0 +
b0 %
b0 )
#20000
b110010 %
b110010 )
