ROM/rom.sv
module rom (
    input  wire [2:0] address,
    output reg  [7:0] data
);
    always @(*) begin
        case (address)
            3'd0: data = 8'h11;
            3'd1: data = 8'h22;
            3'd2: data = 8'h33;
            3'd3: data = 8'h44;
            3'd4: data = 8'h55;
            3'd5: data = 8'h66;
            3'd6: data = 8'h77;
            3'd7: data = 8'h88;
            default: data = 8'h00;
        endcase
    end

    initial begin
        $dumpfile("rom.vcd");
        $dumpvars(0, rom);
    end
endmodule

ROM/rom.vcd
$date
	Wed Aug 26 06:51:34 2026
$end
$version
	Icarus Verilog
$end
$timescale
	1ps
$end
$scope module rom $end
$var wire 3 ! address [2:0] $end
$var reg 8 " data [7:0] $end
$upscope $end
$enddefinitions $end
$comment Show the parameter values. $end
$dumpall
$end
#0
$dumpvars
b10001 "
b0 !
$end
#1000
b100010 "
b1 !
#2000
b110011 "
b10 !
#3000
b1000100 "
b11 !
#4000
b1010101 "
b100 !
#5000
b1100110 "
b101 !
#6000
b1110111 "
b110 !
#7000
b10001000 "
b111 !
#8000
b10001 "
b0 !
#9000
b10001000 "
b111 !
#10000
b1110111 "
b110 !
#11000
b1100110 "
b101 !
#12000
b1010101 "
b100 !
#13000
b1000100 "
b11 !
#14000
b110011 "
b10 !
#15000
b100010 "
b1 !
#16000
b10001 "
b0 !
