adder.v
module adder (
    input  signed [7:0] a,
    input  signed [7:0] b,
    output signed [8:0] y
);
    assign y = a + b;

    initial begin
        $dumpfile("adder_logic.vcd");
        $dumpvars(0, adder);
    end
endmodule

adder_logic.vcd
$date
	Thu Aug 20 14:26:50 2026
$end
$version
	Icarus Verilog
$end
$timescale
	1ps
$end
$scope module adder $end
$var wire 8 ! a [7:0] $end
$var wire 8 " b [7:0] $end
$var wire 9 # y [8:0] $end
$upscope $end
$enddefinitions $end
$comment Show the parameter values. $end
$dumpall
$end
#0
$dumpvars
b0 #
b0 "
b0 !
$end
#2000
b11111111 "
b111111110 #
b11111111 !
#4000
b0 #
b1 "
#6000
b10000000 "
b100000000 #
b10000000 !
#8000
b111111111 #
b1111111 "
#10000
b11111110 #
b1111111 !
#12000
b10000000 #
b1 "
#14000
b110010 "
b0 #
b11001110 !
#16000
b11111111 "
b111111111 #
b0 !
#18001
b1110110 "
b1001011 #
b11010101 !
#20001
b10011101 "
b110010000 #
b11110011 !
#22001
b11011110 "
b111011101 #
b11111111 !
#24001
b111001 "
b1010011 #
b11010 !
#26001
b1100110 "
b1010110 #
b11110000 !
#28001
b100010 "
b110111101 #
b10011011 !
#30001
b1101 "
b100001 #
b10100 !
#32001
b1110111 "
b11001 #
b10100010 !
#34001
b11010000 "
b1001001 #
b1111001 !
#36001
b1101100 "
b10011001 #
b101101 !
#38001
b10010100 "
b110111000 #
b100100 !
#40001
b1010010 "
b1001100 #
b11111010 !
#42001
b10010 "
b1010111 #
b1000101 !
#44001
b10001111 "
b101100010 #
b11010011 !
#46001
b10101111 "
b110100010 #
b11110011 !
#48001
b11001000 "
b110011110 #
b11010110 !
#50001
b10000010 "
b101011100 #
b11011010 !
#52001
b1100110 "
b10010010 #
b101100 !
#54001
b11111 "
b10011010 #
b1111011 !
#56001
b1001110 "
b10 #
b10110100 !
#58001
b11011011 "
b111011001 #
b11111110 !
#60001
b10001001 "
b101001010 #
b11000001 !
#62001
b11010101 "
b101100001 #
b10001100 !
#64001
b11100000 "
b100010 #
b1000010 !
#66001
b10101101 "
b111011000 #
b101011 !
#68001
b10010111 "
b111111101 #
b1100110 !
#70001
b10000100 "
b100010010 #
b10001110 !
#72001
b11100110 "
b101001 #
b1000011 !
#74001
b10111110 "
b100101 #
b1100111 !
#76001
b1111111 "
b1000 #
b10001001 !
#78001
b10100010 "
b101010111 #
b10110101 !
#80001
b11011011 "
b110101111 #
b11010100 !
#82001
b10000010 "
b100100100 #
b10100010 !
#84001
b11000 "
b10001100 #
b1110100 !
#86001
b110110 "
b1110 #
b11011000 !
#88001
b10100001 "
b100100011 #
b10000010 !
#90001
b10010111 "
b111010100 #
b111101 !
#92001
b10111011 "
b110100 #
b1111001 !
#94001
b101101 "
b110110001 #
b10000100 !
#96001
b1010001 "
b111010110 #
b10000101 !
#98001
b11000001 "
b111001101 #
b1100 !
#100001
b1011100 "
b1010110 #
b11111010 !
#102001
b101101 "
b1001110 #
b100001 !
#104001
b1001101 "
b111111010 #
b10101101 !
#106001
b11111100 "
b110110110 #
b10111010 !
#108001
b10001101 "
b111001111 #
b1000010 !
#110001
b1110110 "
b1111000 #
b10 !
#112001
b1100001 "
b111100010 #
b10000001 !
#114001
b1 "
b110110111 #
b10110110 !
#116001
b1101001 "
b110110 #
b11001101 !
#118001
b1010001 "
b10110100 #
b1100011 !
#120001
b1110 "
b100011 #
b10101 !
#122001
b10001001 "
b100010111 #
b10001110 !
#124001
b101 "
b1101110 #
b1101001 !
#126001
b1010101 "
b111011000 #
b10000011 !
#128001
b10101100 "
b111000100 #
b11000 !
#130001
b1110000 "
b1111001 #
b1001 !
#132001
b11011100 "
b111010011 #
b11110111 !
#134001
b1101 "
b0 #
b11110011 !
#136001
b1111011 "
b10011 #
b10011000 !
#138001
b11000101 "
b101101111 #
b10101010 !
#140001
b10110000 "
b111111000 #
b1001000 !
#142001
b11100100 "
b110000010 #
b10011110 !
#144001
b10011110 "
b101100010 #
b11000100 !
#146001
b10001010 "
b110010011 #
b1001 !
#148001
b10011110 "
b100 #
b1100110 !
#150001
b10100011 "
b110111000 #
b10101 !
#152001
b11110010 "
b111100100 #
b11110010 !
#154001
b1110100 "
b100000 #
b10101100 !
#156001
b100110 "
b110100110 #
b10000000 !
#158001
b10010010 "
b101010100 #
b11000010 !
#160001
b10101100 "
b110101011 #
b11111111 !
#162001
b10000011 "
b110011101 #
b11010 !
#164001
b11000101 "
b111000010 #
b11111101 !
#166001
b11101010 "
b111101100 #
b10 !
#168001
b11111101 "
b110001110 #
b10010001 !
#170001
b101001 "
b100111 #
b11111110 !
#172001
b10010100 "
b100010111 #
b10000011 !
#174001
b1100000 "
b110101 #
b11010101 !
#176001
b10100 "
b11101 #
b1001 !
#178001
b10100000 "
b110001011 #
b11101011 !
#180001
b11111001 "
b110100011 #
b10101010 !
#182001
b1101010 "
b11000100 #
b1011010 !
#184001
b11001001 "
b101001100 #
b10000011 !
#186001
b1010100 "
b10101001 #
b1010101 !
#188001
b11100000 "
b110010011 #
b10110011 !
#190001
b110110 "
b10010010 #
b1011100 !
#192001
b101011 "
b1000011 #
b11000 !
#194001
b1101010 "
b1001100 #
b11100010 !
#196001
b11001010 "
b110001010 #
b11000000 !
#198001
b10110000 "
b101111001 #
b11001001 !
#200001
b10000000 "
b101001000 #
b11001000 !
#202001
b11000101 "
b111011 #
b1110110 !
#204001
b110110 "
b111000011 #
b10001101 !
#206001
b1111110 "
b10001101 #
b1111 !
#208001
b1110011 "
b110000 #
b10111101 !
#210001
b11 "
b110010100 #
b10010001 !
#212001
b110110 "
b10001000 #
b1010010 !
#214001
b1010011 "
b1011001 #
b110 !
#216001
b11011010 "
b111000000 #
b11100110 !
#218001
b11 "
b111011110 #
b11011011 !
#220001
b1100011 "
b101111 #
b11001100 !
#222001
b1101 "
b1100101 #
b1011000 !
#224001
b11110101 "
b1011110 #
b1101001 !
#226001
b11001100 "
b101110010 #
b10100110 !
#228001
b1101001 "
b10101111 #
b1000110 !
#230001
b1011100 "
b1111000 #
b11100 !
#232001
b10011000 "
b110001001 #
b11110001 !
#234001
b1110000 "
b101111 #
b10111111 !
#236001
b1111010 "
b11001101 #
b1010011 !
#238001
b111000 "
b111100100 #
b10101100 !
#240001
b10010100 "
b111001111 #
b111011 !
#242001
b1100011 "
b11001111 #
b1101100 !
#244001
b110100 "
b111011 #
b111 !
#246001
b1110001 "
b1110111 #
b110 !
#248001
b11000100 "
b1000010 #
b1111110 !
#250001
b111 "
b1101111 #
b1101000 !
#252001
b11011111 "
b101110111 #
b10011000 !
#254001
b1101101 "
b10110011 #
b1000110 !
#256001
b10101101 "
b111111100 #
b1001111 !
#258001
b11101010 "
b110001010 #
b10100000 !
#260001
b1101 "
b1100001 #
b1010100 !
#262001
b10001111 "
b111001101 #
b111110 !
#264001
b10110000 "
b110101110 #
b11111110 !
#266001
b11100111 "
b111000 #
b1010001 !
#268001
b110111 "
b111010100 #
b10011101 !
#270001
b10111000 "
b100111011 #
b10000011 !
#272001
b10100010 "
b100111001 #
b10010111 !
#274001
b10110111 "
b110000010 #
b11001011 !
#276001
b10011110 "
b100100100 #
b10000110 !
#278001
b111010 "
b111100001 #
b10100111 !
#280001
b1010100 "
b111101001 #
b10010101 !
#282001
b11010011 "
b1100 #
b111001 !
#284001
b1101011 "
b111001 #
b11001110 !
#286001
b111111 "
b10010110 #
b1010111 !
#288001
b10 "
b111110110 #
b11110100 !
#290001
b111101 "
b11011 #
b11011110 !
#292001
b10010010 "
b110011111 #
b1101 !
#294001
b10110000 "
b111000010 #
b10010 !
#296001
b1001010 "
b111101100 #
b10100010 !
#298001
b110000 "
b111001111 #
b10011111 !
#300001
b10110101 "
b111111011 #
b1000110 !
#302001
b11111101 "
b110110001 #
b10110100 !
#304001
b1010100 "
b1011010 #
b110 !
#306001
b10100100 "
b110000011 #
b11011111 !
#308001
b10110010 "
b110101100 #
b11111010 !
#310001
b11001111 "
b110011000 #
b11001001 !
#312001
b11110 "
b110010 #
b10100 !
#314001
b11110010 "
b1001000 #
b1010110 !
#316001
b10111011 "
b111110000 #
b110101 !
#318001
b101011 "
b110010 #
b111 !
#320001
b100101 "
b111100110 #
b11000001 !
#322001
b10110100 "
b101001101 #
b10011001 !
#324001
b1101101 "
b1011000 #
b11101011 !
#326001
b11101010 "
b110000000 #
b10010110 !
#328001
b1 "
b110100 #
b110011 !
#330001
b10010010 "
b101101100 #
b11011010 !
#332001
b101 "
b0 #
b11111011 !
#334001
b101011 "
b111111101 #
b11010010 !
#336001
b110010 "
b110111111 #
b10001101 !
#338001
b1110111 "
b11001110 #
b1010111 !
#340001
b11011110 "
b1111 #
b110001 !
#342001
b100 "
b1101000 #
b1100100 !
#344001
b1110011 "
b11110000 #
b1111101 !
#346001
b11011011 "
b110010111 #
b10111100 !
#348001
b1011001 "
b10111110 #
b1100101 !
#350001
b10001010 "
b101011010 #
b11010000 !
#352001
b1001 "
b111101 #
b110100 !
#354001
b1110010 "
b1001001 #
b11010111 !
#356001
b11001001 "
b10 #
b111001 !
#358001
b10101011 "
b101110011 #
b11001000 !
#360001
b1000001 "
b111111011 #
b10111010 !
#362001
b11010101 "
b1001100 #
b1110111 !
#364001
b111111 "
b1010101 #
b10110 !
#366001
b1110111 "
b10010010 #
b11011 !
#368001
b10110 "
b1011011 #
b1000101 !
#370001
b11111110 "
b1010101 #
b1010111 !
#372001
b1100011 "
b11010001 #
b1101110 !
#374001
b11011101 "
b110111000 #
b11011011 !
#376001
b10000010 "
b101111010 #
b11111000 !
#378001
b11100111 "
b110101101 #
b11000110 !
#380001
b10011000 "
b111010000 #
b111000 !
#382001
b1100000 "
b110111 #
b11010111 !
#384001
b100100 "
b110101 #
b10001 !
#386001
b10101101 "
b110110111 #
b1010 !
#388001
b10101010 "
b101 #
b1011011 !
#390001
b101010 "
b110101011 #
b10000001 !
#392001
b11101101 "
b111111001 #
b1100 !
#394001
b10011101 "
b100100000 #
b10000011 !
#396001
b11001000 "
b110110011 #
b11101011 !
#398001
b10110010 "
b110101101 #
b11111011 !
#400001
b11110100 "
b110110000 #
b10111100 !
#402001
b1110001 "
b1100 #
b10011011 !
#404001
b10111000 "
b100010 #
b1101010 !
#406001
b11001011 "
b111110100 #
b101001 !
#408001
b10110 "
b10010011 #
b1111101 !
#410001
b11011000 "
b1 #
b101001 !
#412001
b1000000 "
b1001 #
b11001001 !
#414001
b10001100 "
b110001111 #
b11 !
#416001
b11000111 "
b101010010 #
b10001011 !
#418001
b11100111 "
b111011001 #
b11110010 !
#420001
b1000011 "
b1110010 #
b101111 !
#422001
b1101111 "
b111110001 #
b10000010 !
#424001
b1111001 "
b1011111 #
b11100110 !
#426001
b10110100 "
b101100001 #
b10101101 !
#428001
b111100 "
b10001011 #
b1001111 !
#430001
b10110011 "
b111011010 #
b100111 !
#432001
b1100011 "
b1011010 #
b11110111 !
#434001
b11011100 "
b111100001 #
b101 !
#436001
b1101 "
b1010001 #
b1000100 !
#438001
b111 "
b110100101 #
b10011110 !
#440001
b11110100 "
b110010101 #
b10100001 !
#442001
b10111101 "
b111100011 #
b100110 !
#444001
b10001000 "
b111010001 #
b1001001 !
#446001
b101011 "
b110111101 #
b10010010 !
#448001
b1110100 "
b0 #
b10001100 !
#450001
b11110001 "
b110001010 #
b10011001 !
#452001
b1110101 "
b11001010 #
b1010101 !
#454001
b100011 "
b101 #
b11100010 !
#456001
b10111110 "
b111110101 #
b110111 !
#458001
b11101011 "
b101111101 #
b10010010 !
#460001
b10011010 "
b100100000 #
b10000110 !
#462001
b10110110 "
b110011 #
b1111101 !
#464001
b10110010 "
b111101000 #
b110110 !
#466001
b10011000 "
b101101011 #
b11010011 !
#468001
b10010011 "
b101101000 #
b11010101 !
#470001
b10110100 "
b1110 #
b1011010 !
#472001
b11100011 "
b11100 #
b111001 !
#474001
b111000 "
b110111 #
b11111111 !
#476001
b10000101 "
b110110100 #
b101111 !
#478001
b10000110 "
b101000111 #
b11000001 !
#480001
b10101001 "
b110100100 #
b11111011 !
#482001
b1101110 "
b1101 #
b10011111 !
#484001
b11000110 "
b101111 #
b1101001 !
#486001
b1001010 "
b111001101 #
b10000011 !
#488001
b1101111 "
b101011 #
b10111100 !
#490001
b10010100 "
b100101110 #
b10011010 !
#492001
b101110 "
b10010111 #
b1101001 !
#494001
b101111 #
b11000110 "
#496001
b10000000 "
b101110010 #
b11110010 !
#498001
b11011001 "
b110010101 #
b10111100 !
#500001
b11101001 "
b110001000 #
b10011111 !
#502001
b11000001 "
b100000 #
b1011111 !
#504001
b11001101 "
b111100100 #
b10111 !
#506001
b10010101 "
b110010100 #
b11111111 !
#508001
b1110 "
b10000100 #
b1110110 !
#510001
b11000000 "
b111000000 #
b0 !
#512001
b11101000 "
b110000100 #
b10011100 !
#514001
b10010000 "
b101010100 #
b11000100 !
#516001
b11111111 "
b1110011 #
b1110100 !
#518001
b1101101 "
b10011100 #
b101111 !
#520001
b1011110 "
b1100111 #
b1001 !
#522001
b11110010 "
b111111010 #
b1000 !
#524001
b10000 "
b111011101 #
b11001101 !
#526001
b1100010 "
b111100110 #
b10000100 !
#528001
b101100 "
b111010010 #
b10100110 !
#530001
b101110 "
b111011111 #
b10110001 !
#532001
b11101111 "
b1101010 #
b1111011 !
#534001
b1101111 "
b11100010 #
b1110011 !
#536001
b1110110 "
b1101 #
b10010111 !
#538001
b11100000 "
b10000 #
b110000 !
#540001
b1010110 "
b10 #
b10101100 !
#542001
b11110 "
b110110 #
b11000 !
#544001
b11101000 "
b1010101 #
b1101101 !
#546001
b11011 "
b1011011 #
b1000000 !
#548001
b11001001 "
b101100001 #
b10011000 !
#550001
b10111000 "
b100 #
b1001100 !
#552001
b10001001 "
b101001100 #
b11000011 !
#554001
b101000 "
b111010011 #
b10101011 !
#556001
b10001101 "
b101110001 #
b11100100 !
#558001
b1100100 "
b111100111 #
b10000011 !
#560001
b11000000 "
b111100100 #
b100100 !
#562001
b10111111 "
b110000101 #
b11000110 !
#564001
b1011110 "
b11001 #
b10111011 !
#566001
b10001011 "
b111110110 #
b1101011 !
#568001
b101010 "
b110110011 #
b10001001 !
#570001
b11100110 "
b1001100 #
b1100110 !
#572001
b1110011 "
b11010111 #
b1100100 !
#574001
b10000011 "
b101100000 #
b11011101 !
#576001
b10110010 "
b100000 #
b1101110 !
#578001
b110 "
b111010000 #
b11001010 !
#580001
b110011 "
b11100 #
b11101001 !
#582001
b11100011 "
b111000000 #
b11011101 !
#584001
b11110001 "
b1011100 #
b1101011 !
#586001
b1000011 "
b111100001 #
b10011110 !
#588001
b111100 "
b10 #
b11000110 !
#590001
b1001101 "
b10010010 #
b1000101 !
#592001
b1110010 "
b10010000 #
b11110 !
#594001
b10011010 "
b101011100 #
b11000010 !
#596001
b1010001 "
b1000011 #
b11110010 !
#598001
b100001 "
b1111111 #
b1011110 !
#600001
b1101010 "
b1011101 #
b11110011 !
#602001
b1010100 "
b1001111 #
b11111011 !
#604001
b101111 "
b111000010 #
b10010011 !
#606001
b1100000 "
b10110011 #
b1010011 !
#608001
b11011010 "
b101101000 #
b10001110 !
#610001
b1010011 "
b101000 #
b11010101 !
#612001
b11011000 "
b1001110 #
b1110110 !
#614001
b1111011 "
b1011011 #
b11100000 !
#616001
b1001 "
b111000010 #
b10111001 !
#618001
b1110000 "
b101111 #
b10111111 !
#620001
b11010100 "
b110001 #
b1011101 !
#622001
b11101100 "
b111000111 #
b11011011 !
#624001
b1001111 "
b111011001 #
b10001010 !
#626001
b1010101 "
b10111111 #
b1101010 !
#628001
b11010101 "
b111111101 #
b101000 !
#630001
b10010111 "
b111001100 #
b110101 !
#632001
b10110011 "
b110110101 #
b10 !
#634001
b11110010 "
b111100100 #
b11110010 !
#636001
b1110 "
b111001 #
b101011 !
#638001
b11110101 "
b10000 #
b11011 !
#640001
b10101011 "
b11101 #
b1110010 !
#642001
b101101 "
b10011000 #
b1101011 !
#644001
b11000100 "
b111010101 #
b10001 !
#646001
b11100110 "
b1010111 #
b1110001 !
#648001
b1000111 "
b111100100 #
b10011101 !
#650001
b11000000 "
b110100010 #
b11100010 !
#652001
b1101101 "
b10000 #
b10100011 !
#654001
b110101 "
b100011 #
b11101110 !
#656001
b100110 "
b1010101 #
b101111 !
#658001
b1000110 "
b1111011 #
b110101 !
#660001
b100000 "
b1110100 #
b1010100 !
#662001
b11000011 "
b110101111 #
b11101100 !
#664001
b11100 "
b111010 #
b11110 !
#666001
b10111100 "
b101010001 #
b10010101 !
#668001
b11100101 "
b101110111 #
b10010010 !
#670001
b11000001 "
b111010110 #
b10101 !
#672001
b11010 "
b100000 #
b110 !
#674001
b10100 "
b110100110 #
b10010010 !
#676001
b1000000 "
b1011111 #
b11111 !
#678001
b11011000 "
b1001101 #
b1110101 !
#680001
b101111 "
b1111001 #
b1001010 !
#682001
b101 "
b110000110 #
b10000001 !
#684001
b10010010 "
b101010000 #
b10111110 !
#686001
b10000110 "
b110011100 #
b10110 !
#688001
b10110000 "
b101011100 #
b10101100 !
#690001
b1011010 "
b1100111 #
b1101 !
#692001
b10101 "
b101010 #
b10101 !
#694001
b101000 "
b111001101 #
b10100101 !
#696001
b10011100 "
b111111001 #
b1011101 !
#698001
b1000101 "
b1111100 #
b110111 !
#700001
b1010110 "
b10001011 #
b110101 !
#702001
b11000 "
b10000110 #
b1101110 !
#704001
b1001 "
b111010111 #
b11001110 !
#706001
b11101110 "
b1100010 #
b1110100 !
#708001
b1001110 "
b10011000 #
b1001010 !
#710001
b10001101 "
b110010111 #
b1010 !
#712001
b111010 "
b111111001 #
b10111111 !
#714001
b1111 "
b110100111 #
b10011000 !
#716001
b1100 "
b111000001 #
b10110101 !
#718001
b11100001 "
b111010100 #
b11110011 !
#720001
b1110000 "
b11 #
b10010011 !
#722001
b1101001 "
b10001111 #
b100110 !
#724001
b10000100 "
b100010110 #
b10010010 !
#726001
b10101000 "
b111000001 #
b11001 !
#728001
b11101000 "
b111101110 #
b110 !
#730001
b10101101 "
b111110000 #
b1000011 !
#732001
b110010 "
b10100111 #
b1110101 !
#734001
b101 "
b10011 #
b1110 !
#736001
b1100011 "
b10000101 #
b100010 !
#738001
b11 "
b110101110 #
b10101011 !
#740001
b11110110 "
b111001001 #
b11010011 !
#742001
b11110000 "
b0 #
b10000 !
#744001
b11010000 "
b111111001 #
b101001 !
#746001
b1101111 #
b1000110 "
#748001
b1010 "
b10110 #
b1100 !
#750001
b1110011 "
b11111 #
b10101100 !
#752001
b101101 "
b11110 #
b11110001 !
#754001
b1000110 "
b10010101 #
b1001111 !
#756001
b11000001 "
b111011000 #
b10111 !
#758001
b11011010 "
b110101 #
b1011011 !
#760001
b10011110 "
b101100100 #
b11000110 !
#762001
b1101011 "
b1110101 #
b1010 !
#764001
b10011010 "
b10110 #
b1111100 !
#766001
b11111000 "
b111111110 #
b110 !
#768001
b10010110 "
b111000011 #
b101101 !
#770001
b10001110 "
b110111100 #
b101110 !
#772001
b10101110 "
b110001011 #
b11011101 !
#774001
b1011 "
b111011100 #
b11010001 !
#776001
b10000100 "
b101100000 #
b11011100 !
#778001
b1011100 "
b11110 #
b11000010 !
#780001
b11010110 "
b1010101 #
b1111111 !
#782001
b11111010 "
b1100001 #
b1100111 !
#784001
b1000000 "
b1001 #
b11001001 !
#786001
b10011001 "
b101011000 #
b10111111 !
#788001
b110110 "
b11011 #
b11100101 !
#790001
b1010001 "
b10100 #
b11000011 !
#792001
b10100000 "
b111010101 #
b110101 !
#794001
b10000010 "
b111100100 #
b1100010 !
#796001
b11101000 "
b110101000 #
b11000000 !
#798001
b110 "
b111111111 #
b11111001 !
#800001
b1 "
b110011100 #
b10011011 !
#802001
b1011000 "
b1001010 #
b11110010 !
#804001
b11001001 "
b100001 #
b1011000 !
#806001
b110 "
b100101 #
b11111 !
#808001
b10011010 "
b110101011 #
b10001 !
#810001
b11011101 "
b111001110 #
b11110001 !
#812001
b11100100 "
b111010100 #
b11110000 !
#814001
b10000011 "
b101001000 #
b11000101 !
#816001
b1111001 "
b10001110 #
b10101 !
#818001
b11001110 "
b110100001 #
b11010011 !
#820001
b101 "
b110111 #
b110010 !
#822001
b1100010 "
b1110000 #
b1110 !
#824001
b11111111 "
b111000110 #
b11000111 !
#826001
b1111111 "
b110011 #
b10110100 !
#828001
b1000011 "
b111001110 #
b10001011 !
#830001
b1111111 "
b11110100 #
b1110101 !
#832001
b1000101 "
b1000110 #
b1 !
#834001
b11011011 "
b110000 #
b1010101 !
#836001
b11100000 "
b100101 #
b1000101 !
#838001
b11011110 "
b110100000 #
b11000010 !
#840001
b101000 "
b110101100 #
b10000100 !
#842001
b1010100 "
b110010 #
b11011110 !
#844001
b101010 "
b111101100 #
b11000010 !
#846001
b1110010 "
b101011 #
b10111001 !
#848001
b11011000 "
b101111101 #
b10100101 !
#850001
b1001100 "
b11100 #
b11010000 !
#852001
b10011000 "
b111111001 #
b1100001 !
#854001
b10101101 "
b101101010 #
b10111101 !
#856001
b1001 "
b110111010 #
b10110001 !
#858001
b1000010 "
b111000010 #
b10000000 !
#860001
b11011011 "
b111101110 #
b10011 !
#862001
b1011011 "
b1010 #
b10101111 !
#864001
b10000 "
b11000 #
b1000 !
#866001
b10010111 "
b110101110 #
b10111 !
#868001
b10110111 "
b101001010 #
b10010011 !
#870001
b11101110 "
b110101001 #
b10111011 !
#872001
b10101101 "
b110111001 #
b1100 !
#874001
b10101000 "
b110010101 #
b11101101 !
#876001
b10111010 "
b1111 #
b1010101 !
#878001
b1001000 "
b1100010 #
b11010 !
#880001
b1000111 "
b10011010 #
b1010011 !
#882001
b111111 "
b111110001 #
b10110010 !
#884001
b1101010 "
b1100000 #
b11110110 !
#886001
b10000101 "
b111000111 #
b1000010 !
#888001
b11111000 "
b1000000 #
b1001000 !
#890001
b11011110 "
b11010 #
b111100 !
#892001
b1 "
b100111 #
b100110 !
#894001
b100111 "
b110 #
b11011111 !
#896001
b10111000 "
b110111110 #
b110 !
#898001
b1101111 "
b111110010 #
b10000011 !
#900001
b10101000 "
b111001101 #
b100101 !
#902001
b1011010 "
b10000100 #
b101010 !
#904001
b10100100 "
b111000111 #
b100011 !
#906001
b1010111 "
b1110111 #
b100000 !
#908001
b1010011 "
b100111 #
b11010100 !
#910001
b11101110 "
b0 #
b10010 !
#912001
b10010111 "
b110011011 #
b100 !
#914001
b11101101 "
b111101001 #
b11111100 !
#916001
b1010101 "
b10100000 #
b1001011 !
#918001
b101110 "
b0 #
b11010010 !
#920001
b1111011 "
b10010111 #
b11100 !
#922001
b11110010 "
b1000010 #
b1010000 !
#924001
b1101010 "
b10111 #
b10101101 !
#926001
b10000010 "
b100010001 #
b10001111 !
#928001
b1010001 "
b10011101 #
b1001100 !
#930001
b1001101 "
b11001000 #
b1111011 !
#932001
b11011110 "
b111110111 #
b11001 !
#934001
b1101 "
b111010100 #
b11000111 !
#936001
b10110110 "
b101111000 #
b11000010 !
#938001
b1110000 "
b1011110 #
b11101110 !
#940001
b1011101 "
b11010110 #
b1111001 !
#942001
b110100 "
b111000101 #
b10010001 !
#944001
b10011110 "
b110101010 #
b1100 !
#946001
b10110011 "
b10101 #
b1100010 !
#948001
b1101001 "
b101010 #
b11000001 !
#950001
b1 "
b111101011 #
b11101010 !
#952001
b110010 "
b1100100 #
b110010 !
#954001
b101111 "
b111101011 #
b10111100 !
#956001
b11000001 "
b101011 #
b1101010 !
#958001
b10111001 "
b110110001 #
b11111000 !
#960001
b11101111 "
b110110001 #
b11000010 !
#962001
b111111000 #
b1001 !
#964001
b11011 "
b111000111 #
b10101100 !
#966001
b10000111 "
b111010111 #
b1010000 !
#968001
b1101110 "
b11100010 #
b1110100 !
#970001
b10 "
b110000100 #
b10000010 !
#972001
b1000011 "
b111111001 #
b10110110 !
#974001
b11100001 "
b1010111 #
b1110110 !
#976001
b11010000 "
b10000 #
b1000000 !
#978001
b11000001 "
b110001100 #
b11001011 !
#980001
b1101100 "
b1110000 #
b100 !
#982001
b11100000 "
b110001011 #
b10101011 !
#984001
b10001110 "
b100100000 #
b10010010 !
#986001
b101101 "
b1001110 #
b100001 !
#988001
b10001111 "
b111010110 #
b1000111 !
#990001
b10111110 "
b110101011 #
b11101101 !
#992001
b11110100 "
b1001101 #
b1011001 !
#994001
b10000010 "
b101101100 #
b11101010 !
#996001
b1010101 "
b1001101 #
b11111000 !
#998001
b1110001 "
b11011 #
b10101010 !
#1000001
b10001000 "
b100001110 #
b10000110 !
#1002001
b10000100 "
b100111000 #
b10110100 !
#1004001
b10100110 "
b111010000 #
b101010 !
#1006001
b11010101 "
b10110 #
b1000001 !
#1008001
b11111110 "
b110011011 #
b10011101 !
#1010001
b110011 "
b1011011 #
b101000 !
#1012001
b11001011 "
b101010100 #
b10001001 !
#1014001
b11010010 "
b111111100 #
b101010 !
#1016001
b1111 "
b110100111 #
b10011000 !
#1018001
b111001 "
b11101 #
b11100100 !
#1020001
b10000111 "
b110000111 #
b0 !
#1022001
b1000110 "
b1101011 #
b100101 !
#1024001
b1100 "
b1011010 #
b1001110 !
#1026001
b1111 "
b1000001 #
b110010 !
#1028001
b1010001 "
b10011101 #
b1001100 !
#1030001
b10000000 "
b111111010 #
b1111010 !
#1032001
b10100011 "
b100110100 #
b10010001 !
#1034001
b11000100 "
b110010110 #
b11010010 !
#1036001
b11111100 "
b1111010 #
b1111110 !
#1038001
b1001010 "
b1011100 #
b10010 !
#1040001
b10111000 "
b101101110 #
b10110110 !
#1042001
b10111101 "
b101111 #
b1110010 !
#1044001
b1100101 "
b10100011 #
b111110 !
#1046001
b11010110 "
b111111011 #
b100101 !
#1048001
b11010100 "
b110011011 #
b11000111 !
#1050001
b1010 "
b110011010 #
b10010000 !
#1052001
b1 "
b10 #
b1 !
#1054001
b101000 "
b1110101 #
b1001101 !
#1056001
b1001101 "
b1011100 #
b1111 !
#1058001
b10011001 "
b1110 #
b1110101 !
#1060001
b11000110 "
b101110110 #
b10110000 !
#1062001
b11101101 "
b111011101 #
b11110000 !
#1064001
b1111 "
b111110111 #
b11101000 !
#1066001
b1110011 "
b100010 #
b10101111 !
#1068001
b111101 "
b1111 #
b11010010 !
#1070001
b11010001 "
b101000 #
b1010111 !
#1072001
b10100000 "
b101010011 #
b10110011 !
#1074001
b1110001 "
b10011111 #
b101110 !
#1076001
b1011000 "
b111101 #
b11100101 !
#1078001
b10000010 "
b111101110 #
b1101100 !
#1080001
b11100101 "
b1001010 #
b1100101 !
#1082001
b10000010 "
b111101010 #
b1101000 !
#1084001
b10101111 "
b10101 #
b1100110 !
#1086001
b1000001 "
b11111 #
b11011110 !
#1088001
b101000 "
b10000111 #
b1011111 !
#1090001
b1100001 "
b10011110 #
b111101 !
#1092001
b110001 "
b10111 #
b11100110 !
#1094001
b11011010 "
b11110 #
b1000100 !
#1096001
b1110001 "
b110110 #
b11000101 !
#1098001
b11000111 "
b1000001 #
b1111010 !
#1100001
b11001110 "
b100111 #
b1011001 !
#1102001
b10101110 "
b111111100 #
b1001110 !
#1104001
b11100111 "
b101110111 #
b10010000 !
#1106001
b11000010 "
b101001 #
b1100111 !
#1108001
b1000010 "
b111000 #
b11110110 !
#1110001
b1101101 "
b10010 #
b10100101 !
#1112001
b101100 "
b10101001 #
b1111101 !
#1114001
b1011110 "
b1001010 #
b11101100 !
#1116001
b11101001 "
b1001001 #
b1100000 !
#1118001
b1101 "
b111000111 #
b10111010 !
#1120001
b110111 "
b1001 #
b11010010 !
#1122001
b11001000 "
b111101011 #
b100011 !
#1124001
b11110101 "
b111001100 #
b11010111 !
#1126001
b10111110 "
b110101111 #
b11110001 !
#1128001
b11001001 "
b111000110 #
b11111101 !
#1130001
b110010 "
b1100110 #
b110100 !
#1132001
b10011001 "
b100011011 #
b10000010 !
#1134001
b10111010 "
b101100110 #
b10101100 !
#1136001
b10001110 "
b110011101 #
b1111 !
#1138001
b1010 "
b111011110 #
b11010100 !
#1140001
b1100000 "
b111000 #
b11011000 !
#1142001
b1001000 "
b110 #
b10111110 !
#1144001
b1111101 "
b10100111 #
b101010 !
#1146001
b11010001 "
b110001110 #
b10111101 !
#1148001
b110101 "
b10001000 #
b1010011 !
#1150001
b11110101 "
b1001001 #
b1010100 !
#1152001
b10100110 "
b100101000 #
b10000010 !
#1154001
b11111100 "
b101010 #
b101110 !
#1156001
b101011 "
b1111000 #
b1001101 !
#1158001
b11001110 "
b10101 #
b1000111 !
#1160001
b11101 "
b10011011 #
b1111110 !
#1162001
b10011110 "
b110011011 #
b11111101 !
#1164001
b11100111 "
b111010101 #
b11101110 !
#1166001
b11111000 "
b101111000 #
b10000000 !
#1168001
b11010011 "
b111110001 #
b11110 !
#1170001
b100001 "
b110110110 #
b10010101 !
#1172001
b10001100 "
b110010111 #
b1011 !
#1174001
b11000001 "
b111110111 #
b110110 !
#1176001
b101101 "
b111000000 #
b10010011 !
#1178001
b11001100 "
b110010001 #
b11000101 !
#1180001
b10110001 "
b101111101 #
b11001100 !
#1182001
b11010110 "
b110111 #
b1100001 !
#1184001
b11010 "
b110110001 #
b10010111 !
#1186001
b11101011 "
b110000110 #
b10011011 !
#1188001
b1010000 "
b111110111 #
b10100111 !
#1190001
b11010000 "
b101100000 #
b10010000 !
#1192001
b110111 "
b10001011 #
b1010100 !
#1194001
b1110000 "
b1001111 #
b11011111 !
#1196001
b10101100 "
b110000011 #
b11010111 !
#1198001
b1110101 "
b10100 #
b10011111 !
#1200001
b11001111 "
b101110000 #
b10100001 !
#1202001
b10110000 "
b101100110 #
b10110110 !
#1204001
b100111 "
b111010100 #
b10101101 !
#1206001
b101101 "
b111010010 #
b10100101 !
#1208001
b11011111 "
b111010110 #
b11110111 !
#1210001
b10001000 "
b100100111 #
b10011111 !
