alu.v
module alu (
    input  [7:0]  a,
    input  [7:0]  b,
    input  [1:0]  op,        // 00=add, 01=sub, 10=mul, 11=div
    output reg [15:0] result,    // wide enough to hold the largest case (multiply)
    output reg [7:0]  remainder, // only meaningful for divide
    output reg div_by_zero
);

    localparam ADD = 2'b00;
    localparam SUB = 2'b01;
    localparam MUL = 2'b10;
    localparam DIV = 2'b11;

    always @(*) begin
        // Defaults every cycle to avoid inferred latches
        result      = 16'd0;
        remainder   = 8'd0;
        div_by_zero = 1'b0;

        case (op)
            ADD: result = {7'd0, a} + {7'd0, b};       // 9-bit-equivalent sum, zero-extended
            SUB: result = {{8{1'b0}}, a} - {{8{1'b0}}, b}; // treated as unsigned wraparound; see note below
            MUL: result = a * b;                        // full 16-bit product
            DIV: begin
                if (b == 0) begin
                    div_by_zero = 1'b1;
                    result      = 16'd0;
                    remainder   = 8'd0;
                end else begin
                    result    = {8'd0, a / b};  // quotient in lower 8 bits
                    remainder = a % b;
                end
            end
            default: result = 16'd0;
        endcase
    end

    initial begin
        $dumpfile("alu.vcd");
        $dumpvars(0, alu);
    end

endmodule

alu.vcd
$date
	Thu Aug 20 16:37:59 2026
$end
$version
	Icarus Verilog
$end
$timescale
	1ps
$end
$scope module alu $end
$var wire 8 ! a [7:0] $end
$var wire 8 " b [7:0] $end
$var wire 2 # op [1:0] $end
$var parameter 2 $ ADD $end
$var parameter 2 % DIV $end
$var parameter 2 & MUL $end
$var parameter 2 ' SUB $end
$var reg 1 ( div_by_zero $end
$var reg 8 ) remainder [7:0] $end
$var reg 16 * result [15:0] $end
$upscope $end
$enddefinitions $end
$comment Show the parameter values. $end
$dumpall
b1 '
b10 &
b11 %
b0 $
$end
#0
$dumpvars
b0 *
b0 )
0(
b0 #
b0 "
b0 !
$end
#2000
b111111110 *
b11111111 "
b11111111 !
#4000
b10010110 *
b110010 "
b1100100 !
#6000
b10 *
b1 "
b1 !
#8001
b110010 *
b1 #
b110010 "
b1100100 !
#10001
b0 *
b0 "
b0 !
#12001
b11111111 *
b11111111 !
#14001
b1111111111001110 *
b1100100 "
b110010 !
#16002
b0 *
b10 #
b0 "
b0 !
#18002
b1111111000000001 *
b11111111 "
b11111111 !
#20002
b100000000 *
b10000 "
b10000 !
#22002
b11001000 *
b11001000 "
b1 !
#24003
b101 *
b11 #
b10 "
b1010 !
#26003
b11111111 *
b1 "
b11111111 !
#28003
b1 )
b10 *
b11 "
b111 !
#30003
b0 )
b0 *
b101 "
b0 !
#32004
1(
b0 "
b101010 !
#34005
b11010001010 *
0(
b10 #
b10010 "
b1011101 !
#36005
b110101 )
b1 *
b11 #
b10111101 "
b11110010 !
#38005
b0 )
b1111111111110100 *
b1 #
b10101 "
b1001 !
#40005
b100111111 *
b0 #
b11010101 "
b1101010 !
#42005
b101010000 *
b10101100 "
b10100100 !
#44005
b11010010 *
b10111000 "
b11010 !
#46005
b10110110 *
b1100010 "
b1010100 !
#48005
b110010101100011 *
b10 #
b10110011 "
b10010001 !
#50005
b100 *
b1 #
b10110 "
b11010 !
#52005
b1111111111000111 *
b10001110 "
b1010101 !
#54005
b10011110 *
b100101 "
b11000011 !
#56005
b110000 *
b10101 "
b1000101 !
#58005
b1111111101110011 *
b11100100 "
b1010111 !
#60005
b11110111 *
b0 #
b100001 "
b11010110 !
#62005
b111111111111 *
b10 #
b11000011 "
b10101 !
#64005
b11 )
b0 *
b11 #
b1011111 "
b11 !
#66005
b1101011 )
b11110101 "
b1101011 !
#68005
b11100110 *
b0 )
b0 #
b11011101 "
b1001 !
#70005
b111 )
b100 *
b11 #
b111010 "
b11101111 !
#72005
b111010 )
b0 *
b111111 "
b111010 !
#74005
b10011011 *
b0 )
b1 #
b10111 "
b10110010 !
#76005
b1111000 *
b10000101 "
b11111101 !
#78005
b10100 )
b10 *
b11 #
b110000 "
b1110100 !
#80005
b0 )
b10101110 *
b1 #
b1001001 "
b11110111 !
#82005
b1111111110101101 *
b1011100 "
b1001 !
#84005
b1011000 *
b10001010 "
b11100010 !
#86005
b101011110 *
b0 #
b1101010 "
b11110100 !
#88005
b10001111 *
b1 #
b100100 "
b10110011 !
#90005
b1101010010000 *
b10 #
b1100100 "
b1000100 !
#92005
b11010011 *
b1 #
b100110 "
b11111001 !
#94005
b100011111 *
b0 #
b10101100 "
b1110011 !
#96005
b10000 )
b1 *
b11 #
b110000 "
b1000000 !
#98005
b0 )
b1001100 *
b1 #
b10101101 "
b11111001 !
#100005
b110100 *
b11111 "
b1010011 !
#102005
b110 )
b1 *
b11 #
b10000000 "
b10000110 !
#104005
b10110 )
b1000 *
b11010 "
b11100110 !
#106005
b0 )
b101100101 *
b0 #
b11001111 "
b10010110 !
#108005
b10111011000 *
b10 #
b10111011 "
b1000 !
#110005
b1000111 *
b1 #
b100100 "
b1101011 !
#112005
b1011111 *
b10110 "
b1110101 !
#114005
b10000111110100 *
b10 #
b1101010 "
b1010010 !
#116005
b101011100000 *
b11101 "
b1100000 !
#118005
b10010 )
b10 *
b11 #
b111100 "
b10001010 !
#120005
b0 )
b1111111111101100 *
b1 #
b10101011 "
b10010111 !
#122005
b111011111110000 *
b10 #
b10011000 "
b11001010 !
#124005
b1010010011001010 *
b11101101 "
b10110010 !
#126005
b100111110 *
b0 #
b11010011 "
b1101011 !
#128005
b1101011100010 *
b10 #
b1101111 "
b111110 !
#130005
b10010000011110 *
b11001001 "
b101110 !
#132005
b1111110111000 *
b100011 "
b11101000 !
#134005
b11100110101 *
b101001 "
b101101 !
#136005
b101110100 *
b0 #
b11001010 "
b10101010 !
#138005
b100000 )
b0 *
b11 #
b11101110 "
b100000 !
#140005
b100010110011 *
b0 )
b10 #
b10001 "
b10000011 !
#142005
b111011 )
b1 *
b11 #
b10010101 "
b11010000 !
#144005
b0 )
b1111111110001100 *
b1 #
b11010110 "
b1100010 !
#146005
b101011010000100 *
b10 #
b1100010 "
b11100010 !
#148005
b10011 )
b100 *
b11 #
b11101 "
b10000111 !
#150005
b101100 )
b1 *
b1110100 "
b10100000 !
#152005
b0 )
b111011000110010 *
b10 #
b1111011 "
b11110110 !
#154005
b100111001 *
b0 #
b10111001 "
b10000000 !
#156005
b1101110 *
b1 #
b1001011 "
b10111001 !
#158005
b1110110000 *
b10 #
b11101100 "
b100 !
#160005
b10100011 *
b1 #
b101 "
b10101000 !
#162005
b11001 )
b0 *
b11 #
b1110111 "
b11001 !
#164005
b10010111 )
b10111110 "
b10010111 !
#166005
b1 *
b10101 )
b1010110 "
b1101011 !
#168005
b100100 )
b0 *
b11111110 "
b100100 !
#170005
b1 *
b1011 )
b10011101 "
b10101000 !
#172005
b1000 )
b0 *
b11000110 "
b1000 !
#174005
b101010001 *
b0 )
b0 #
b10001011 "
b11000110 !
#176005
b11100011 *
b11011110 "
b101 !
#178005
b101000111 *
b1001100 "
b11111011 !
#180005
b1001011111100000 *
b10 #
b10110100 "
b11011000 !
#182005
b100001101 *
b0 #
b101100 "
b11100001 !
#184005
b101001110 *
b10001111 "
b10111111 !
#186005
b111010 )
b1 *
b11 #
b1100101 "
b10011111 !
#188005
b1010 )
b1101 *
b1011 "
b10011001 !
#190005
b0 )
b1010010 *
b0 #
b10011 "
b111111 !
#192005
b1011100111000111 *
b10 #
b11111001 "
b10111111 !
#194005
b100000000 *
b0 #
b11000100 "
b111100 !
#196005
b100101011 *
b10001010 "
b10100001 !
#198005
b100010 *
b1 #
b11010001 "
b11110011 !
#200005
b101110011 *
b0 #
b10111011 "
b10111000 !
#202005
b10110100 )
b0 *
b11 #
b11000101 "
b10110100 !
#204005
b1010100000000010 *
b0 )
b10 #
b10111011 "
b11100110 !
#206005
b100101011 *
b0 #
b1110000 !
#208005
b1000110110011010 *
b10 #
b11111010 "
b10010001 !
#210005
b100000 )
b1 *
b11 #
b11000110 "
b11100110 !
#212005
b0 )
b11000001101001 *
b10 #
b10011001 "
b1010001 !
#214005
b10010011 )
b0 *
b11 #
b11110000 "
b10010011 !
#216005
b111 )
b10011011 "
b111 !
#218005
b1111111110101010 *
b0 )
b1 #
b10000001 "
b101011 !
#220005
b1000 )
b10000 *
b11 #
b1001 "
b10011000 !
#222005
b0 )
b1111000 *
b0 #
b10 "
b1110110 !
#224005
b1 *
b11 #
b1110110 "
#226005
b10110101 *
b0 #
b1011110 "
b1010111 !
#228005
b1111111111100110 *
b1 #
b1100001 "
b1000111 !
#230005
b1000100001000010 *
b10 #
b11010110 "
b10100011 !
#232005
b11000000 *
b0 #
b10100100 "
b11100 !
#234005
b1101011001110100 *
b10 #
b11110100 "
b11100001 !
#236005
b11001000 *
b0 #
b10010100 "
b110100 !
#238005
b11101110 *
b101 "
b11101001 !
#240005
b101101000000 *
b10 #
b1010000 "
b100100 !
#242005
b1111111110011110 *
b1 #
b1101000 "
b110 !
#244005
b1001101 *
b11101 "
b1101010 !
#246005
b1010101 *
b0 #
b1001111 "
b110 !
#248005
b110101101010101 *
b10 #
b11010101 "
b10000001 !
#250005
b1001101101011010 *
b11001101 "
b11000010 !
#252005
b110010111111001 *
b1110011 "
b11100011 !
#254005
b10010110 )
b0 *
b11 #
b10011001 "
b10010110 !
#256005
b11010111101000 *
b0 )
b10 #
b1011100 "
#258005
b101111 )
b0 *
b11 #
b1101110 "
b101111 !
#260005
b1000000 )
b11010101 "
b1000000 !
#262005
b1111011 *
b0 )
b0 #
b1 "
b1111010 !
#264005
b111010010000000 *
b10 #
b10000000 "
b11101001 !
#266005
b1101 )
b1 *
b11 #
b10100010 "
b10101111 !
#268005
b0 )
b1111111111010011 *
b1 #
b10111010 "
b10001101 !
#270005
b110111 *
b10111 "
b1001110 !
#272005
b10101001 *
b0 #
b101 "
b10100100 !
#274005
b1 *
b11 #
b10011101 "
b10011101 !
#276005
b101001 )
b10 *
b101011 "
b1111111 !
#278005
b0 )
b1000000011001010 *
b10 #
b11010010 "
b10011101 !
#280005
b101010 *
b1 #
b1001010 "
b1110100 !
#282005
b100111111011101 *
b10 #
b10010001 "
b10001101 !
#284005
b111001 )
b0 *
b11 #
b1111110 "
b111001 !
#286005
b101 *
b0 )
b1 #
b10110 "
b11011 !
#288005
b1111111110110110 *
b11010010 "
b10001000 !
#290005
b11 )
b11 *
b11 #
b1010010 "
b11111001 !
#292005
b0 )
b1110001 *
b1 #
b1001111 "
b11000000 !
#294005
b10010110 *
b0 #
b111 "
b10001111 !
#296005
b1100010100 *
b10 #
b11000101 "
b100 !
#298005
b1111111111101001 *
b1 #
b101010 "
b10011 !
#300005
b10011001 *
b110100 "
b11001101 !
#302005
b0 *
b11 #
b11010100 "
b0 !
#304005
b110010100 *
b0 #
b11100111 "
b10101101 !
#306005
b1111111111100111 *
b1 #
b10000100 "
b1101011 !
#308005
b100101101011111 *
b10 #
b1010101 "
b11100011 !
#310005
b11010 )
b0 *
b11 #
b1101001 "
b11010 !
#312005
b1100000 *
b0 )
b1 #
b1110000 "
b11010000 !
#314005
b11011101111000 *
b10 #
b10001110 "
b1100100 !
#316005
b11110110 *
b0 #
b11001011 "
b101011 !
#318005
b100000000 *
b1110111 "
b10001001 !
#320005
b10010011 )
b0 *
b11 #
b11011000 "
b10010011 !
#322005
b10100011101000 *
b0 )
b10 #
b1001101 "
b10001000 !
#324005
b100011110111000 *
b10110100 "
b1100110 !
#326005
b101000100 *
b0 #
b11011001 "
b1101011 !
#328005
b10011 *
b1 #
b11001 "
b101100 !
#330005
b1001100 *
b10001110 "
b11011010 !
#332005
b110001000000 *
b10 #
b1110000 "
b11100 !
#334005
b1010110101011001 *
b11000111 "
b11011111 !
#336005
b11101000 )
b0 *
b11 #
b11110100 "
b11101000 !
#338005
b1 *
b1011101 )
b10100000 "
b11111101 !
#340005
b1000110 )
b1 *
b10010101 "
b11011011 !
#342005
b0 )
b101 *
b11000 "
b1111000 !
#344005
b1000001010 *
b10 #
b11101 "
b10010 !
#346005
b100100110 *
b0 #
b10101001 "
b1111101 !
#348005
b11101 *
b1 #
b10110101 "
b11010010 !
#350005
b1111111111000010 *
b1000000 "
b10 !
#352005
b11000001 *
b0 #
b10100110 "
b11011 !
#354005
b11111 )
b0 *
b11 #
b10101010 "
b11111 !
#356005
b1111111111110101 *
b0 )
b1 #
b11110111 "
b11101100 !
#358005
b100000011 *
b0 #
b11001100 "
b110111 !
#360005
b1111000 )
b0 *
b11 #
b11110000 "
b1111000 !
#362005
b10 *
b1111 )
b10111 "
b111101 !
#364005
b0 )
b100110111101110 *
b10 #
b10010110 "
b10000101 !
#366005
b1111111111100011 *
b1 #
b1110110 "
b1011001 !
#368005
b110000011 *
b0 #
b10110111 "
b11001100 !
#370005
b11001011011100 *
b10 #
b1000110 "
b10111010 !
#372005
b10011 *
b1 #
b1111111 "
b10010010 !
#374005
b10011 )
b100 *
b11 #
b101100 "
b11000011 !
#376005
b10111111 )
b0 *
b11111010 "
b10111111 !
#378005
b1111111110100100 *
b0 )
b1 #
b11010010 "
b1110110 !
#380005
b101000001 *
b0 #
b11011001 "
b1101000 !
#382005
b100001110 *
b110100 "
b11011010 !
#384005
b1001010 )
b0 *
b11 #
b1010101 "
b1001010 !
#386005
b11110001 )
b11110010 "
b11110001 !
#388005
b1111111110011011 *
b0 )
b1 #
b10100101 "
b1000000 !
#390005
b100001010101000 *
b10 #
b1001000 "
b11101101 !
#392005
b100 )
b1 *
b11 #
b1101111 "
b1110011 !
#394005
b11 )
b10 *
b101001 "
b1010101 !
#396005
b0 )
b1101110 *
b1 #
b1001101 "
b10111011 !
#398005
b1001110 *
b0 #
b10000 "
b111110 !
#400005
b110010 )
b1 *
b11 #
b1101011 "
b10011101 !
#402005
b1111 )
b0 *
b10011100 "
b1111 !
#404005
b1000011010101 *
b0 )
b10 #
b11111 "
b10001011 !
#406005
b10101011 *
b1 #
b100100 "
b11001111 !
#408005
b11010000 *
b0 #
b10100110 "
b101010 !
#410005
b11110 )
b0 *
b11 #
b1000010 "
b11110 !
#412005
b10101010 *
b0 )
b1 #
b101110 "
b11011000 !
#414005
b11011100 *
b11000 "
b11110100 !
#416005
b1111111100111101 *
b11101111 "
b101100 !
#418005
b100010111 *
b0 #
b1011010 "
b10111101 !
#420005
b101010011010000 *
b10 #
b10111000 "
b1110110 !
#422005
b1111111110001000 *
b1 #
b10011110 "
b100110 !
#424005
b1000 )
b100 *
b11 #
b10011 "
b1010100 !
#426005
b1100011 )
b0 *
b11011010 "
b1100011 !
#428005
b100000101 *
b0 )
b0 #
b101001 "
b11011100 !
#430005
b11001000 *
b10000111 "
b1000001 !
#432005
b1101011101000 *
b10 #
b111000 "
b1111011 !
#434005
b10101110 )
b0 *
b11 #
b11101011 "
b10101110 !
#436005
b110011 )
b11100101 "
b110011 !
#438005
b1110111 *
b0 )
b1 #
b10110 "
b10001101 !
#440005
b10110001 )
b0 *
b11 #
b11101010 "
b10110001 !
#442005
b111011 *
b0 )
b1 #
b10101000 "
b11100011 !
#444005
b11011 *
b100100 "
b111111 !
#446005
b110100 *
b0 #
b10000 "
b100100 !
#448005
b110 )
b1 *
b11 #
b10001110 "
b10010100 !
#450005
b0 )
b100110001010011 *
b10 #
b10100111 "
b1110101 !
#452005
b10001111 )
b0 *
b11 #
b11001110 "
b10001111 !
#454005
b1011101 )
b10000111 "
b1011101 !
#456005
b1111111111110110 *
b0 )
b1 #
b1100010 "
b1011000 !
#458005
b1111111110000011 *
b10010110 "
b11001 !
#460005
b100011100 *
b0 #
b100000 "
b11111100 !
#462005
b10111000 )
b0 *
b11 #
b11110100 "
b10111000 !
#464005
b110010010 *
b0 )
b0 #
b11011110 "
b10110100 !
#466005
b110100010100110 *
b10 #
b1110010 "
b11101011 !
#468005
b1101111100100 *
b1110111 "
b111100 !
#470005
b10101 )
b0 *
b11 #
b10010011 "
b10101 !
#472005
b11101101 *
b0 )
b0 #
b11000 "
b11010101 !
#474005
b11 )
b1100 *
b11 #
b1000 "
b1100011 !
#476005
b0 )
b1111111110110001 *
b1 #
b1110000 "
b100001 !
#478005
b10011001110000 *
b10 #
b1010000 "
b1111011 !
#480005
b10011010 *
b1 #
b100010 "
b10111100 !
#482005
b11000010 *
b0 #
b1101110 "
b1010100 !
#484005
b101011101 *
b10100111 "
b10110110 !
#486005
b101010111001010 *
b10 #
b10011110 "
b10001011 !
#488005
b1111111111000001 *
b1 #
b10011000 "
b1011001 !
#490005
b1111111111101111 *
b111100 "
b101011 !
#492005
b110101 *
b10010100 "
b11001001 !
#494005
b100010101111011 *
b10 #
b10010011 "
b1111001 !
#496005
b100001 )
b1 *
b11 #
b10111011 "
b11011100 !
#498005
b0 )
b1000100111010000 *
b10 #
b10101000 "
b11010010 !
#500005
b100 )
b0 *
b11 #
b10010001 "
b100 !
#502005
b100000 *
b0 )
b0 #
b0 "
b100000 !
#504005
b100010100 *
b111010 "
b11011010 !
#506005
b11001111 *
b10110011 "
b11100 !
#508005
b1100000 *
b1011110 "
b10 !
#510005
b110011111100001 *
b10 #
b10000011 "
b11001011 !
#512005
b11001111 *
b0 #
b10001010 "
b1000101 !
#514005
b100111111100101 *
b10 #
b10110101 "
b1110001 !
#516005
b1010000000 *
b10100000 "
b100 !
#518005
b110110100 *
b0 #
b11101001 "
b11001011 !
#520005
b1010011111010 *
b10 #
b10110011 "
b11110 !
#522005
b101001011011000 *
b11110001 "
b1011000 !
#524005
b10110 )
b0 *
b11 #
b1100111 "
b10110 !
#526005
b1111111101111100 *
b0 )
b1 #
b10010111 "
b10011 !
#528005
b101111 *
b101100 "
b1011011 !
#530005
b11110001 *
b0 #
b100011 "
b11001110 !
#532005
b1010011 *
b1 #
b1110000 "
b11000011 !
#534005
b1111111111111001 *
b11111111 "
b11111000 !
#536005
b1111110101010 *
b10 #
b11000001 "
b101010 !
#538005
b101000000 *
b0 #
b1111111 "
b11000001 !
#540005
b1111111111110111 *
b1 #
b10001000 "
b1111111 !
#542005
b100000111 *
b0 #
b10001001 "
b1111110 !
#544005
b100001100110 *
b10 #
b11010111 "
b1010 !
#546005
b1000100000100010 *
b11001101 "
b10101010 !
#548005
b100011101 *
b0 #
b1110111 "
b10100110 !
#550005
b1000111 *
b1 #
b10110000 "
b11110111 !
#552005
b110100010 *
b0 #
b11100001 "
b11000001 !
#554005
b1000111 )
b0 *
b11 #
b11110101 "
b1000111 !
#556005
b11101001 *
b0 )
b0 #
b11001011 "
b11110 !
#558005
b1111111111010011 *
b1 #
b10111001 "
b10001100 !
#560005
b1101 )
b1000 *
b11 #
b11100 "
b11101101 !
#562005
b0 )
b1101001000000 *
b10 #
b1101001 "
b1000000 !
#564005
b111100001000001 *
b10000011 "
b11101011 !
#566005
b1111111100111100 *
b1 #
b11110001 "
b101101 !
#568005
b11011 *
b10 #
b1001 "
b11 !
#570005
b1111111101011011 *
b1 #
b11100000 "
b111011 !
#572005
b1111111111110011 *
b100101 "
b11000 !
#574005
b1111 )
b11 *
b11 #
b1001100 "
b11110011 !
#576005
b0 )
b11011011 *
b0 #
b1111 "
b11001100 !
#578005
b1100001 *
b1 #
b1111111 "
b11100000 !
#580005
b101000110 *
b0 #
b10111111 "
b10000111 !
#582005
b101000 )
b1 *
b11 #
b1100100 "
b10001100 !
#584005
b11 )
b101 *
b1010 "
b110101 !
#586005
b0 )
b1011011011000 *
b10 #
b100010 "
b10101100 !
#588005
b10101001 *
b0 #
b1001010 "
b1011111 !
#590005
b1011010 *
b11011 "
b111111 !
#592005
b10001000 )
b0 *
b11 #
b11011011 "
b10001000 !
#594005
b1111111111001011 *
b0 )
b1 #
b11000110 "
b10010001 !
#596005
b110111110 *
b0 #
b11000011 "
b11111011 !
#598005
b10101101 *
b1 #
b1100 "
b10111001 !
#600005
b100011011100000 *
b10 #
b11011000 "
b1010100 !
#602005
b100110110101 *
b1000111 "
b100011 !
#604005
b110110111111 *
b10011001 "
b10111 !
#606005
b10001 )
b1 *
b11 #
b111001 "
b1001010 !
#608005
b0 )
b1111111111110101 *
b1 #
b1110000 "
b1100101 !
#610005
b100100001 *
b0 #
b11010010 "
b1001111 !
#612005
b101000000 *
b11100110 "
b1011010 !
#614005
b1111111110010111 *
b1 #
b10101011 "
b1000010 !
#616005
b101001 *
b1001101 "
b1110110 !
#618005
b1111111101011110 *
b11000101 "
b100011 !
#620005
b101110000100000 *
b10 #
b10000110 "
b10110000 !
#622005
b1111111111110100 *
b1 #
b11100010 "
b11010110 !
#624005
b11101111 *
b0 #
b1001101 "
b10100010 !
#626005
b11010011010 *
b10 #
b10101001 "
b1010 !
#628005
b10100 )
b111 *
b11 #
b11001 "
b11000011 !
#630005
b0 )
b1010100 *
b1 #
b1110011 "
b11000111 !
#632005
b110 )
b1 *
b11 #
b11110101 "
b11111011 !
#634005
b0 )
b100001101100 *
b10 #
b10011010 "
b1110 !
#636005
b1111111110001010 *
b1 #
b11000100 "
b1001110 !
#638005
b10001 *
b1011000 "
b1101001 !
#640005
b10 *
b11 #
b11000 "
b110000 !
#642005
b1100010 *
b1 #
b10011000 "
b11111010 !
#644005
b110001100 *
b0 #
b11100010 "
b10101010 !
#646005
b110001100011 *
b10 #
b10101 "
b10010111 !
#648005
b10001010 *
b110 "
b10111 !
#650005
b1011 )
b10 *
b11 #
b1100 "
b100011 !
#652005
b0 )
b101000 *
b10 #
b101000 "
b1 !
#654005
b10100111 *
b0 #
b10001 "
b10010110 !
#656005
b101011 )
b0 *
b11 #
b11011011 "
b101011 !
#658005
b11101000100 *
b0 )
b10 #
b1111100 "
b1111 !
#660005
b10011000 *
b0 #
b1011111 "
b111001 !
#662005
b10010 )
b0 *
b11 #
b10101111 "
b10010 !
#664005
b1000000 )
b1111000 "
b1000000 !
#666005
b1011011001100001 *
b0 )
b10 #
b11000101 "
b11101101 !
#668005
b111000100 *
b0 #
b11111101 "
b11000111 !
#670005
b101111011010000 *
b10 #
b10100100 "
b10010100 !
#672005
b110111 *
b1 #
b1101110 "
b10100101 !
#674005
b10101 )
b1 *
b11 #
b1100011 "
b1111000 !
#676005
b10000101 )
b0 *
b11110110 "
b10000101 !
#678005
b11111011011001 *
b0 )
b10 #
b10101101 "
b1011101 !
#680005
b101100000 *
b0 #
b1111111 "
b11100001 !
#682005
b1111111111111011 *
b1 #
b10101010 "
b10100101 !
#684005
b110110 )
b0 *
b11 #
b10010100 "
b110110 !
#686005
b1000101 *
b0 )
b1 #
b1110001 "
b10110110 !
#688005
b100001110 *
b0 #
b10011111 "
b1101111 !
#690005
b101011011 *
b10001111 "
b11001100 !
#692005
b11 )
b0 *
b11 #
b10101010 "
b11 !
#694005
b10010100100000 *
b0 )
b10 #
b10000100 "
b1001000 !
#696005
b101111100 *
b0 #
b11011100 "
b10100000 !
#698005
b1 )
b1 *
b11 #
b110001 "
b110010 !
#700005
b0 )
b100101 *
b0 #
b11110 "
b111 !
#702005
b1111111111110011 *
b1 #
b1010011 "
b1000110 !
#704005
b1000 )
b100 *
b11 #
b10100 "
b1011000 !
#706005
b0 )
b11010001 *
b0 #
b10010011 "
b111110 !
#708005
b10011100 *
b111111 "
b1011101 !
#710005
b11001000 *
b1100001 "
b1100111 !
#712005
b10100 )
b101 *
b11 #
b101000 "
b11011100 !
#714005
b0 )
b0 *
b10 #
b11011100 "
b0 !
#716005
b1011000 *
b1 #
b11110 "
b1110110 !
#718005
b11001111 *
b0 #
b11 "
b11001100 !
#720005
b100101 *
b1 #
b1011101 "
b10000010 !
#722005
b1111111111001011 *
b10000001 "
b1001100 !
#724005
b1111111101110110 *
b10101001 "
b11111 !
#726005
b1000100100010000 *
b10 #
b10101100 "
b11001100 !
#728005
b11010000110 *
b1010 "
b10100111 !
#730005
b111100011 *
b10100001 "
b11 !
#732005
b1001101110100 *
b11111001 "
b10100 !
#734005
b1111111111100001 *
b1 #
b10111011 "
b10011100 !
#736005
b1010010110101011 *
b10 #
b11001001 "
b11010011 !
#738005
b1111111111101010 *
b1 #
b1001010 "
b110100 !
#740005
b11001110 )
b0 *
b11 #
b11010110 "
b11001110 !
#742005
b10001111000000 *
b0 )
b10 #
b101100 "
b11010000 !
#744005
b1001 )
b1001 *
b11 #
b10000 "
b10011001 !
#746005
b11010 )
b100 *
b110000 "
b11011010 !
#748005
b0 )
b1111111111001101 *
b1 #
b11111111 "
b11001100 !
#750005
b1111111111000110 *
b1010001 "
b10111 !
#752005
b11111 *
b10000011 "
b10100010 !
#754005
b1110000110111 *
b10 #
b11111 "
b11101001 !
#756005
b1110111 )
b0 *
b11 #
b11001100 "
b1110111 !
#758005
b100100001100010 *
b0 )
b10 #
b1010101 "
b11011010 !
#760005
b1010 )
b1 *
b11 #
b1110000 "
b1111010 !
#762005
b0 )
b1111111101110110 *
b1 #
b11110101 "
b1101011 !
#764005
b10010011011011 *
b10 #
b11111111 "
b100101 !
#766005
b100011001110000 *
b11000100 "
b1011100 !
#768005
b1111111110101100 *
b1 #
b10001010 "
b110110 !
#770005
b110101100101000 *
b10 #
b1101100 "
b11111110 !
#772005
b101111011100 *
b10111 "
b10000100 !
#774005
b1110100011010 *
b10010101 "
b110010 !
#776005
b1111111101110101 *
b1 #
b11111100 "
b1110001 !
#778005
b1010 )
b0 *
b11 #
b11010000 "
b1010 !
#780005
b111101 *
b0 )
b0 #
b0 "
b111101 !
#782005
b111101010 *
b11111010 "
b11110000 !
#784005
b10100110 *
b1 #
b1101 "
b10110011 !
#786005
b101010111 *
b0 #
b11101101 "
b1101010 !
#788005
b1011111101000000 *
b10 #
b11000000 "
b11111111 !
#790005
b1101111 *
b0 #
b101 "
b1101010 !
#792005
b1000 )
b10 *
b11 #
b1100010 "
b11001100 !
#794005
b0 )
b1100000011111 *
b10 #
b11110111 "
b11001 !
#796005
b1111111110111100 *
b1 #
b1011110 "
b11010 !
#798005
b100011 *
b10010110 "
b10111001 !
#800005
b1111111110111001 *
b10011000 "
b1010001 !
#802005
b1011010 *
b1100100 "
b10111110 !
#804005
b1000000 *
b10111010 "
b11111010 !
#806005
b10010101 *
b110100 "
b11001001 !
#808005
b101111 *
b1110000 "
b10011111 !
#810005
b1111111110011100 *
b10000101 "
b100001 !
#812005
b100011 )
b10 *
b11 #
b110101 "
b10001101 !
#814005
b0 )
b11001000 *
b0 #
b1000100 "
b10000100 !
#816005
b101111011 *
b10011111 "
b11011100 !
#818005
b1001100 )
b0 *
b11 #
b11110111 "
b1001100 !
#820005
b11101000 *
b0 )
b0 #
b11000101 "
b100011 !
#822005
b10111100 *
b10001010 "
b110010 !
#824005
b1001001 )
b0 *
b11 #
b10000001 "
b1001001 !
#826005
b100001001 *
b0 )
b0 #
b111110 "
b11001011 !
#828005
b110110100 *
b11101011 "
b11001001 !
#830005
b11101100 *
b1 #
b1011 "
b11110111 !
#832005
b111110010110 *
b10 #
b10000101 "
b11110 !
#834005
b1111111101101101 *
b1 #
b10101000 "
b10101 !
#836005
b10001111 *
b1011001 "
b11101000 !
#838005
b1110010001000 *
b10 #
b1011000 "
b1010011 !
#840005
b101101110 *
b0 #
b10111000 "
b10110110 !
#842005
b11101 *
b1 #
b10010101 "
b10110010 !
#844005
b1111111110111000 *
b11111110 "
b10110110 !
#846005
b110010 )
b0 *
b11 #
b1111011 "
b110010 !
#848005
b111100 )
b10110101 "
b111100 !
#850005
b1111 *
b0 )
b1 #
b1101100 "
b1111011 !
#852005
b1111111110111011 *
b10000000 "
b111011 !
#854005
b10100100 *
b1000111 "
b11101011 !
#856005
b10100 )
b0 *
b11 #
b10001101 "
b10100 !
#858005
b1010000001101000 *
b0 )
b10 #
b10101110 "
b11101100 !
#860005
b1111111111110010 *
b1 #
b10001001 "
b1111011 !
#862005
b100000 )
b0 *
b11 #
b1110010 "
b100000 !
#864005
b100011111 *
b0 )
b0 #
b1001110 "
b11010001 !
#866005
b101010 *
b1 #
b100100 "
b1001110 !
#868005
b1101001101101 *
b10 #
b100001 "
b11001101 !
#870005
b11000110 )
b0 *
b11 #
b11001000 "
b11000110 !
#872005
b111100011110010 *
b0 )
b10 #
b10001001 "
b11100010 !
#874005
b1100110101100 *
b110101 "
b1111100 !
#876005
b11010001 *
b0 #
b1101001 "
b1101000 !
#878005
b110 )
b111 *
b11 #
b100010 "
b11110100 !
#880005
b0 )
b10010001 *
b0 #
b1100110 "
b101011 !
#882005
b100010000 *
b10011100 "
b1110100 !
#884005
b100101010 *
b1011111 "
b11001011 !
#886005
b10000011 )
b0 *
b11 #
b11101110 "
b10000011 !
#888005
b1011 *
b0 )
b0 #
b1010 "
b1 !
#890005
b110101000 *
b10110100 "
b11110100 !
#892005
b1111011 *
b1 #
b10000000 "
b11111011 !
#894005
b1001001001001000 *
b10 #
b10010111 "
b11111000 !
#896005
b1111111110111001 *
b1 #
b10110010 "
b1101011 !
#898005
b10010 *
b11 #
b110 "
b1101100 !
#900005
b100000100 *
b0 #
b10000000 "
b10000100 !
#902005
b100111000 *
b1100110 "
b11010010 !
#904005
b1010110 *
b11000 "
b111110 !
#906005
b11011010010000 *
b10 #
b1001000 "
b11000010 !
#908005
b110101010010 *
b1101110 "
b11111 !
#910005
b1110111 *
b1 #
b10001000 "
b11111111 !
#912005
b1001001101101000 *
b10 #
b10110010 "
b11010100 !
#914005
b100101101011100 *
b11010100 "
b1011011 !
#916005
b10101110 )
b0 *
b11 #
b11011011 "
b10101110 !
#918005
b10011100 *
b0 )
b1 #
b101101 "
b11001001 !
#920005
b1010 )
b0 *
b11 #
b11001111 "
b1010 !
#922005
b1000110010100000 *
b0 )
b10 #
b10010110 "
b11110000 !
#924005
b100 )
b0 *
b11 #
b10111010 "
b100 !
#926005
b101110111100110 *
b0 )
b10 #
b1110111 "
b11001010 !
#928005
b101100100 *
b0 #
b11001000 "
b10011100 !
#930005
b10010001011011 *
b10 #
b101001 "
b11100011 !
#932005
b11010010 )
b0 *
b11 #
b11101011 "
b11010010 !
