Arithmetic/arith_unit.sv
module arith_unit #(
    parameter WIDTH = 4
)(
    input  wire signed [WIDTH-1:0] a,
    input  wire signed [WIDTH-1:0] b,
    input  wire [2:0] op,   // <-- OP is now an input
    output reg  signed [(2*WIDTH)-1:0] y
);

    always @(*) begin
        case (op)   // use input, not parameter
            3'b000: y = a + b;
            3'b001: y = a - b;
            3'b010: y = a * b;
            3'b011: y = (b != 0) ? a / b : 0;
            3'b100: y = (b != 0) ? a % b : 0;
            3'b101: y = a;
            3'b110: y = b;
            3'b111: y = 0;
            default: y = 0;
        endcase
    end

    initial begin
        $dumpfile("arith_unit.vcd");
        $dumpvars(0, arith_unit);
    end
endmodule

Arithmetic/arith_unit.vcd
$date
	Fri Aug 21 11:49:34 2026
$end
$version
	Icarus Verilog
$end
$timescale
	1ps
$end
$scope module arith_unit $end
$var wire 4 ! a [3:0] $end
$var wire 4 " b [3:0] $end
$var wire 3 # op [2:0] $end
$var parameter 32 $ WIDTH $end
$var reg 8 % y [7:0] $end
$upscope $end
$enddefinitions $end
$comment Show the parameter values. $end
$dumpall
b100 $
$end
#0
$dumpvars
b11110000 %
b0 #
b1000 "
b1000 !
$end
#1000
b11110001 %
b1001 "
#2000
b11110010 %
b1010 "
#3000
b11110011 %
b1011 "
#4000
b11110100 %
b1100 "
#5000
b11110101 %
b1101 "
#6000
b11110110 %
b1110 "
#7000
b11110111 %
b1111 "
#8000
b11111000 %
b0 "
#9000
b11111001 %
b1 "
#10000
b11111010 %
b10 "
#11000
b11111011 %
b11 "
#12000
b11111100 %
b100 "
#13000
b11111101 %
b101 "
#14000
b11111110 %
b110 "
#15000
b11111111 %
b111 "
#16000
b11110001 %
b1000 "
b1001 !
#17000
b11110010 %
b1001 "
#18000
b11110011 %
b1010 "
#19000
b11110100 %
b1011 "
#20000
b11110101 %
b1100 "
#21000
b11110110 %
b1101 "
#22000
b11110111 %
b1110 "
#23000
b11111000 %
b1111 "
#24000
b11111001 %
b0 "
#25000
b11111010 %
b1 "
#26000
b11111011 %
b10 "
#27000
b11111100 %
b11 "
#28000
b11111101 %
b100 "
#29000
b11111110 %
b101 "
#30000
b11111111 %
b110 "
#31000
b0 %
b111 "
#32000
b11110010 %
b1000 "
b1010 !
#33000
b11110011 %
b1001 "
#34000
b11110100 %
b1010 "
#35000
b11110101 %
b1011 "
#36000
b11110110 %
b1100 "
#37000
b11110111 %
b1101 "
#38000
b11111000 %
b1110 "
#39000
b11111001 %
b1111 "
#40000
b11111010 %
b0 "
#41000
b11111011 %
b1 "
#42000
b11111100 %
b10 "
#43000
b11111101 %
b11 "
#44000
b11111110 %
b100 "
#45000
b11111111 %
b101 "
#46000
b0 %
b110 "
#47000
b1 %
b111 "
#48000
b11110011 %
b1000 "
b1011 !
#49000
b11110100 %
b1001 "
#50000
b11110101 %
b1010 "
#51000
b11110110 %
b1011 "
#52000
b11110111 %
b1100 "
#53000
b11111000 %
b1101 "
#54000
b11111001 %
b1110 "
#55000
b11111010 %
b1111 "
#56000
b11111011 %
b0 "
#57000
b11111100 %
b1 "
#58000
b11111101 %
b10 "
#59000
b11111110 %
b11 "
#60000
b11111111 %
b100 "
#61000
b0 %
b101 "
#62000
b1 %
b110 "
#63000
b10 %
b111 "
#64000
b11110100 %
b1000 "
b1100 !
#65000
b11110101 %
b1001 "
#66000
b11110110 %
b1010 "
#67000
b11110111 %
b1011 "
#68000
b11111000 %
b1100 "
#69000
b11111001 %
b1101 "
#70000
b11111010 %
b1110 "
#71000
b11111011 %
b1111 "
#72000
b11111100 %
b0 "
#73000
b11111101 %
b1 "
#74000
b11111110 %
b10 "
#75000
b11111111 %
b11 "
#76000
b0 %
b100 "
#77000
b1 %
b101 "
#78000
b10 %
b110 "
#79000
b11 %
b111 "
#80000
b11110101 %
b1000 "
b1101 !
#81000
b11110110 %
b1001 "
#82000
b11110111 %
b1010 "
#83000
b11111000 %
b1011 "
#84000
b11111001 %
b1100 "
#85000
b11111010 %
b1101 "
#86000
b11111011 %
b1110 "
#87000
b11111100 %
b1111 "
#88000
b11111101 %
b0 "
#89000
b11111110 %
b1 "
#90000
b11111111 %
b10 "
#91000
b0 %
b11 "
#92000
b1 %
b100 "
#93000
b10 %
b101 "
#94000
b11 %
b110 "
#95000
b100 %
b111 "
#96000
b11110110 %
b1000 "
b1110 !
#97000
b11110111 %
b1001 "
#98000
b11111000 %
b1010 "
#99000
b11111001 %
b1011 "
#100000
b11111010 %
b1100 "
#101000
b11111011 %
b1101 "
#102000
b11111100 %
b1110 "
#103000
b11111101 %
b1111 "
#104000
b11111110 %
b0 "
#105000
b11111111 %
b1 "
#106000
b0 %
b10 "
#107000
b1 %
b11 "
#108000
b10 %
b100 "
#109000
b11 %
b101 "
#110000
b100 %
b110 "
#111000
b101 %
b111 "
#112000
b11110111 %
b1000 "
b1111 !
#113000
b11111000 %
b1001 "
#114000
b11111001 %
b1010 "
#115000
b11111010 %
b1011 "
#116000
b11111011 %
b1100 "
#117000
b11111100 %
b1101 "
#118000
b11111101 %
b1110 "
#119000
b11111110 %
b1111 "
#120000
b11111111 %
b0 "
#121000
b0 %
b1 "
#122000
b1 %
b10 "
#123000
b10 %
b11 "
#124000
b11 %
b100 "
#125000
b100 %
b101 "
#126000
b101 %
b110 "
#127000
b110 %
b111 "
#128000
b11111000 %
b1000 "
b0 !
#129000
b11111001 %
b1001 "
#130000
b11111010 %
b1010 "
#131000
b11111011 %
b1011 "
#132000
b11111100 %
b1100 "
#133000
b11111101 %
b1101 "
#134000
b11111110 %
b1110 "
#135000
b11111111 %
b1111 "
#136000
b0 %
b0 "
#137000
b1 %
b1 "
#138000
b10 %
b10 "
#139000
b11 %
b11 "
#140000
b100 %
b100 "
#141000
b101 %
b101 "
#142000
b110 %
b110 "
#143000
b111 %
b111 "
#144000
b11111001 %
b1000 "
b1 !
#145000
b11111010 %
b1001 "
#146000
b11111011 %
b1010 "
#147000
b11111100 %
b1011 "
#148000
b11111101 %
b1100 "
#149000
b11111110 %
b1101 "
#150000
b11111111 %
b1110 "
#151000
b0 %
b1111 "
#152000
b1 %
b0 "
#153000
b10 %
b1 "
#154000
b11 %
b10 "
#155000
b100 %
b11 "
#156000
b101 %
b100 "
#157000
b110 %
b101 "
#158000
b111 %
b110 "
#159000
b1000 %
b111 "
#160000
b11111010 %
b1000 "
b10 !
#161000
b11111011 %
b1001 "
#162000
b11111100 %
b1010 "
#163000
b11111101 %
b1011 "
#164000
b11111110 %
b1100 "
#165000
b11111111 %
b1101 "
#166000
b0 %
b1110 "
#167000
b1 %
b1111 "
#168000
b10 %
b0 "
#169000
b11 %
b1 "
#170000
b100 %
b10 "
#171000
b101 %
b11 "
#172000
b110 %
b100 "
#173000
b111 %
b101 "
#174000
b1000 %
b110 "
#175000
b1001 %
b111 "
#176000
b11111011 %
b1000 "
b11 !
#177000
b11111100 %
b1001 "
#178000
b11111101 %
b1010 "
#179000
b11111110 %
b1011 "
#180000
b11111111 %
b1100 "
#181000
b0 %
b1101 "
#182000
b1 %
b1110 "
#183000
b10 %
b1111 "
#184000
b11 %
b0 "
#185000
b100 %
b1 "
#186000
b101 %
b10 "
#187000
b110 %
b11 "
#188000
b111 %
b100 "
#189000
b1000 %
b101 "
#190000
b1001 %
b110 "
#191000
b1010 %
b111 "
#192000
b11111100 %
b1000 "
b100 !
#193000
b11111101 %
b1001 "
#194000
b11111110 %
b1010 "
#195000
b11111111 %
b1011 "
#196000
b0 %
b1100 "
#197000
b1 %
b1101 "
#198000
b10 %
b1110 "
#199000
b11 %
b1111 "
#200000
b100 %
b0 "
#201000
b101 %
b1 "
#202000
b110 %
b10 "
#203000
b111 %
b11 "
#204000
b1000 %
b100 "
#205000
b1001 %
b101 "
#206000
b1010 %
b110 "
#207000
b1011 %
b111 "
#208000
b11111101 %
b1000 "
b101 !
#209000
b11111110 %
b1001 "
#210000
b11111111 %
b1010 "
#211000
b0 %
b1011 "
#212000
b1 %
b1100 "
#213000
b10 %
b1101 "
#214000
b11 %
b1110 "
#215000
b100 %
b1111 "
#216000
b101 %
b0 "
#217000
b110 %
b1 "
#218000
b111 %
b10 "
#219000
b1000 %
b11 "
#220000
b1001 %
b100 "
#221000
b1010 %
b101 "
#222000
b1011 %
b110 "
#223000
b1100 %
b111 "
#224000
b11111110 %
b1000 "
b110 !
#225000
b11111111 %
b1001 "
#226000
b0 %
b1010 "
#227000
b1 %
b1011 "
#228000
b10 %
b1100 "
#229000
b11 %
b1101 "
#230000
b100 %
b1110 "
#231000
b101 %
b1111 "
#232000
b110 %
b0 "
#233000
b111 %
b1 "
#234000
b1000 %
b10 "
#235000
b1001 %
b11 "
#236000
b1010 %
b100 "
#237000
b1011 %
b101 "
#238000
b1100 %
b110 "
#239000
b1101 %
b111 "
#240000
b11111111 %
b1000 "
b111 !
#241000
b0 %
b1001 "
#242000
b1 %
b1010 "
#243000
b10 %
b1011 "
#244000
b11 %
b1100 "
#245000
b100 %
b1101 "
#246000
b101 %
b1110 "
#247000
b110 %
b1111 "
#248000
b111 %
b0 "
#249000
b1000 %
b1 "
#250000
b1001 %
b10 "
#251000
b1010 %
b11 "
#252000
b1011 %
b100 "
#253000
b1100 %
b101 "
#254000
b1101 %
b110 "
#255000
b1110 %
b111 "
