day7simpleram/ram.sv
module simple_ram (
    input  wire       clk,
    input  wire        write_enable,
    input  wire [7:0]  address,
    input  wire [7:0]  write_data,
    output reg  [7:0]  read_data
);

    reg [7:0] memory [0:255];

    initial begin
        $dumpfile("simple_ram.vcd");
        $dumpvars(0, simple_ram);
    end

    always @(posedge clk) begin
        if (write_enable)
            memory[address] <= write_data;
        read_data <= memory[address];
    end

endmodule

day7simpleram/simple_ram.vcd
$date
	Tue Aug 25 12:35:31 2026
$end
$version
	Icarus Verilog
$end
$timescale
	1ps
$end
$scope module simple_ram $end
$var wire 8 ! address [7:0] $end
$var wire 1 " clk $end
$var wire 8 # write_data [7:0] $end
$var wire 1 $ write_enable $end
$var reg 8 % read_data [7:0] $end
$upscope $end
$enddefinitions $end
#0
$dumpvars
bx %
1$
b10101010 #
1"
b10000 !
$end
#5000
0"
#10000
0$
1"
#15000
0"
#20000
b10101010 %
1"
#21000
b1010101 #
b100000 !
1$
#25000
0"
#30000
0$
bx %
1"
#35000
0"
#40000
b1010101 %
1"
#41000
b10000 !
#45000
0"
#50000
b10101010 %
1"
