bit_vector/div_signed_netlist.v
/* Generated by Yosys 0.33 (git sha1 2584903a060) */

module div_signed(a, b, quotient, remainder);
  wire _000_;
  wire _001_;
  wire _002_;
  wire _003_;
  wire _004_;
  wire _005_;
  wire _006_;
  wire _007_;
  wire _008_;
  wire _009_;
  wire _010_;
  wire _011_;
  wire _012_;
  wire _013_;
  wire _014_;
  wire _015_;
  wire _016_;
  wire _017_;
  wire _018_;
  wire _019_;
  wire _020_;
  wire _021_;
  wire _022_;
  wire _023_;
  wire _024_;
  wire _025_;
  wire _026_;
  wire _027_;
  wire _028_;
  wire _029_;
  wire _030_;
  wire _031_;
  wire _032_;
  wire _033_;
  wire _034_;
  wire _035_;
  wire _036_;
  wire _037_;
  wire _038_;
  wire _039_;
  wire _040_;
  wire _041_;
  wire _042_;
  wire _043_;
  wire _044_;
  wire _045_;
  wire _046_;
  wire _047_;
  wire _048_;
  wire _049_;
  wire _050_;
  wire _051_;
  wire _052_;
  wire _053_;
  wire _054_;
  wire _055_;
  wire _056_;
  wire _057_;
  wire _058_;
  wire _059_;
  wire _060_;
  wire _061_;
  wire _062_;
  wire _063_;
  wire _064_;
  wire _065_;
  wire _066_;
  wire _067_;
  wire _068_;
  wire _069_;
  wire _070_;
  wire _071_;
  wire _072_;
  wire _073_;
  wire _074_;
  wire _075_;
  wire _076_;
  wire _077_;
  wire _078_;
  wire _079_;
  wire _080_;
  wire _081_;
  wire _082_;
  wire _083_;
  wire _084_;
  wire _085_;
  wire _086_;
  wire _087_;
  wire _088_;
  wire _089_;
  wire _090_;
  wire _091_;
  wire _092_;
  wire _093_;
  wire _094_;
  wire _095_;
  wire _096_;
  wire _097_;
  wire _098_;
  wire _099_;
  wire _100_;
  wire _101_;
  wire _102_;
  wire _103_;
  wire _104_;
  wire _105_;
  wire _106_;
  wire _107_;
  wire _108_;
  wire _109_;
  wire _110_;
  wire _111_;
  wire _112_;
  wire _113_;
  wire _114_;
  wire _115_;
  wire _116_;
  wire _117_;
  wire _118_;
  wire _119_;
  wire _120_;
  wire _121_;
  wire _122_;
  wire _123_;
  wire _124_;
  wire _125_;
  wire _126_;
  wire _127_;
  wire _128_;
  wire _129_;
  wire _130_;
  wire _131_;
  wire _132_;
  wire _133_;
  wire _134_;
  wire _135_;
  wire _136_;
  wire _137_;
  wire _138_;
  wire _139_;
  wire _140_;
  wire _141_;
  wire _142_;
  wire _143_;
  wire _144_;
  wire _145_;
  wire _146_;
  wire _147_;
  wire _148_;
  wire _149_;
  wire _150_;
  wire _151_;
  wire _152_;
  wire _153_;
  wire _154_;
  wire _155_;
  wire _156_;
  wire _157_;
  wire _158_;
  wire _159_;
  wire _160_;
  wire _161_;
  wire _162_;
  wire _163_;
  wire _164_;
  wire _165_;
  wire _166_;
  wire _167_;
  wire _168_;
  wire _169_;
  wire _170_;
  wire _171_;
  wire _172_;
  wire _173_;
  wire _174_;
  wire _175_;
  wire _176_;
  wire _177_;
  wire _178_;
  wire _179_;
  wire _180_;
  wire _181_;
  wire _182_;
  wire _183_;
  wire _184_;
  wire _185_;
  wire _186_;
  wire _187_;
  wire _188_;
  wire _189_;
  wire _190_;
  wire _191_;
  wire _192_;
  wire _193_;
  wire _194_;
  wire _195_;
  wire _196_;
  wire _197_;
  wire _198_;
  wire _199_;
  wire _200_;
  wire _201_;
  wire _202_;
  wire _203_;
  wire _204_;
  wire _205_;
  wire _206_;
  wire _207_;
  wire _208_;
  wire _209_;
  wire _210_;
  wire _211_;
  wire _212_;
  wire _213_;
  wire _214_;
  wire _215_;
  wire _216_;
  wire _217_;
  wire _218_;
  wire _219_;
  wire _220_;
  wire _221_;
  wire _222_;
  wire _223_;
  wire _224_;
  wire _225_;
  wire _226_;
  wire _227_;
  wire _228_;
  wire _229_;
  wire _230_;
  wire _231_;
  wire _232_;
  wire _233_;
  wire _234_;
  wire _235_;
  wire _236_;
  wire _237_;
  wire _238_;
  wire _239_;
  wire _240_;
  wire _241_;
  wire _242_;
  wire _243_;
  wire _244_;
  wire _245_;
  wire _246_;
  wire _247_;
  wire _248_;
  wire _249_;
  wire _250_;
  wire _251_;
  wire _252_;
  wire _253_;
  wire _254_;
  wire _255_;
  wire _256_;
  wire _257_;
  wire _258_;
  wire _259_;
  wire _260_;
  wire _261_;
  wire _262_;
  wire _263_;
  wire _264_;
  wire _265_;
  wire _266_;
  wire _267_;
  wire _268_;
  wire _269_;
  wire _270_;
  wire _271_;
  wire _272_;
  wire _273_;
  wire _274_;
  wire _275_;
  wire _276_;
  wire _277_;
  wire _278_;
  wire _279_;
  wire _280_;
  wire _281_;
  wire _282_;
  wire _283_;
  wire _284_;
  wire _285_;
  wire _286_;
  wire _287_;
  wire _288_;
  wire _289_;
  wire _290_;
  wire _291_;
  wire _292_;
  wire _293_;
  wire _294_;
  wire _295_;
  wire _296_;
  wire _297_;
  wire _298_;
  wire _299_;
  wire _300_;
  wire _301_;
  wire _302_;
  wire _303_;
  wire _304_;
  wire _305_;
  wire _306_;
  wire _307_;
  wire _308_;
  wire _309_;
  wire _310_;
  wire _311_;
  wire _312_;
  wire _313_;
  wire _314_;
  wire _315_;
  wire _316_;
  wire _317_;
  wire _318_;
  wire _319_;
  wire _320_;
  wire _321_;
  wire _322_;
  wire _323_;
  wire _324_;
  wire _325_;
  wire _326_;
  wire _327_;
  wire _328_;
  wire _329_;
  wire _330_;
  wire _331_;
  wire _332_;
  wire _333_;
  wire _334_;
  wire _335_;
  wire _336_;
  wire _337_;
  wire _338_;
  wire _339_;
  wire _340_;
  wire _341_;
  wire _342_;
  wire _343_;
  wire _344_;
  wire _345_;
  wire _346_;
  wire _347_;
  wire _348_;
  wire _349_;
  wire _350_;
  wire _351_;
  wire _352_;
  wire _353_;
  wire _354_;
  wire _355_;
  wire _356_;
  wire _357_;
  wire _358_;
  wire _359_;
  wire _360_;
  wire _361_;
  wire _362_;
  wire _363_;
  wire _364_;
  wire _365_;
  wire _366_;
  wire _367_;
  wire _368_;
  wire _369_;
  wire _370_;
  wire _371_;
  wire _372_;
  wire _373_;
  wire _374_;
  wire _375_;
  wire _376_;
  wire _377_;
  wire _378_;
  wire _379_;
  wire _380_;
  wire _381_;
  wire _382_;
  wire _383_;
  wire _384_;
  wire _385_;
  wire _386_;
  wire _387_;
  wire _388_;
  wire _389_;
  wire _390_;
  wire _391_;
  wire _392_;
  wire _393_;
  wire _394_;
  wire _395_;
  wire _396_;
  wire _397_;
  wire _398_;
  wire _399_;
  wire _400_;
  wire _401_;
  wire _402_;
  wire _403_;
  wire _404_;
  wire _405_;
  wire _406_;
  wire _407_;
  wire _408_;
  wire _409_;
  wire _410_;
  wire _411_;
  wire _412_;
  wire _413_;
  wire _414_;
  wire _415_;
  wire _416_;
  wire _417_;
  wire _418_;
  wire _419_;
  wire _420_;
  wire _421_;
  wire _422_;
  wire _423_;
  wire _424_;
  wire _425_;
  wire _426_;
  wire _427_;
  wire _428_;
  wire _429_;
  wire _430_;
  wire _431_;
  wire _432_;
  wire _433_;
  wire _434_;
  wire _435_;
  wire _436_;
  wire _437_;
  wire _438_;
  wire _439_;
  wire _440_;
  wire _441_;
  wire _442_;
  wire _443_;
  wire _444_;
  wire _445_;
  wire _446_;
  wire _447_;
  wire _448_;
  wire _449_;
  wire _450_;
  wire _451_;
  wire _452_;
  wire _453_;
  wire _454_;
  wire _455_;
  wire _456_;
  wire _457_;
  wire _458_;
  wire _459_;
  wire _460_;
  wire _461_;
  wire _462_;
  wire _463_;
  wire _464_;
  wire _465_;
  wire _466_;
  wire _467_;
  wire _468_;
  wire _469_;
  wire _470_;
  wire _471_;
  wire _472_;
  wire _473_;
  wire _474_;
  wire _475_;
  wire _476_;
  input [7:0] a;
  wire [7:0] a;
  input [7:0] b;
  wire [7:0] b;
  output [7:0] quotient;
  wire [7:0] quotient;
  output [7:0] remainder;
  wire [7:0] remainder;
  assign _235_ = ~b[7];
  assign _246_ = ~b[6];
  assign _257_ = ~(b[5] | b[4]);
  assign _268_ = ~(b[3] | b[2]);
  assign _279_ = b[0] | b[1];
  assign _290_ = _279_ | ~(_268_);
  assign _301_ = _257_ & ~(_290_);
  assign _312_ = ~(_301_ & _246_);
  assign _323_ = _312_ | _235_;
  assign _334_ = ~a[7];
  assign _343_ = ~a[6];
  assign _353_ = a[5] | a[4];
  assign _362_ = ~(a[3] | a[2]);
  assign _373_ = a[1] | a[0];
  assign _383_ = _362_ & ~(_373_);
  assign _393_ = _383_ & ~(_353_);
  assign _403_ = ~(_393_ & _343_);
  assign _412_ = _403_ | _334_;
  assign _421_ = ~a[5];
  assign _429_ = _383_ & ~(a[4]);
  assign _433_ = _429_ ^ a[5];
  assign _434_ = a[7] ? _433_ : _421_;
  assign _435_ = a[7] | ~(a[4]);
  assign _436_ = _383_ ^ a[4];
  assign _437_ = a[7] & ~(_436_);
  assign _438_ = _437_ | ~(_435_);
  assign _003_ = _434_ & ~(_438_);
  assign _439_ = _412_ ^ b[0];
  assign _440_ = _393_ ^ a[6];
  assign _441_ = a[7] ? _440_ : _343_;
  assign _442_ = ~(_441_ & _439_);
  assign _006_ = _003_ & ~(_442_);
  assign _443_ = ~a[3];
  assign _444_ = ~a[2];
  assign _445_ = _444_ & ~(_373_);
  assign _446_ = _445_ ^ a[3];
  assign _447_ = a[7] ? _446_ : _443_;
  assign _448_ = _373_ ^ _444_;
  assign _449_ = a[7] ? _448_ : _444_;
  assign _037_ = ~(_449_ & _447_);
  assign _450_ = ~a[1];
  assign _451_ = ~(a[1] ^ a[0]);
  assign _452_ = a[7] ? _451_ : _450_;
  assign _453_ = a[0] | ~(_452_);
  assign _454_ = _453_ | _037_;
  assign _455_ = _454_ | ~(_006_);
  assign _456_ = b[0] ^ b[1];
  assign _457_ = b[7] ? _456_ : b[1];
  assign _458_ = _279_ ^ b[2];
  assign _459_ = b[7] ? _458_ : b[2];
  assign _460_ = _459_ | _457_;
  assign _461_ = _290_ ^ b[4];
  assign _462_ = b[7] ? _461_ : b[4];
  assign _463_ = _279_ | b[2];
  assign _464_ = _463_ ^ b[3];
  assign _465_ = b[7] ? _464_ : b[3];
  assign _466_ = _465_ | _462_;
  assign _467_ = _466_ | _460_;
  assign _468_ = _301_ ^ _246_;
  assign _469_ = b[7] ? _468_ : b[6];
  assign _470_ = _290_ | b[4];
  assign _471_ = _470_ ^ b[5];
  assign _472_ = b[7] ? _471_ : b[5];
  assign _473_ = _472_ | _469_;
  assign _474_ = _473_ | ~(_323_);
  assign _475_ = _474_ | _467_;
  assign _476_ = _475_ | _455_;
  assign _000_ = _412_ | b[0];
  assign _001_ = _439_ & ~(_441_);
  assign _002_ = _000_ & ~(_001_);
  assign _004_ = ~(_003_ | _442_);
  assign _005_ = _002_ & ~(_004_);
  assign _007_ = _005_ & ~(_006_);
  assign _008_ = _007_ | _467_;
  assign _009_ = _008_ | _473_;
  assign _010_ = _323_ & ~(_009_);
  assign _011_ = _476_ & ~(_010_);
  assign _012_ = _003_ & ~(_003_);
  assign _013_ = _012_ & _441_;
  assign _014_ = _013_ ^ _439_;
  assign _015_ = _011_ ? _412_ : _014_;
  assign _016_ = _438_ | ~(_434_);
  assign _017_ = _015_ ^ _457_;
  assign _018_ = ~b[0];
  assign _019_ = _012_ ^ _441_;
  assign _020_ = _011_ ? _441_ : _019_;
  assign _021_ = _020_ ^ _018_;
  assign _022_ = _017_ & ~(_021_);
  assign _023_ = _016_ | ~(_022_);
  assign _024_ = _023_ | _454_;
  assign _025_ = _323_ & ~(_469_);
  assign _026_ = _465_ | _459_;
  assign _027_ = _472_ | _462_;
  assign _028_ = _027_ | _026_;
  assign _029_ = _028_ | ~(_025_);
  assign _030_ = _029_ | _024_;
  assign _031_ = _015_ | _457_;
  assign _032_ = _020_ | b[0];
  assign _033_ = _017_ & ~(_032_);
  assign _034_ = _031_ & ~(_033_);
  assign _035_ = _022_ & ~(_003_);
  assign _036_ = _034_ & ~(_035_);
  assign _038_ = _037_ | ~(_037_);
  assign _039_ = _038_ & ~(_023_);
  assign _040_ = _036_ & ~(_039_);
  assign _041_ = _040_ | _028_;
  assign _042_ = _025_ & ~(_041_);
  assign _043_ = _030_ & ~(_042_);
  assign _044_ = ~(_012_ | _021_);
  assign _045_ = _032_ & ~(_044_);
  assign _046_ = _045_ ^ _017_;
  assign _047_ = _043_ ? _015_ : _046_;
  assign _048_ = ~(_038_ | _438_);
  assign _049_ = _048_ ^ _434_;
  assign _050_ = _011_ ? _434_ : _049_;
  assign _051_ = _435_ & ~(_437_);
  assign _052_ = _051_ & ~(_038_);
  assign _053_ = _052_ ^ _050_;
  assign _054_ = _043_ ? _050_ : _053_;
  assign _055_ = _054_ ^ b[0];
  assign _056_ = _043_ ? _051_ : _051_;
  assign _057_ = ~(_056_ & _055_);
  assign _058_ = _047_ ^ _459_;
  assign _059_ = ~(_012_ ^ _021_);
  assign _060_ = _043_ ? _020_ : _059_;
  assign _061_ = ~(_060_ ^ _457_);
  assign _062_ = _058_ & ~(_061_);
  assign _063_ = _057_ | ~(_062_);
  assign _064_ = _063_ | _454_;
  assign _065_ = _473_ | _466_;
  assign _066_ = _065_ | ~(_323_);
  assign _067_ = _066_ | _064_;
  assign _068_ = _047_ | _459_;
  assign _069_ = _060_ | _457_;
  assign _070_ = _058_ & ~(_069_);
  assign _071_ = _068_ & ~(_070_);
  assign _072_ = _054_ | b[0];
  assign _073_ = _055_ & ~(_056_);
  assign _074_ = _072_ & ~(_073_);
  assign _075_ = _062_ & ~(_074_);
  assign _076_ = _071_ & ~(_075_);
  assign _077_ = _038_ & ~(_063_);
  assign _078_ = _076_ & ~(_077_);
  assign _079_ = _078_ | _065_;
  assign _080_ = _323_ & ~(_079_);
  assign _081_ = _067_ & ~(_080_);
  assign _082_ = _038_ & ~(_057_);
  assign _083_ = _074_ & ~(_082_);
  assign _084_ = ~(_083_ | _061_);
  assign _085_ = _069_ & ~(_084_);
  assign _086_ = _085_ ^ _058_;
  assign _087_ = _081_ ? _047_ : _086_;
  assign _088_ = _025_ & ~(_027_);
  assign _089_ = _056_ & ~(_038_);
  assign _090_ = _089_ ^ _055_;
  assign _091_ = _081_ ? _054_ : _090_;
  assign _092_ = _091_ ^ _457_;
  assign _093_ = ~(_056_ ^ _038_);
  assign _094_ = _081_ ? _056_ : _093_;
  assign _095_ = _094_ ^ _018_;
  assign _096_ = _095_ | ~(_092_);
  assign _097_ = _087_ ^ _465_;
  assign _098_ = ~(_083_ ^ _061_);
  assign _099_ = _081_ ? _060_ : _098_;
  assign _100_ = ~(_099_ ^ _459_);
  assign _101_ = _097_ & ~(_100_);
  assign _102_ = _096_ | ~(_101_);
  assign _103_ = _102_ | _454_;
  assign _104_ = _103_ | ~(_088_);
  assign _105_ = _087_ | _465_;
  assign _106_ = _099_ | _459_;
  assign _107_ = _097_ & ~(_106_);
  assign _108_ = _105_ & ~(_107_);
  assign _109_ = _091_ | _457_;
  assign _110_ = _094_ | b[0];
  assign _111_ = _092_ & ~(_110_);
  assign _112_ = _109_ & ~(_111_);
  assign _113_ = _101_ & ~(_112_);
  assign _114_ = _108_ & ~(_113_);
  assign _115_ = _038_ & ~(_102_);
  assign _116_ = _114_ & ~(_115_);
  assign _117_ = _088_ & ~(_116_);
  assign _118_ = _104_ & ~(_117_);
  assign _119_ = _038_ & ~(_096_);
  assign _120_ = _112_ & ~(_119_);
  assign _121_ = ~(_120_ | _100_);
  assign _122_ = _106_ & ~(_121_);
  assign _123_ = _122_ ^ _097_;
  assign _124_ = _118_ ? _087_ : _123_;
  assign _125_ = _038_ & ~(_095_);
  assign _126_ = _110_ & ~(_125_);
  assign _127_ = _126_ ^ _092_;
  assign _128_ = _118_ ? _091_ : _127_;
  assign _129_ = _128_ ^ _459_;
  assign _130_ = _095_ ^ _038_;
  assign _131_ = _118_ ? _094_ : _130_;
  assign _132_ = ~(_131_ ^ _457_);
  assign _133_ = _129_ & ~(_132_);
  assign _134_ = _124_ ^ _462_;
  assign _135_ = ~(_120_ ^ _100_);
  assign _136_ = _118_ ? _099_ : _135_;
  assign _137_ = ~(_136_ ^ _465_);
  assign _138_ = _137_ | ~(_134_);
  assign _139_ = _133_ & ~(_138_);
  assign _140_ = _447_ ^ _018_;
  assign _141_ = _140_ | ~(_449_);
  assign _142_ = ~(_141_ | _453_);
  assign _143_ = ~(_142_ & _139_);
  assign _144_ = _143_ | _474_;
  assign _145_ = _124_ | _462_;
  assign _146_ = _136_ | _465_;
  assign _147_ = _134_ & ~(_146_);
  assign _148_ = _145_ & ~(_147_);
  assign _149_ = _128_ | _459_;
  assign _150_ = _131_ | _457_;
  assign _151_ = _129_ & ~(_150_);
  assign _152_ = _149_ & ~(_151_);
  assign _153_ = ~(_152_ | _138_);
  assign _154_ = _148_ & ~(_153_);
  assign _155_ = _447_ & ~(_018_);
  assign _156_ = _139_ & ~(_155_);
  assign _157_ = _154_ & ~(_156_);
  assign _158_ = _157_ | _473_;
  assign _159_ = _323_ & ~(_158_);
  assign _160_ = _144_ & ~(_159_);
  assign _161_ = _133_ & ~(_155_);
  assign _162_ = _152_ & ~(_161_);
  assign _163_ = ~(_162_ | _137_);
  assign _164_ = _146_ & ~(_163_);
  assign _165_ = _164_ ^ _134_;
  assign _166_ = _160_ ? _124_ : _165_;
  assign _167_ = ~(_155_ | _132_);
  assign _168_ = _150_ & ~(_167_);
  assign _169_ = _168_ ^ _129_;
  assign _170_ = _160_ ? _128_ : _169_;
  assign _171_ = _170_ ^ _465_;
  assign _172_ = ~(_155_ ^ _132_);
  assign _173_ = _160_ ? _131_ : _172_;
  assign _174_ = ~(_173_ ^ _459_);
  assign _175_ = _171_ & ~(_174_);
  assign _176_ = _166_ ^ _472_;
  assign _177_ = ~(_162_ ^ _137_);
  assign _178_ = _160_ ? _136_ : _177_;
  assign _179_ = ~(_178_ ^ _462_);
  assign _180_ = _179_ | ~(_176_);
  assign _181_ = _175_ & ~(_180_);
  assign _182_ = ~_140_;
  assign _183_ = _160_ ? _447_ : _182_;
  assign _184_ = _183_ ^ _457_;
  assign _185_ = _449_ ^ _018_;
  assign _186_ = ~_185_;
  assign _187_ = ~(_186_ & _184_);
  assign _188_ = ~(_187_ | _453_);
  assign _189_ = ~(_188_ & _181_);
  assign _190_ = _189_ | ~(_025_);
  assign _191_ = _166_ | _472_;
  assign _192_ = _178_ | _462_;
  assign _193_ = _176_ & ~(_192_);
  assign _194_ = _191_ & ~(_193_);
  assign _195_ = _170_ | _465_;
  assign _196_ = _173_ | _459_;
  assign _197_ = _171_ & ~(_196_);
  assign _198_ = _195_ & ~(_197_);
  assign _199_ = ~(_198_ | _180_);
  assign _200_ = _194_ & ~(_199_);
  assign _201_ = ~(_183_ | _457_);
  assign _202_ = _449_ | b[0];
  assign _203_ = _184_ & ~(_202_);
  assign _204_ = _203_ | _201_;
  assign _205_ = _187_ & ~(_204_);
  assign _206_ = _181_ & ~(_205_);
  assign _207_ = _200_ & ~(_206_);
  assign _208_ = _025_ & ~(_207_);
  assign _209_ = _190_ & ~(_208_);
  assign _210_ = ~_179_;
  assign _211_ = _175_ & ~(_205_);
  assign _212_ = _198_ & ~(_211_);
  assign _213_ = _210_ & ~(_212_);
  assign _214_ = _192_ & ~(_213_);
  assign _215_ = _214_ ^ _176_;
  assign _216_ = _209_ ? _166_ : _215_;
  assign _217_ = ~_174_;
  assign _218_ = _217_ & ~(_205_);
  assign _219_ = _196_ & ~(_218_);
  assign _220_ = _219_ ^ _171_;
  assign _221_ = _209_ ? _170_ : _220_;
  assign _222_ = _221_ ^ _462_;
  assign _223_ = _205_ ^ _217_;
  assign _224_ = _209_ ? _173_ : _223_;
  assign _225_ = ~(_224_ ^ _465_);
  assign _226_ = _222_ & ~(_225_);
  assign _227_ = _216_ ^ _469_;
  assign _228_ = _212_ ^ _210_;
  assign _229_ = _209_ ? _178_ : _228_;
  assign _230_ = ~(_229_ ^ _472_);
  assign _231_ = ~_230_;
  assign _232_ = ~(_231_ & _227_);
  assign _233_ = _226_ & ~(_232_);
  assign _234_ = _449_ & ~(_018_);
  assign _236_ = _234_ ^ _184_;
  assign _237_ = _209_ ? _183_ : _236_;
  assign _238_ = _237_ ^ _459_;
  assign _239_ = _209_ ? _449_ : _186_;
  assign _240_ = ~(_239_ ^ _457_);
  assign _241_ = _238_ & ~(_240_);
  assign _242_ = _452_ ^ _018_;
  assign _243_ = ~(_242_ | a[0]);
  assign _244_ = ~(_243_ & _241_);
  assign _245_ = _233_ & ~(_244_);
  assign _247_ = _216_ | _469_;
  assign _248_ = _229_ | _472_;
  assign _249_ = _227_ & ~(_248_);
  assign _250_ = _247_ & ~(_249_);
  assign _251_ = _221_ | _462_;
  assign _252_ = _224_ | _465_;
  assign _253_ = _222_ & ~(_252_);
  assign _254_ = _251_ & ~(_253_);
  assign _255_ = ~(_254_ | _232_);
  assign _256_ = _250_ & ~(_255_);
  assign _258_ = _237_ | _459_;
  assign _259_ = _239_ | _457_;
  assign _260_ = _238_ & ~(_259_);
  assign _261_ = _258_ & ~(_260_);
  assign _262_ = _452_ & ~(_018_);
  assign _263_ = _241_ & ~(_262_);
  assign _264_ = _261_ & ~(_263_);
  assign _265_ = _233_ & ~(_264_);
  assign _266_ = _256_ & ~(_265_);
  assign _267_ = _226_ & ~(_264_);
  assign _269_ = _254_ & ~(_267_);
  assign _270_ = _231_ & ~(_269_);
  assign _271_ = _248_ & ~(_270_);
  assign _272_ = _271_ ^ _227_;
  assign _273_ = _216_ & ~(_323_);
  assign _274_ = ~(_245_ & _323_);
  assign _275_ = _323_ & ~(_266_);
  assign _276_ = _274_ & ~(_275_);
  assign _277_ = _276_ ? _216_ : _272_;
  assign _278_ = ~(_277_ ^ _323_);
  assign _280_ = _269_ ^ _231_;
  assign _281_ = _276_ ? _229_ : _280_;
  assign _282_ = ~(_281_ & _469_);
  assign _283_ = _278_ & ~(_282_);
  assign _284_ = _283_ | _273_;
  assign _285_ = ~(_281_ ^ _469_);
  assign _286_ = _278_ & ~(_285_);
  assign _287_ = ~_225_;
  assign _288_ = _287_ & ~(_264_);
  assign _289_ = _252_ & ~(_288_);
  assign _291_ = _289_ ^ _222_;
  assign _292_ = _276_ ? _221_ : _291_;
  assign _293_ = ~(_292_ & _472_);
  assign _294_ = _292_ ^ _472_;
  assign _295_ = _264_ ^ _287_;
  assign _296_ = _276_ ? _224_ : _295_;
  assign _297_ = ~(_296_ & _462_);
  assign _298_ = _294_ & ~(_297_);
  assign _299_ = _293_ & ~(_298_);
  assign _300_ = _286_ & ~(_299_);
  assign _302_ = _300_ | _284_;
  assign _303_ = ~(_296_ ^ _462_);
  assign _304_ = _303_ | ~(_294_);
  assign _305_ = _286_ & ~(_304_);
  assign _306_ = ~(_262_ | _240_);
  assign _307_ = _259_ & ~(_306_);
  assign _308_ = _307_ ^ _238_;
  assign _309_ = _276_ ? _237_ : _308_;
  assign _310_ = ~(_309_ & _465_);
  assign _311_ = _309_ ^ _465_;
  assign _313_ = ~(_262_ ^ _240_);
  assign _314_ = _276_ ? _239_ : _313_;
  assign _315_ = ~(_314_ & _459_);
  assign _316_ = _311_ & ~(_315_);
  assign _317_ = _310_ & ~(_316_);
  assign _318_ = ~(_314_ ^ _459_);
  assign _319_ = _311_ & ~(_318_);
  assign _320_ = ~_242_;
  assign _321_ = _276_ ? _452_ : _320_;
  assign _322_ = ~(_321_ & _457_);
  assign _324_ = _321_ ^ _457_;
  assign _325_ = a[0] & ~(b[0]);
  assign _326_ = _324_ & ~(_325_);
  assign _327_ = _322_ & ~(_326_);
  assign _328_ = _319_ & ~(_327_);
  assign _329_ = _317_ & ~(_328_);
  assign _330_ = _305_ & ~(_329_);
  assign _331_ = _330_ | _302_;
  assign _332_ = b[0] ^ a[0];
  assign _333_ = _324_ & ~(_332_);
  assign _335_ = ~(_333_ & _319_);
  assign _336_ = _305_ & ~(_335_);
  assign _337_ = _331_ & ~(_336_);
  assign quotient[0] = ~_337_;
  assign _338_ = b[0] & ~(a[0]);
  assign _339_ = _338_ ^ _324_;
  assign _340_ = _337_ ? _321_ : _339_;
  assign _341_ = ~_340_;
  assign remainder[0] = _337_ ? a[0] : _332_;
  assign _342_ = ~(remainder[0] ^ _340_);
  assign remainder[1] = a[7] ? _342_ : _341_;
  assign _344_ = ~_318_;
  assign _345_ = _321_ | _457_;
  assign _346_ = _324_ & ~(_338_);
  assign _347_ = _345_ & ~(_346_);
  assign _348_ = _347_ ^ _344_;
  assign _349_ = _337_ ? _314_ : _348_;
  assign _350_ = ~_349_;
  assign _351_ = _340_ & ~(remainder[0]);
  assign _352_ = _351_ ^ _349_;
  assign remainder[2] = a[7] ? _352_ : _350_;
  assign _354_ = ~_309_;
  assign _355_ = _314_ | _459_;
  assign _356_ = _344_ & ~(_347_);
  assign _357_ = _356_ | ~(_355_);
  assign _358_ = _357_ ^ _311_;
  assign _359_ = _337_ ? _354_ : _358_;
  assign _360_ = _351_ & ~(_350_);
  assign _361_ = ~(_360_ ^ _359_);
  assign remainder[3] = a[7] ? _361_ : _359_;
  assign _363_ = ~_303_;
  assign _364_ = _309_ | _465_;
  assign _365_ = _311_ & ~(_355_);
  assign _366_ = _364_ & ~(_365_);
  assign _367_ = _319_ & ~(_347_);
  assign _368_ = _366_ & ~(_367_);
  assign _369_ = _368_ ^ _363_;
  assign _370_ = _337_ ? _296_ : _369_;
  assign _371_ = ~_370_;
  assign _372_ = _359_ | ~(_349_);
  assign _374_ = _351_ & ~(_372_);
  assign _375_ = _374_ ^ _370_;
  assign remainder[4] = a[7] ? _375_ : _371_;
  assign _376_ = ~_292_;
  assign _377_ = _296_ | _462_;
  assign _378_ = _363_ & ~(_368_);
  assign _379_ = _378_ | ~(_377_);
  assign _380_ = _379_ ^ _294_;
  assign _381_ = _337_ ? _376_ : _380_;
  assign _382_ = ~(_374_ & _370_);
  assign _384_ = _382_ ^ _381_;
  assign remainder[5] = a[7] ? _384_ : _381_;
  assign _385_ = ~_285_;
  assign _386_ = _292_ | _472_;
  assign _387_ = _294_ & ~(_377_);
  assign _388_ = _386_ & ~(_387_);
  assign _389_ = ~(_368_ | _304_);
  assign _390_ = _388_ & ~(_389_);
  assign _391_ = _390_ ^ _385_;
  assign _392_ = _337_ ? _281_ : _391_;
  assign _394_ = ~_392_;
  assign _395_ = _381_ | ~(_370_);
  assign _396_ = _395_ | ~(_374_);
  assign _397_ = _396_ ^ _394_;
  assign remainder[6] = a[7] ? _397_ : _394_;
  assign _398_ = ~_277_;
  assign _399_ = _281_ | _469_;
  assign _400_ = _385_ & ~(_390_);
  assign _401_ = _399_ & ~(_400_);
  assign _402_ = ~(_401_ ^ _278_);
  assign _404_ = _337_ ? _398_ : _402_;
  assign _405_ = _396_ | _394_;
  assign _406_ = _405_ ^ _404_;
  assign remainder[7] = a[7] ? _406_ : _404_;
  assign _407_ = ~_276_;
  assign _408_ = ~(b[7] ^ a[7]);
  assign _409_ = _337_ ^ _276_;
  assign quotient[1] = _408_ ? _407_ : _409_;
  assign _410_ = ~_209_;
  assign _411_ = ~(_337_ & _276_);
  assign _413_ = _411_ ^ _410_;
  assign quotient[2] = _408_ ? _410_ : _413_;
  assign _414_ = ~_160_;
  assign _415_ = _209_ & ~(_411_);
  assign _416_ = _415_ ^ _160_;
  assign quotient[3] = _408_ ? _414_ : _416_;
  assign _417_ = ~_118_;
  assign _418_ = ~(_209_ & _160_);
  assign _419_ = _418_ | _411_;
  assign _420_ = _419_ ^ _417_;
  assign quotient[4] = _408_ ? _417_ : _420_;
  assign _422_ = ~_081_;
  assign _423_ = _118_ & ~(_419_);
  assign _424_ = _423_ ^ _081_;
  assign quotient[5] = _408_ ? _422_ : _424_;
  assign _425_ = ~_043_;
  assign _426_ = ~(_118_ & _081_);
  assign _427_ = _426_ | _419_;
  assign _428_ = _427_ ^ _425_;
  assign quotient[6] = _408_ ? _425_ : _428_;
  assign _430_ = ~_011_;
  assign _431_ = _043_ & ~(_427_);
  assign _432_ = _431_ ^ _011_;
  assign quotient[7] = _408_ ? _430_ : _432_;
endmodule

bit_vector/div_signed.vcd
$date
	Fri Aug 21 06:11:43 2026
$end
$version
	Icarus Verilog
$end
$timescale
	1ps
$end
$scope module div_signed $end
$var wire 8 ! a [7:0] $end
$var wire 8 " b [7:0] $end
$var wire 8 # remainder [7:0] $end
$var wire 8 $ quotient [7:0] $end
$upscope $end
$enddefinitions $end
$comment Show the parameter values. $end
$dumpall
$end
#0
$dumpvars
b101 $
b0 #
b100 "
b10100 !
$end
#1000
b11111011 $
b11111100 "
#2000
b10 "
b11111101 $
b11111111 #
b11111001 !
#3000
b11111100 "
b101 $
b0 #
b11101100 !
#4000
b11110110 "
b0 $
b11 #
b11 !
#5000
b11111001 "
b0 #
b0 !
#6000
b1 "
b10011100 $
b0 #
b10011100 !
#7000
b11111111 "
b1111111 $
b10000001 !
#8000
bx #
b0 "
bx $
b1010 !
