bit_vector/multiply_signed_netlist.v
/* Generated by Yosys 0.33 (git sha1 2584903a060) */

module multiply_signed(a, b, product);
  wire _000_;
  wire _001_;
  wire _002_;
  wire _003_;
  wire _004_;
  wire _005_;
  wire _006_;
  wire _007_;
  wire _008_;
  wire _009_;
  wire _010_;
  wire _011_;
  wire _012_;
  wire _013_;
  wire _014_;
  wire _015_;
  wire _016_;
  wire _017_;
  wire _018_;
  wire _019_;
  wire _020_;
  wire _021_;
  wire _022_;
  wire _023_;
  wire _024_;
  wire _025_;
  wire _026_;
  wire _027_;
  wire _028_;
  wire _029_;
  wire _030_;
  wire _031_;
  wire _032_;
  wire _033_;
  wire _034_;
  wire _035_;
  wire _036_;
  wire _037_;
  wire _038_;
  wire _039_;
  wire _040_;
  wire _041_;
  wire _042_;
  wire _043_;
  wire _044_;
  wire _045_;
  wire _046_;
  wire _047_;
  wire _048_;
  wire _049_;
  wire _050_;
  wire _051_;
  wire _052_;
  wire _053_;
  wire _054_;
  wire _055_;
  wire _056_;
  wire _057_;
  wire _058_;
  wire _059_;
  wire _060_;
  wire _061_;
  wire _062_;
  wire _063_;
  wire _064_;
  wire _065_;
  wire _066_;
  wire _067_;
  wire _068_;
  wire _069_;
  wire _070_;
  wire _071_;
  wire _072_;
  wire _073_;
  wire _074_;
  wire _075_;
  wire _076_;
  wire _077_;
  wire _078_;
  wire _079_;
  wire _080_;
  wire _081_;
  wire _082_;
  wire _083_;
  wire _084_;
  wire _085_;
  wire _086_;
  wire _087_;
  wire _088_;
  wire _089_;
  wire _090_;
  wire _091_;
  wire _092_;
  wire _093_;
  wire _094_;
  wire _095_;
  wire _096_;
  wire _097_;
  wire _098_;
  wire _099_;
  wire _100_;
  wire _101_;
  wire _102_;
  wire _103_;
  wire _104_;
  wire _105_;
  wire _106_;
  wire _107_;
  wire _108_;
  wire _109_;
  wire _110_;
  wire _111_;
  wire _112_;
  wire _113_;
  wire _114_;
  wire _115_;
  wire _116_;
  wire _117_;
  wire _118_;
  wire _119_;
  wire _120_;
  wire _121_;
  wire _122_;
  wire _123_;
  wire _124_;
  wire _125_;
  wire _126_;
  wire _127_;
  wire _128_;
  wire _129_;
  wire _130_;
  wire _131_;
  wire _132_;
  wire _133_;
  wire _134_;
  wire _135_;
  wire _136_;
  wire _137_;
  wire _138_;
  wire _139_;
  wire _140_;
  wire _141_;
  wire _142_;
  wire _143_;
  wire _144_;
  wire _145_;
  wire _146_;
  wire _147_;
  wire _148_;
  wire _149_;
  wire _150_;
  wire _151_;
  wire _152_;
  wire _153_;
  wire _154_;
  wire _155_;
  wire _156_;
  wire _157_;
  wire _158_;
  wire _159_;
  wire _160_;
  wire _161_;
  wire _162_;
  wire _163_;
  wire _164_;
  wire _165_;
  wire _166_;
  wire _167_;
  wire _168_;
  wire _169_;
  wire _170_;
  wire _171_;
  wire _172_;
  wire _173_;
  wire _174_;
  wire _175_;
  wire _176_;
  wire _177_;
  wire _178_;
  wire _179_;
  wire _180_;
  wire _181_;
  wire _182_;
  wire _183_;
  wire _184_;
  wire _185_;
  wire _186_;
  wire _187_;
  wire _188_;
  wire _189_;
  wire _190_;
  wire _191_;
  wire _192_;
  wire _193_;
  wire _194_;
  wire _195_;
  wire _196_;
  wire _197_;
  wire _198_;
  wire _199_;
  wire _200_;
  wire _201_;
  wire _202_;
  wire _203_;
  wire _204_;
  wire _205_;
  wire _206_;
  wire _207_;
  wire _208_;
  wire _209_;
  wire _210_;
  wire _211_;
  wire _212_;
  wire _213_;
  wire _214_;
  wire _215_;
  wire _216_;
  wire _217_;
  wire _218_;
  wire _219_;
  wire _220_;
  wire _221_;
  wire _222_;
  wire _223_;
  wire _224_;
  wire _225_;
  wire _226_;
  wire _227_;
  wire _228_;
  wire _229_;
  wire _230_;
  wire _231_;
  wire _232_;
  wire _233_;
  wire _234_;
  wire _235_;
  wire _236_;
  wire _237_;
  wire _238_;
  wire _239_;
  wire _240_;
  wire _241_;
  wire _242_;
  wire _243_;
  wire _244_;
  wire _245_;
  wire _246_;
  wire _247_;
  wire _248_;
  wire _249_;
  wire _250_;
  wire _251_;
  wire _252_;
  wire _253_;
  wire _254_;
  wire _255_;
  wire _256_;
  wire _257_;
  wire _258_;
  wire _259_;
  wire _260_;
  wire _261_;
  wire _262_;
  wire _263_;
  wire _264_;
  wire _265_;
  wire _266_;
  wire _267_;
  wire _268_;
  wire _269_;
  wire _270_;
  wire _271_;
  wire _272_;
  wire _273_;
  wire _274_;
  wire _275_;
  wire _276_;
  wire _277_;
  wire _278_;
  wire _279_;
  wire _280_;
  wire _281_;
  wire _282_;
  wire _283_;
  wire _284_;
  wire _285_;
  wire _286_;
  wire _287_;
  wire _288_;
  wire _289_;
  wire _290_;
  wire _291_;
  wire _292_;
  wire _293_;
  wire _294_;
  wire _295_;
  wire _296_;
  wire _297_;
  wire _298_;
  wire _299_;
  wire _300_;
  wire _301_;
  wire _302_;
  wire _303_;
  wire _304_;
  wire _305_;
  wire _306_;
  wire _307_;
  wire _308_;
  wire _309_;
  wire _310_;
  wire _311_;
  wire _312_;
  wire _313_;
  wire _314_;
  wire _315_;
  wire _316_;
  wire _317_;
  wire _318_;
  wire _319_;
  wire _320_;
  wire _321_;
  wire _322_;
  wire _323_;
  wire _324_;
  wire _325_;
  wire _326_;
  wire _327_;
  wire _328_;
  wire _329_;
  wire _330_;
  wire _331_;
  wire _332_;
  wire _333_;
  wire _334_;
  wire _335_;
  wire _336_;
  wire _337_;
  wire _338_;
  wire _339_;
  wire _340_;
  wire _341_;
  wire _342_;
  wire _343_;
  wire _344_;
  wire _345_;
  wire _346_;
  wire _347_;
  wire _348_;
  wire _349_;
  wire _350_;
  wire _351_;
  wire _352_;
  wire _353_;
  wire _354_;
  wire _355_;
  wire _356_;
  wire _357_;
  wire _358_;
  wire _359_;
  wire _360_;
  wire _361_;
  wire _362_;
  wire _363_;
  wire _364_;
  wire _365_;
  wire _366_;
  wire _367_;
  wire _368_;
  wire _369_;
  wire _370_;
  wire _371_;
  wire _372_;
  wire _373_;
  wire _374_;
  wire _375_;
  wire _376_;
  wire _377_;
  wire _378_;
  wire _379_;
  wire _380_;
  wire _381_;
  wire _382_;
  wire _383_;
  wire _384_;
  wire _385_;
  wire _386_;
  wire _387_;
  wire _388_;
  wire _389_;
  wire _390_;
  wire _391_;
  wire _392_;
  wire _393_;
  wire _394_;
  wire _395_;
  wire _396_;
  wire _397_;
  wire _398_;
  wire _399_;
  wire _400_;
  wire _401_;
  wire _402_;
  wire _403_;
  wire _404_;
  wire _405_;
  wire _406_;
  input [7:0] a;
  wire [7:0] a;
  input [7:0] b;
  wire [7:0] b;
  output [15:0] product;
  wire [15:0] product;
  assign product[0] = b[0] & a[0];
  assign _244_ = b[0] & a[1];
  assign _255_ = b[1] & a[0];
  assign product[1] = _255_ ^ _244_;
  assign _276_ = b[0] & a[2];
  assign _286_ = b[1] & a[1];
  assign _297_ = _286_ ^ _276_;
  assign _308_ = b[2] & a[0];
  assign _318_ = ~_308_;
  assign _329_ = _318_ ^ _297_;
  assign _339_ = _255_ & _244_;
  assign product[2] = ~(_339_ ^ _329_);
  assign _354_ = ~(b[0] & a[3]);
  assign _355_ = ~(b[1] & a[2]);
  assign _356_ = _355_ ^ _354_;
  assign _357_ = ~(b[2] & a[1]);
  assign _358_ = _357_ ^ _356_;
  assign _359_ = ~(_286_ & _276_);
  assign _360_ = _297_ & ~(_318_);
  assign _361_ = _359_ & ~(_360_);
  assign _362_ = _361_ ^ _358_;
  assign _363_ = b[3] & a[0];
  assign _364_ = ~_363_;
  assign _365_ = _364_ ^ _362_;
  assign _366_ = _339_ & ~(_329_);
  assign product[3] = ~(_366_ ^ _365_);
  assign _367_ = ~(b[0] & a[4]);
  assign _368_ = ~(b[1] & a[3]);
  assign _369_ = _368_ ^ _367_;
  assign _370_ = ~(b[2] & a[2]);
  assign _371_ = _370_ ^ _369_;
  assign _372_ = _355_ | _354_;
  assign _373_ = _356_ & ~(_357_);
  assign _374_ = _372_ & ~(_373_);
  assign _375_ = _374_ ^ _371_;
  assign _376_ = b[3] & a[1];
  assign _377_ = b[4] & a[0];
  assign _378_ = ~(_377_ ^ _376_);
  assign _379_ = _378_ ^ _375_;
  assign _380_ = _361_ | _358_;
  assign _381_ = _362_ & ~(_364_);
  assign _382_ = _380_ & ~(_381_);
  assign _383_ = ~(_382_ ^ _379_);
  assign _384_ = _366_ & ~(_365_);
  assign product[4] = ~(_384_ ^ _383_);
  assign _385_ = ~(b[0] & a[6]);
  assign _386_ = ~(b[1] & a[5]);
  assign _387_ = _386_ ^ _385_;
  assign _388_ = ~(b[2] & a[4]);
  assign _389_ = _388_ ^ _387_;
  assign _390_ = ~(b[0] & a[5]);
  assign _391_ = b[1] & a[4];
  assign _392_ = _390_ | ~(_391_);
  assign _393_ = b[2] & a[3];
  assign _394_ = _391_ ^ _390_;
  assign _395_ = _393_ & ~(_394_);
  assign _396_ = _392_ & ~(_395_);
  assign _397_ = _396_ ^ _389_;
  assign _398_ = b[3] & a[3];
  assign _399_ = b[4] & a[2];
  assign _400_ = _399_ ^ _398_;
  assign _401_ = ~(b[5] & a[1]);
  assign _402_ = _401_ ^ _400_;
  assign _403_ = _402_ ^ _397_;
  assign _404_ = ~(_394_ ^ _393_);
  assign _405_ = _368_ | _367_;
  assign _406_ = _369_ & ~(_370_);
  assign _000_ = _405_ & ~(_406_);
  assign _001_ = _000_ | ~(_404_);
  assign _002_ = b[3] & a[2];
  assign _003_ = b[4] & a[1];
  assign _004_ = _003_ ^ _002_;
  assign _005_ = b[5] & a[0];
  assign _006_ = _005_ ^ _004_;
  assign _007_ = _000_ ^ _404_;
  assign _008_ = _006_ & ~(_007_);
  assign _009_ = _001_ & ~(_008_);
  assign _010_ = _009_ ^ _403_;
  assign _011_ = ~(_003_ & _002_);
  assign _012_ = _005_ & _004_;
  assign _013_ = _011_ & ~(_012_);
  assign _014_ = b[6] & a[0];
  assign _015_ = _014_ ^ _013_;
  assign _016_ = ~(_015_ ^ _010_);
  assign _017_ = ~(_007_ ^ _006_);
  assign _018_ = _374_ | _371_;
  assign _019_ = _375_ & ~(_378_);
  assign _020_ = _018_ & ~(_019_);
  assign _021_ = _020_ | ~(_017_);
  assign _022_ = _377_ & _376_;
  assign _023_ = _020_ ^ _017_;
  assign _024_ = _022_ & ~(_023_);
  assign _025_ = _021_ & ~(_024_);
  assign _026_ = _025_ ^ _016_;
  assign _027_ = _023_ ^ _022_;
  assign _028_ = _382_ | _379_;
  assign _029_ = _028_ | _027_;
  assign _030_ = ~(_029_ ^ _026_);
  assign _031_ = _028_ ^ _027_;
  assign _032_ = _384_ & ~(_383_);
  assign _033_ = _032_ & _031_;
  assign product[6] = ~(_033_ ^ _030_);
  assign _034_ = b[0] & a[7];
  assign _035_ = _034_ ^ b[7];
  assign _036_ = ~(b[1] & a[6]);
  assign _037_ = _036_ ^ _035_;
  assign _038_ = _386_ | _385_;
  assign _039_ = _387_ & ~(_388_);
  assign _040_ = _038_ & ~(_039_);
  assign _041_ = _040_ ^ _037_;
  assign _042_ = ~(b[2] & a[5]);
  assign _043_ = ~(b[3] & a[4]);
  assign _044_ = _043_ ^ _042_;
  assign _045_ = ~(b[4] & a[3]);
  assign _046_ = _045_ ^ _044_;
  assign _047_ = _046_ ^ _041_;
  assign _048_ = _396_ | _389_;
  assign _049_ = _397_ & ~(_402_);
  assign _050_ = _048_ & ~(_049_);
  assign _051_ = _050_ ^ _047_;
  assign _052_ = _399_ & _398_;
  assign _053_ = _400_ & ~(_401_);
  assign _054_ = _053_ | _052_;
  assign _055_ = ~(b[5] & a[2]);
  assign _056_ = b[6] & a[1];
  assign _057_ = ~(_056_ ^ _055_);
  assign _058_ = b[7] & ~(a[0]);
  assign _059_ = ~_058_;
  assign _060_ = _059_ ^ _057_;
  assign _061_ = _060_ ^ _054_;
  assign _062_ = _061_ ^ _051_;
  assign _063_ = _009_ | _403_;
  assign _064_ = _010_ & ~(_015_);
  assign _065_ = _063_ & ~(_064_);
  assign _066_ = _065_ ^ _062_;
  assign _067_ = _014_ & ~(_013_);
  assign _068_ = ~_067_;
  assign _069_ = _068_ ^ _066_;
  assign _070_ = _016_ & ~(_025_);
  assign _071_ = _070_ ^ _069_;
  assign _072_ = _029_ | _026_;
  assign _073_ = _033_ & ~(_030_);
  assign _074_ = _072_ & ~(_073_);
  assign product[7] = _074_ ^ _071_;
  assign _075_ = b[1] & a[7];
  assign _076_ = ~(_075_ ^ _034_);
  assign _077_ = b[2] & a[6];
  assign _078_ = _077_ ^ _076_;
  assign _079_ = ~(_034_ & b[7]);
  assign _080_ = _035_ & ~(_036_);
  assign _081_ = _079_ & ~(_080_);
  assign _082_ = _081_ ^ _078_;
  assign _083_ = ~(b[3] & a[5]);
  assign _084_ = ~(b[4] & a[4]);
  assign _085_ = _084_ ^ _083_;
  assign _086_ = ~(b[5] & a[3]);
  assign _087_ = _086_ ^ _085_;
  assign _088_ = _087_ ^ _082_;
  assign _089_ = _040_ | _037_;
  assign _090_ = _041_ & ~(_046_);
  assign _091_ = _089_ & ~(_090_);
  assign _092_ = _091_ ^ _088_;
  assign _093_ = _043_ | _042_;
  assign _094_ = _044_ & ~(_045_);
  assign _095_ = _093_ & ~(_094_);
  assign _096_ = b[6] & a[2];
  assign _097_ = b[7] & ~(a[1]);
  assign _098_ = ~(_097_ ^ _096_);
  assign _099_ = _098_ ^ _095_;
  assign _100_ = _055_ | ~(_056_);
  assign _101_ = _057_ & ~(_059_);
  assign _102_ = _100_ & ~(_101_);
  assign _103_ = _102_ ^ _099_;
  assign _104_ = _103_ ^ _092_;
  assign _105_ = _050_ | _047_;
  assign _106_ = _051_ & ~(_061_);
  assign _107_ = _105_ & ~(_106_);
  assign _108_ = _107_ ^ _104_;
  assign _109_ = _054_ & ~(_060_);
  assign _110_ = ~_109_;
  assign _111_ = _110_ ^ _108_;
  assign _112_ = _065_ | _062_;
  assign _113_ = _066_ & ~(_068_);
  assign _114_ = _112_ & ~(_113_);
  assign _115_ = ~(_114_ ^ _111_);
  assign _116_ = _070_ & ~(_069_);
  assign _117_ = ~(_072_ | _071_);
  assign _118_ = _117_ | _116_;
  assign _119_ = _071_ | _030_;
  assign _120_ = _033_ & ~(_119_);
  assign _121_ = _120_ | _118_;
  assign product[8] = ~(_121_ ^ _115_);
  assign _122_ = b[2] & a[7];
  assign _123_ = _122_ ^ _076_;
  assign _124_ = ~(_075_ & _034_);
  assign _125_ = _077_ & ~(_076_);
  assign _126_ = _124_ & ~(_125_);
  assign _127_ = _126_ ^ _123_;
  assign _128_ = ~(b[3] & a[6]);
  assign _129_ = b[4] & a[5];
  assign _130_ = ~(_129_ ^ _128_);
  assign _131_ = b[5] & a[4];
  assign _132_ = ~_131_;
  assign _133_ = _132_ ^ _130_;
  assign _134_ = _133_ ^ _127_;
  assign _135_ = _081_ | _078_;
  assign _136_ = _082_ & ~(_087_);
  assign _137_ = _135_ & ~(_136_);
  assign _138_ = _137_ ^ _134_;
  assign _139_ = _084_ | _083_;
  assign _140_ = _085_ & ~(_086_);
  assign _141_ = _139_ & ~(_140_);
  assign _142_ = b[6] & a[3];
  assign _143_ = b[7] & ~(a[2]);
  assign _144_ = ~(_143_ ^ _142_);
  assign _145_ = ~(_144_ ^ _141_);
  assign _146_ = _097_ & _096_;
  assign _147_ = _146_ ^ _145_;
  assign _148_ = _147_ ^ _138_;
  assign _149_ = _091_ | _088_;
  assign _150_ = _092_ & ~(_103_);
  assign _151_ = _149_ & ~(_150_);
  assign _152_ = _151_ ^ _148_;
  assign _153_ = _098_ | _095_;
  assign _154_ = _099_ & ~(_102_);
  assign _155_ = _153_ & ~(_154_);
  assign _156_ = ~(_155_ ^ _152_);
  assign _157_ = _107_ | _104_;
  assign _158_ = _108_ & ~(_110_);
  assign _159_ = _157_ & ~(_158_);
  assign _160_ = _159_ ^ _156_;
  assign _161_ = _114_ | _111_;
  assign _162_ = _121_ & ~(_115_);
  assign _163_ = _161_ & ~(_162_);
  assign product[9] = _163_ ^ _160_;
  assign _164_ = _122_ & ~(_076_);
  assign _165_ = _124_ & ~(_164_);
  assign _166_ = _165_ ^ _123_;
  assign _167_ = b[3] & a[7];
  assign _168_ = b[4] & a[6];
  assign _169_ = ~(_168_ ^ _167_);
  assign _170_ = b[5] & a[5];
  assign _171_ = _170_ ^ _169_;
  assign _172_ = _171_ ^ _166_;
  assign _173_ = _126_ | _123_;
  assign _174_ = _127_ & ~(_133_);
  assign _175_ = _173_ & ~(_174_);
  assign _176_ = _175_ ^ _172_;
  assign _177_ = _128_ | ~(_129_);
  assign _178_ = _130_ & ~(_132_);
  assign _179_ = _177_ & ~(_178_);
  assign _180_ = b[6] & a[4];
  assign _181_ = b[7] & ~(a[3]);
  assign _182_ = ~(_181_ ^ _180_);
  assign _183_ = ~(_182_ ^ _179_);
  assign _184_ = _143_ & _142_;
  assign _185_ = _184_ ^ _183_;
  assign _186_ = _185_ ^ _176_;
  assign _187_ = _137_ | _134_;
  assign _188_ = _138_ & ~(_147_);
  assign _189_ = _187_ & ~(_188_);
  assign _190_ = _189_ ^ _186_;
  assign _191_ = _144_ | _141_;
  assign _192_ = _146_ & ~(_145_);
  assign _193_ = _191_ & ~(_192_);
  assign _194_ = _193_ ^ _190_;
  assign _195_ = _151_ | _148_;
  assign _196_ = _152_ & ~(_155_);
  assign _197_ = _195_ & ~(_196_);
  assign _198_ = ~(_197_ ^ _194_);
  assign _199_ = _156_ & ~(_159_);
  assign _200_ = ~(_161_ | _160_);
  assign _201_ = _200_ | _199_;
  assign _202_ = _160_ | _115_;
  assign _203_ = _202_ | ~(_121_);
  assign _204_ = _203_ & ~(_201_);
  assign product[10] = _204_ ^ _198_;
  assign _205_ = b[4] & a[7];
  assign _206_ = ~(_205_ ^ _167_);
  assign _207_ = b[5] & a[6];
  assign _208_ = _207_ ^ _206_;
  assign _209_ = _208_ ^ _166_;
  assign _210_ = _165_ | _123_;
  assign _211_ = _166_ & ~(_171_);
  assign _212_ = _210_ & ~(_211_);
  assign _213_ = _212_ ^ _209_;
  assign _214_ = ~(_168_ & _167_);
  assign _215_ = _170_ & ~(_169_);
  assign _216_ = _214_ & ~(_215_);
  assign _217_ = b[6] & a[5];
  assign _218_ = b[7] & ~(a[4]);
  assign _219_ = ~(_218_ ^ _217_);
  assign _220_ = ~(_219_ ^ _216_);
  assign _221_ = _181_ & _180_;
  assign _222_ = _221_ ^ _220_;
  assign _223_ = _222_ ^ _213_;
  assign _224_ = _175_ | _172_;
  assign _225_ = _176_ & ~(_185_);
  assign _226_ = _224_ & ~(_225_);
  assign _227_ = _226_ ^ _223_;
  assign _228_ = _182_ | _179_;
  assign _229_ = _184_ & ~(_183_);
  assign _230_ = _228_ & ~(_229_);
  assign _231_ = _230_ ^ _227_;
  assign _232_ = _189_ | _186_;
  assign _233_ = _190_ & ~(_193_);
  assign _234_ = _232_ & ~(_233_);
  assign _235_ = ~(_234_ ^ _231_);
  assign _236_ = _197_ | _194_;
  assign _237_ = ~(_204_ | _198_);
  assign _238_ = _236_ & ~(_237_);
  assign product[11] = _238_ ^ _235_;
  assign _239_ = b[5] & a[7];
  assign _240_ = _239_ ^ _206_;
  assign _241_ = _240_ ^ _166_;
  assign _242_ = ~_241_;
  assign _243_ = _166_ & ~(_208_);
  assign _245_ = _210_ & ~(_243_);
  assign _246_ = _245_ ^ _242_;
  assign _247_ = ~(_205_ & _167_);
  assign _248_ = _207_ & ~(_206_);
  assign _249_ = _247_ & ~(_248_);
  assign _250_ = b[6] & a[6];
  assign _251_ = b[7] & ~(a[5]);
  assign _252_ = ~(_251_ ^ _250_);
  assign _253_ = ~(_252_ ^ _249_);
  assign _254_ = _218_ & _217_;
  assign _256_ = _254_ ^ _253_;
  assign _257_ = ~(_256_ ^ _246_);
  assign _258_ = _212_ | _209_;
  assign _259_ = _213_ & ~(_222_);
  assign _260_ = _258_ & ~(_259_);
  assign _261_ = _260_ ^ _257_;
  assign _262_ = _219_ | _216_;
  assign _263_ = _221_ & ~(_220_);
  assign _264_ = _262_ & ~(_263_);
  assign _265_ = _264_ ^ _261_;
  assign _266_ = _226_ | _223_;
  assign _267_ = _227_ & ~(_230_);
  assign _268_ = _266_ & ~(_267_);
  assign _269_ = ~(_268_ ^ _265_);
  assign _270_ = _234_ | _231_;
  assign _271_ = ~(_236_ | _235_);
  assign _272_ = _270_ & ~(_271_);
  assign _273_ = _235_ | _198_;
  assign _274_ = _201_ & ~(_273_);
  assign _275_ = _272_ & ~(_274_);
  assign _277_ = _273_ | _202_;
  assign _278_ = _121_ & ~(_277_);
  assign _279_ = _275_ & ~(_278_);
  assign product[12] = _279_ ^ _269_;
  assign _280_ = _166_ & ~(_240_);
  assign _281_ = _210_ & ~(_280_);
  assign _282_ = _281_ ^ _242_;
  assign _283_ = _239_ & ~(_206_);
  assign _284_ = _247_ & ~(_283_);
  assign _285_ = b[6] & a[7];
  assign _287_ = b[7] & ~(a[6]);
  assign _288_ = ~(_287_ ^ _285_);
  assign _289_ = ~(_288_ ^ _284_);
  assign _290_ = _251_ & _250_;
  assign _291_ = _290_ ^ _289_;
  assign _292_ = ~(_291_ ^ _282_);
  assign _293_ = _245_ | _241_;
  assign _294_ = ~(_256_ | _246_);
  assign _295_ = _293_ & ~(_294_);
  assign _296_ = ~(_295_ ^ _292_);
  assign _298_ = _252_ | _249_;
  assign _299_ = _254_ & ~(_253_);
  assign _300_ = _298_ & ~(_299_);
  assign _301_ = ~(_300_ ^ _296_);
  assign _302_ = _260_ | _257_;
  assign _303_ = _261_ & ~(_264_);
  assign _304_ = _302_ & ~(_303_);
  assign _305_ = ~(_304_ ^ _301_);
  assign _306_ = _268_ | _265_;
  assign _307_ = ~(_279_ | _269_);
  assign _309_ = _306_ & ~(_307_);
  assign product[13] = _309_ ^ _305_;
  assign _310_ = a[7] | ~(b[7]);
  assign _311_ = _310_ ^ _285_;
  assign _312_ = ~(_311_ ^ _284_);
  assign _313_ = _287_ & _285_;
  assign _314_ = _313_ ^ _312_;
  assign _315_ = ~(_314_ ^ _282_);
  assign _316_ = _281_ | _241_;
  assign _317_ = ~(_291_ | _282_);
  assign _319_ = _316_ & ~(_317_);
  assign _320_ = ~(_319_ ^ _315_);
  assign _321_ = _288_ | _284_;
  assign _322_ = _290_ & ~(_289_);
  assign _323_ = _321_ & ~(_322_);
  assign _324_ = ~(_323_ ^ _320_);
  assign _325_ = _295_ | _292_;
  assign _326_ = ~(_300_ | _296_);
  assign _327_ = _325_ & ~(_326_);
  assign _328_ = ~(_327_ ^ _324_);
  assign _330_ = _304_ | _301_;
  assign _331_ = ~(_306_ | _305_);
  assign _332_ = _330_ & ~(_331_);
  assign _333_ = _305_ | _269_;
  assign _334_ = ~(_333_ | _279_);
  assign _335_ = _332_ & ~(_334_);
  assign product[14] = _335_ ^ _328_;
  assign _336_ = _285_ & ~(_310_);
  assign _337_ = _336_ ^ _312_;
  assign _338_ = _337_ ^ _282_;
  assign _340_ = ~(_314_ | _282_);
  assign _341_ = _316_ & ~(_340_);
  assign _342_ = _341_ ^ _338_;
  assign _343_ = _311_ | _284_;
  assign _344_ = _313_ & ~(_312_);
  assign _345_ = _343_ & ~(_344_);
  assign _346_ = _345_ ^ _342_;
  assign _347_ = _319_ | _315_;
  assign _348_ = ~(_323_ | _320_);
  assign _349_ = _347_ & ~(_348_);
  assign _350_ = _349_ ^ _346_;
  assign _351_ = _327_ | _324_;
  assign _352_ = ~(_335_ | _328_);
  assign _353_ = _351_ & ~(_352_);
  assign product[15] = _353_ ^ _350_;
  assign product[5] = _032_ ^ _031_;
endmodule

bit_vector/multiply_signed.vcd
$date
	Fri Aug 21 05:18:07 2026
$end
$version
	Icarus Verilog
$end
$timescale
	1ps
$end
$scope module multiply_signed $end
$var wire 8 ! a [7:0] $end
$var wire 8 " b [7:0] $end
$var wire 16 # product [15:0] $end
$upscope $end
$enddefinitions $end
$comment Show the parameter values. $end
$dumpall
$end
#0
$dumpvars
b11110 #
b110 "
b101 !
$end
#1000
b0 "
b0 #
b11001110 !
#2000
b1111111111001110 #
b11111011 "
b1010 !
#3000
b11111101 "
b1100 #
b11111100 !
#4000
b1 "
b1111111110110011 #
b10110011 !
#5000
b1111111 "
b11111100000001 #
b1111111 !
#6000
b10000000 "
b100000000000000 #
b10000000 !
#7000
b1100000010000000 #
b1111111 "
