bit_vector/sub_signed_netlist.v
/* Generated by Yosys 0.33 (git sha1 2584903a060) */

module sub_signed(a, b, diff);
  wire _00_;
  wire _01_;
  wire _02_;
  wire _03_;
  wire _04_;
  wire _05_;
  wire _06_;
  wire _07_;
  wire _08_;
  wire _09_;
  wire _10_;
  wire _11_;
  wire _12_;
  wire _13_;
  wire _14_;
  wire _15_;
  wire _16_;
  wire _17_;
  wire _18_;
  wire _19_;
  wire _20_;
  wire _21_;
  wire _22_;
  wire _23_;
  wire _24_;
  wire _25_;
  wire _26_;
  wire _27_;
  wire _28_;
  wire _29_;
  wire _30_;
  wire _31_;
  input [7:0] a;
  wire [7:0] a;
  input [7:0] b;
  wire [7:0] b;
  output [7:0] diff;
  wire [7:0] diff;
  assign diff[0] = a[0] ^ b[0];
  assign _00_ = ~(a[1] ^ b[1]);
  assign _01_ = b[0] & ~(a[0]);
  assign diff[1] = ~(_01_ ^ _00_);
  assign _02_ = a[2] ^ b[2];
  assign _03_ = a[1] & ~(b[1]);
  assign _04_ = _00_ & ~(_01_);
  assign _05_ = _04_ | _03_;
  assign diff[2] = ~(_05_ ^ _02_);
  assign _06_ = a[3] ^ b[3];
  assign _07_ = b[2] | ~(a[2]);
  assign _08_ = _05_ & ~(_02_);
  assign _09_ = _07_ & ~(_08_);
  assign diff[3] = _09_ ^ _06_;
  assign _10_ = a[4] ^ b[4];
  assign _11_ = b[3] | ~(a[3]);
  assign _12_ = ~(_07_ | _06_);
  assign _13_ = _11_ & ~(_12_);
  assign _14_ = _06_ | _02_;
  assign _15_ = _05_ & ~(_14_);
  assign _16_ = _13_ & ~(_15_);
  assign diff[4] = _16_ ^ _10_;
  assign _17_ = a[5] ^ b[5];
  assign _18_ = b[4] | ~(a[4]);
  assign _19_ = ~(_16_ | _10_);
  assign _20_ = _18_ & ~(_19_);
  assign diff[5] = _20_ ^ _17_;
  assign _21_ = a[6] ^ b[6];
  assign _22_ = b[5] | ~(a[5]);
  assign _23_ = ~(_18_ | _17_);
  assign _24_ = _22_ & ~(_23_);
  assign _25_ = _17_ | _10_;
  assign _26_ = ~(_25_ | _16_);
  assign _27_ = _24_ & ~(_26_);
  assign diff[6] = _27_ ^ _21_;
  assign _28_ = a[7] ^ b[7];
  assign _29_ = b[6] | ~(a[6]);
  assign _30_ = ~(_27_ | _21_);
  assign _31_ = _29_ & ~(_30_);
  assign diff[7] = _31_ ^ _28_;
endmodule

bit_vector/sub_signed.vcd
$date
	Thu Aug 20 11:00:25 2026
$end
$version
	Icarus Verilog
$end
$timescale
	1ps
$end
$scope module sub_signed $end
$var wire 8 ! a [7:0] $end
$var wire 8 " b [7:0] $end
$var wire 8 # diff [7:0] $end
$upscope $end
$enddefinitions $end
$comment Show the parameter values. $end
$dumpall
$end
#0
$dumpvars
b101 #
b101 "
b1010 !
$end
#1000
b111 "
b0 #
b111 !
#2000
b1010 "
b11111011 #
b101 !
#3000
b11110 "
b10110000 #
b11001110 !
#4000
b11100010 "
b1010 #
b11101100 !
#5000
b0 "
b1111111 #
b1111111 !
#6000
b10000000 #
b11111111 "
#7000
b110010 "
b1101010 #
b10011100 !
