three_bit/design_combo.sv
module combo_gate (
    input  wire a,
    input  wire b,
    input  wire c,
    output wire y
);

    assign y = (a & b)|c;

    initial begin
        $dumpfile("dump_combo.vcd");
        $dumpvars(0,combo_gate);
    end

endmodule

three_bit/dump_combo.vcd
$date
	Thu Aug 20 11:48:53 2026
$end
$version
	Icarus Verilog
$end
$timescale
	1ps
$end
$scope module combo_gate $end
$var wire 1 ! a $end
$var wire 1 " b $end
$var wire 1 # c $end
$var wire 1 $ y $end
$upscope $end
$enddefinitions $end
#0
$dumpvars
0$
0#
0"
0!
$end
#1000
1$
1#
#2000
0$
0#
1"
#3000
1$
1#
#4000
0$
0#
0"
1!
#5000
1$
1#
#6000
0#
1"
#7000
1#
