Seq/adder.sv
module adder (
    input  wire signed [7:0] a,
    input  wire signed [7:0] b,
    output wire signed [8:0] y   // 5 bits to capture carry-out
);
    // Pure arithmetic addition
    assign y = a + b;

    // Dump waveform for GTKWave
    initial begin
        $dumpfile("adder.vcd");
        $dumpvars(0, adder);
    end
endmodule

Seq/adder.vcd
$date
	Thu Aug 20 14:50:55 2026
$end
$version
	Icarus Verilog
$end
$timescale
	1ps
$end
$scope module adder $end
$var wire 8 ! a [7:0] $end
$var wire 8 " b [7:0] $end
$var wire 9 # y [8:0] $end
$upscope $end
$enddefinitions $end
$comment Show the parameter values. $end
$dumpall
$end
#0
$dumpvars
b100000000 #
b10000000 "
b10000000 !
$end
#1000
b100000001 #
b10000001 "
#2000
b100000010 #
b10000010 "
#3000
b100000011 #
b10000011 "
#4000
b100000100 #
b10000100 "
#5000
b100000101 #
b10000101 "
#6000
b100000110 #
b10000110 "
#7000
b100000111 #
b10000111 "
#8000
b100001000 #
b10001000 "
#9000
b100001001 #
b10001001 "
#10000
b100001010 #
b10001010 "
#11000
b100001011 #
b10001011 "
#12000
b100001100 #
b10001100 "
#13000
b100001101 #
b10001101 "
#14000
b100001110 #
b10001110 "
#15000
b100001111 #
b10001111 "
#16000
b100010000 #
b10010000 "
#17000
b100010001 #
b10010001 "
#18000
b100010010 #
b10010010 "
#19000
b100010011 #
b10010011 "
#20000
b100010100 #
b10010100 "
#21000
b100010101 #
b10010101 "
#22000
b100010110 #
b10010110 "
#23000
b100010111 #
b10010111 "
#24000
b100011000 #
b10011000 "
#25000
b100011001 #
b10011001 "
#26000
b100011010 #
b10011010 "
#27000
b100011011 #
b10011011 "
#28000
b100011100 #
b10011100 "
#29000
b100011101 #
b10011101 "
#30000
b100011110 #
b10011110 "
#31000
b100011111 #
b10011111 "
#32000
b100100000 #
b10100000 "
#33000
b100100001 #
b10100001 "
#34000
b100100010 #
b10100010 "
#35000
b100100011 #
b10100011 "
#36000
b100100100 #
b10100100 "
#37000
b100100101 #
b10100101 "
#38000
b100100110 #
b10100110 "
#39000
b100100111 #
b10100111 "
#40000
b100101000 #
b10101000 "
#41000
b100101001 #
b10101001 "
#42000
b100101010 #
b10101010 "
#43000
b100101011 #
b10101011 "
#44000
b100101100 #
b10101100 "
#45000
b100101101 #
b10101101 "
#46000
b100101110 #
b10101110 "
#47000
b100101111 #
b10101111 "
#48000
b100110000 #
b10110000 "
#49000
b100110001 #
b10110001 "
#50000
b100110010 #
b10110010 "
#51000
b100110011 #
b10110011 "
#52000
b100110100 #
b10110100 "
#53000
b100110101 #
b10110101 "
#54000
b100110110 #
b10110110 "
#55000
b100110111 #
b10110111 "
#56000
b100111000 #
b10111000 "
#57000
b100111001 #
b10111001 "
#58000
b100111010 #
b10111010 "
#59000
b100111011 #
b10111011 "
#60000
b100111100 #
b10111100 "
#61000
b100111101 #
b10111101 "
#62000
b100111110 #
b10111110 "
#63000
b100111111 #
b10111111 "
#64000
b101000000 #
b11000000 "
#65000
b101000001 #
b11000001 "
#66000
b101000010 #
b11000010 "
#67000
b101000011 #
b11000011 "
#68000
b101000100 #
b11000100 "
#69000
b101000101 #
b11000101 "
#70000
b101000110 #
b11000110 "
#71000
b101000111 #
b11000111 "
#72000
b101001000 #
b11001000 "
#73000
b101001001 #
b11001001 "
#74000
b101001010 #
b11001010 "
#75000
b101001011 #
b11001011 "
#76000
b101001100 #
b11001100 "
#77000
b101001101 #
b11001101 "
#78000
b101001110 #
b11001110 "
#79000
b101001111 #
b11001111 "
#80000
b101010000 #
b11010000 "
#81000
b101010001 #
b11010001 "
#82000
b101010010 #
b11010010 "
#83000
b101010011 #
b11010011 "
#84000
b101010100 #
b11010100 "
#85000
b101010101 #
b11010101 "
#86000
b101010110 #
b11010110 "
#87000
b101010111 #
b11010111 "
#88000
b101011000 #
b11011000 "
#89000
b101011001 #
b11011001 "
#90000
b101011010 #
b11011010 "
#91000
b101011011 #
b11011011 "
#92000
b101011100 #
b11011100 "
#93000
b101011101 #
b11011101 "
#94000
b101011110 #
b11011110 "
#95000
b101011111 #
b11011111 "
#96000
b101100000 #
b11100000 "
#97000
b101100001 #
b11100001 "
#98000
b101100010 #
b11100010 "
#99000
b101100011 #
b11100011 "
#100000
b101100100 #
b11100100 "
#101000
b101100101 #
b11100101 "
#102000
b101100110 #
b11100110 "
#103000
b101100111 #
b11100111 "
#104000
b101101000 #
b11101000 "
#105000
b101101001 #
b11101001 "
#106000
b101101010 #
b11101010 "
#107000
b101101011 #
b11101011 "
#108000
b101101100 #
b11101100 "
#109000
b101101101 #
b11101101 "
#110000
b101101110 #
b11101110 "
#111000
b101101111 #
b11101111 "
#112000
b101110000 #
b11110000 "
#113000
b101110001 #
b11110001 "
#114000
b101110010 #
b11110010 "
#115000
b101110011 #
b11110011 "
#116000
b101110100 #
b11110100 "
#117000
b101110101 #
b11110101 "
#118000
b101110110 #
b11110110 "
#119000
b101110111 #
b11110111 "
#120000
b101111000 #
b11111000 "
#121000
b101111001 #
b11111001 "
#122000
b101111010 #
b11111010 "
#123000
b101111011 #
b11111011 "
#124000
b101111100 #
b11111100 "
#125000
b101111101 #
b11111101 "
#126000
b101111110 #
b11111110 "
#127000
b101111111 #
b11111111 "
#128000
b110000000 #
b0 "
#129000
b110000001 #
b1 "
#130000
b110000010 #
b10 "
#131000
b110000011 #
b11 "
#132000
b110000100 #
b100 "
#133000
b110000101 #
b101 "
#134000
b110000110 #
b110 "
#135000
b110000111 #
b111 "
#136000
b110001000 #
b1000 "
#137000
b110001001 #
b1001 "
#138000
b110001010 #
b1010 "
#139000
b110001011 #
b1011 "
#140000
b110001100 #
b1100 "
#141000
b110001101 #
b1101 "
#142000
b110001110 #
b1110 "
#143000
b110001111 #
b1111 "
#144000
b110010000 #
b10000 "
#145000
b110010001 #
b10001 "
#146000
b110010010 #
b10010 "
#147000
b110010011 #
b10011 "
#148000
b110010100 #
b10100 "
#149000
b110010101 #
b10101 "
#150000
b110010110 #
b10110 "
#151000
b110010111 #
b10111 "
#152000
b110011000 #
b11000 "
#153000
b110011001 #
b11001 "
#154000
b110011010 #
b11010 "
#155000
b110011011 #
b11011 "
#156000
b110011100 #
b11100 "
#157000
b110011101 #
b11101 "
#158000
b110011110 #
b11110 "
#159000
b110011111 #
b11111 "
#160000
b110100000 #
b100000 "
#161000
b110100001 #
b100001 "
#162000
b110100010 #
b100010 "
#163000
b110100011 #
b100011 "
#164000
b110100100 #
b100100 "
#165000
b110100101 #
b100101 "
#166000
b110100110 #
b100110 "
#167000
b110100111 #
b100111 "
#168000
b110101000 #
b101000 "
#169000
b110101001 #
b101001 "
#170000
b110101010 #
b101010 "
#171000
b110101011 #
b101011 "
#172000
b110101100 #
b101100 "
#173000
b110101101 #
b101101 "
#174000
b110101110 #
b101110 "
#175000
b110101111 #
b101111 "
#176000
b110110000 #
b110000 "
#177000
b110110001 #
b110001 "
#178000
b110110010 #
b110010 "
#179000
b110110011 #
b110011 "
#180000
b110110100 #
b110100 "
#181000
b110110101 #
b110101 "
#182000
b110110110 #
b110110 "
#183000
b110110111 #
b110111 "
#184000
b110111000 #
b111000 "
#185000
b110111001 #
b111001 "
#186000
b110111010 #
b111010 "
#187000
b110111011 #
b111011 "
#188000
b110111100 #
b111100 "
#189000
b110111101 #
b111101 "
#190000
b110111110 #
b111110 "
#191000
b110111111 #
b111111 "
#192000
b111000000 #
b1000000 "
#193000
b111000001 #
b1000001 "
#194000
b111000010 #
b1000010 "
#195000
b111000011 #
b1000011 "
#196000
b111000100 #
b1000100 "
#197000
b111000101 #
b1000101 "
#198000
b111000110 #
b1000110 "
#199000
b111000111 #
b1000111 "
#200000
b111001000 #
b1001000 "
#201000
b111001001 #
b1001001 "
#202000
b111001010 #
b1001010 "
#203000
b111001011 #
b1001011 "
#204000
b111001100 #
b1001100 "
#205000
b111001101 #
b1001101 "
#206000
b111001110 #
b1001110 "
#207000
b111001111 #
b1001111 "
#208000
b111010000 #
b1010000 "
#209000
b111010001 #
b1010001 "
#210000
b111010010 #
b1010010 "
#211000
b111010011 #
b1010011 "
#212000
b111010100 #
b1010100 "
#213000
b111010101 #
b1010101 "
#214000
b111010110 #
b1010110 "
#215000
b111010111 #
b1010111 "
#216000
b111011000 #
b1011000 "
#217000
b111011001 #
b1011001 "
#218000
b111011010 #
b1011010 "
#219000
b111011011 #
b1011011 "
#220000
b111011100 #
b1011100 "
#221000
b111011101 #
b1011101 "
#222000
b111011110 #
b1011110 "
#223000
b111011111 #
b1011111 "
#224000
b111100000 #
b1100000 "
#225000
b111100001 #
b1100001 "
#226000
b111100010 #
b1100010 "
#227000
b111100011 #
b1100011 "
#228000
b111100100 #
b1100100 "
#229000
b111100101 #
b1100101 "
#230000
b111100110 #
b1100110 "
#231000
b111100111 #
b1100111 "
#232000
b111101000 #
b1101000 "
#233000
b111101001 #
b1101001 "
#234000
b111101010 #
b1101010 "
#235000
b111101011 #
b1101011 "
#236000
b111101100 #
b1101100 "
#237000
b111101101 #
b1101101 "
#238000
b111101110 #
b1101110 "
#239000
b111101111 #
b1101111 "
#240000
b111110000 #
b1110000 "
#241000
b111110001 #
b1110001 "
#242000
b111110010 #
b1110010 "
#243000
b111110011 #
b1110011 "
#244000
b111110100 #
b1110100 "
#245000
b111110101 #
b1110101 "
#246000
b111110110 #
b1110110 "
#247000
b111110111 #
b1110111 "
#248000
b111111000 #
b1111000 "
#249000
b111111001 #
b1111001 "
#250000
b111111010 #
b1111010 "
#251000
b111111011 #
b1111011 "
#252000
b111111100 #
b1111100 "
#253000
b111111101 #
b1111101 "
#254000
b111111110 #
b1111110 "
#255000
b111111111 #
b1111111 "
#256000
b10000000 "
b100000001 #
b10000001 !
#257000
b100000010 #
b10000001 "
#258000
b100000011 #
b10000010 "
#259000
b100000100 #
b10000011 "
#260000
b100000101 #
b10000100 "
#261000
b100000110 #
b10000101 "
#262000
b100000111 #
b10000110 "
#263000
b100001000 #
b10000111 "
#264000
b100001001 #
b10001000 "
#265000
b100001010 #
b10001001 "
#266000
b100001011 #
b10001010 "
#267000
b100001100 #
b10001011 "
#268000
b100001101 #
b10001100 "
#269000
b100001110 #
b10001101 "
#270000
b100001111 #
b10001110 "
#271000
b100010000 #
b10001111 "
#272000
b100010001 #
b10010000 "
#273000
b100010010 #
b10010001 "
#274000
b100010011 #
b10010010 "
#275000
b100010100 #
b10010011 "
#276000
b100010101 #
b10010100 "
#277000
b100010110 #
b10010101 "
#278000
b100010111 #
b10010110 "
#279000
b100011000 #
b10010111 "
#280000
b100011001 #
b10011000 "
#281000
b100011010 #
b10011001 "
#282000
b100011011 #
b10011010 "
#283000
b100011100 #
b10011011 "
#284000
b100011101 #
b10011100 "
#285000
b100011110 #
b10011101 "
#286000
b100011111 #
b10011110 "
#287000
b100100000 #
b10011111 "
#288000
b100100001 #
b10100000 "
#289000
b100100010 #
b10100001 "
#290000
b100100011 #
b10100010 "
#291000
b100100100 #
b10100011 "
#292000
b100100101 #
b10100100 "
#293000
b100100110 #
b10100101 "
#294000
b100100111 #
b10100110 "
#295000
b100101000 #
b10100111 "
#296000
b100101001 #
b10101000 "
#297000
b100101010 #
b10101001 "
#298000
b100101011 #
b10101010 "
#299000
b100101100 #
b10101011 "
#300000
b100101101 #
b10101100 "
#301000
b100101110 #
b10101101 "
#302000
b100101111 #
b10101110 "
#303000
b100110000 #
b10101111 "
#304000
b100110001 #
b10110000 "
#305000
b100110010 #
b10110001 "
#306000
b100110011 #
b10110010 "
#307000
b100110100 #
b10110011 "
#308000
b100110101 #
b10110100 "
#309000
b100110110 #
b10110101 "
#310000
b100110111 #
b10110110 "
#311000
b100111000 #
b10110111 "
#312000
b100111001 #
b10111000 "
#313000
b100111010 #
b10111001 "
#314000
b100111011 #
b10111010 "
#315000
b100111100 #
b10111011 "
#316000
b100111101 #
b10111100 "
#317000
b100111110 #
b10111101 "
#318000
b100111111 #
b10111110 "
#319000
b101000000 #
b10111111 "
#320000
b101000001 #
b11000000 "
#321000
b101000010 #
b11000001 "
#322000
b101000011 #
b11000010 "
#323000
b101000100 #
b11000011 "
#324000
b101000101 #
b11000100 "
#325000
b101000110 #
b11000101 "
#326000
b101000111 #
b11000110 "
#327000
b101001000 #
b11000111 "
#328000
b101001001 #
b11001000 "
#329000
b101001010 #
b11001001 "
#330000
b101001011 #
b11001010 "
#331000
b101001100 #
b11001011 "
#332000
b101001101 #
b11001100 "
#333000
b101001110 #
b11001101 "
#334000
b101001111 #
b11001110 "
#335000
b101010000 #
b11001111 "
#336000
b101010001 #
b11010000 "
#337000
b101010010 #
b11010001 "
#338000
b101010011 #
b11010010 "
#339000
b101010100 #
b11010011 "
#340000
b101010101 #
b11010100 "
#341000
b101010110 #
b11010101 "
#342000
b101010111 #
b11010110 "
#343000
b101011000 #
b11010111 "
#344000
b101011001 #
b11011000 "
#345000
b101011010 #
b11011001 "
#346000
b101011011 #
b11011010 "
#347000
b101011100 #
b11011011 "
#348000
b101011101 #
b11011100 "
#349000
b101011110 #
b11011101 "
#350000
b101011111 #
b11011110 "
#351000
b101100000 #
b11011111 "
#352000
b101100001 #
b11100000 "
#353000
b101100010 #
b11100001 "
#354000
b101100011 #
b11100010 "
#355000
b101100100 #
b11100011 "
#356000
b101100101 #
b11100100 "
#357000
b101100110 #
b11100101 "
#358000
b101100111 #
b11100110 "
#359000
b101101000 #
b11100111 "
#360000
b101101001 #
b11101000 "
#361000
b101101010 #
b11101001 "
#362000
b101101011 #
b11101010 "
#363000
b101101100 #
b11101011 "
#364000
b101101101 #
b11101100 "
#365000
b101101110 #
b11101101 "
#366000
b101101111 #
b11101110 "
#367000
b101110000 #
b11101111 "
#368000
b101110001 #
b11110000 "
#369000
b101110010 #
b11110001 "
#370000
b101110011 #
b11110010 "
#371000
b101110100 #
b11110011 "
#372000
b101110101 #
b11110100 "
#373000
b101110110 #
b11110101 "
#374000
b101110111 #
b11110110 "
#375000
b101111000 #
b11110111 "
#376000
b101111001 #
b11111000 "
#377000
b101111010 #
b11111001 "
#378000
b101111011 #
b11111010 "
#379000
b101111100 #
b11111011 "
#380000
b101111101 #
b11111100 "
#381000
b101111110 #
b11111101 "
#382000
b101111111 #
b11111110 "
#383000
b110000000 #
b11111111 "
#384000
b110000001 #
b0 "
#385000
b110000010 #
b1 "
#386000
b110000011 #
b10 "
#387000
b110000100 #
b11 "
#388000
b110000101 #
b100 "
#389000
b110000110 #
b101 "
#390000
b110000111 #
b110 "
#391000
b110001000 #
b111 "
#392000
b110001001 #
b1000 "
#393000
b110001010 #
b1001 "
#394000
b110001011 #
b1010 "
#395000
b110001100 #
b1011 "
#396000
b110001101 #
b1100 "
#397000
b110001110 #
b1101 "
#398000
b110001111 #
b1110 "
#399000
b110010000 #
b1111 "
#400000
b110010001 #
b10000 "
#401000
b110010010 #
b10001 "
#402000
b110010011 #
b10010 "
#403000
b110010100 #
b10011 "
#404000
b110010101 #
b10100 "
#405000
b110010110 #
b10101 "
#406000
b110010111 #
b10110 "
#407000
b110011000 #
b10111 "
#408000
b110011001 #
b11000 "
#409000
b110011010 #
b11001 "
#410000
b110011011 #
b11010 "
#411000
b110011100 #
b11011 "
#412000
b110011101 #
b11100 "
#413000
b110011110 #
b11101 "
#414000
b110011111 #
b11110 "
#415000
b110100000 #
b11111 "
#416000
b110100001 #
b100000 "
#417000
b110100010 #
b100001 "
#418000
b110100011 #
b100010 "
#419000
b110100100 #
b100011 "
#420000
b110100101 #
b100100 "
#421000
b110100110 #
b100101 "
#422000
b110100111 #
b100110 "
#423000
b110101000 #
b100111 "
#424000
b110101001 #
b101000 "
#425000
b110101010 #
b101001 "
#426000
b110101011 #
b101010 "
#427000
b110101100 #
b101011 "
#428000
b110101101 #
b101100 "
#429000
b110101110 #
b101101 "
#430000
b110101111 #
b101110 "
#431000
b110110000 #
b101111 "
#432000
b110110001 #
b110000 "
#433000
b110110010 #
b110001 "
#434000
b110110011 #
b110010 "
#435000
b110110100 #
b110011 "
#436000
b110110101 #
b110100 "
#437000
b110110110 #
b110101 "
#438000
b110110111 #
b110110 "
#439000
b110111000 #
b110111 "
#440000
b110111001 #
b111000 "
#441000
b110111010 #
b111001 "
#442000
b110111011 #
b111010 "
#443000
b110111100 #
b111011 "
#444000
b110111101 #
b111100 "
#445000
b110111110 #
b111101 "
#446000
b110111111 #
b111110 "
#447000
b111000000 #
b111111 "
#448000
b111000001 #
b1000000 "
#449000
b111000010 #
b1000001 "
#450000
b111000011 #
b1000010 "
#451000
b111000100 #
b1000011 "
#452000
b111000101 #
b1000100 "
#453000
b111000110 #
b1000101 "
#454000
b111000111 #
b1000110 "
#455000
b111001000 #
b1000111 "
#456000
b111001001 #
b1001000 "
#457000
b111001010 #
b1001001 "
#458000
b111001011 #
b1001010 "
#459000
b111001100 #
b1001011 "
#460000
b111001101 #
b1001100 "
#461000
b111001110 #
b1001101 "
#462000
b111001111 #
b1001110 "
#463000
b111010000 #
b1001111 "
#464000
b111010001 #
b1010000 "
#465000
b111010010 #
b1010001 "
#466000
b111010011 #
b1010010 "
#467000
b111010100 #
b1010011 "
#468000
b111010101 #
b1010100 "
#469000
b111010110 #
b1010101 "
#470000
b111010111 #
b1010110 "
#471000
b111011000 #
b1010111 "
#472000
b111011001 #
b1011000 "
#473000
b111011010 #
b1011001 "
#474000
b111011011 #
b1011010 "
#475000
b111011100 #
b1011011 "
#476000
b111011101 #
b1011100 "
#477000
b111011110 #
b1011101 "
#478000
b111011111 #
b1011110 "
#479000
b111100000 #
b1011111 "
#480000
b111100001 #
b1100000 "
#481000
b111100010 #
b1100001 "
#482000
b111100011 #
b1100010 "
#483000
b111100100 #
b1100011 "
#484000
b111100101 #
b1100100 "
#485000
b111100110 #
b1100101 "
#486000
b111100111 #
b1100110 "
#487000
b111101000 #
b1100111 "
#488000
b111101001 #
b1101000 "
#489000
b111101010 #
b1101001 "
#490000
b111101011 #
b1101010 "
#491000
b111101100 #
b1101011 "
#492000
b111101101 #
b1101100 "
#493000
b111101110 #
b1101101 "
#494000
b111101111 #
b1101110 "
#495000
b111110000 #
b1101111 "
#496000
b111110001 #
b1110000 "
#497000
b111110010 #
b1110001 "
#498000
b111110011 #
b1110010 "
#499000
b111110100 #
b1110011 "
#500000
b111110101 #
b1110100 "
#501000
b111110110 #
b1110101 "
#502000
b111110111 #
b1110110 "
#503000
b111111000 #
b1110111 "
#504000
b111111001 #
b1111000 "
#505000
b111111010 #
b1111001 "
#506000
b111111011 #
b1111010 "
#507000
b111111100 #
b1111011 "
#508000
b111111101 #
b1111100 "
#509000
b111111110 #
b1111101 "
#510000
b111111111 #
b1111110 "
#511000
b0 #
b1111111 "
#512000
b10000000 "
b100000010 #
b10000010 !
#513000
b100000011 #
b10000001 "
#514000
b100000100 #
b10000010 "
#515000
b100000101 #
b10000011 "
#516000
b100000110 #
b10000100 "
#517000
b100000111 #
b10000101 "
#518000
b100001000 #
b10000110 "
#519000
b100001001 #
b10000111 "
#520000
b100001010 #
b10001000 "
#521000
b100001011 #
b10001001 "
#522000
b100001100 #
b10001010 "
#523000
b100001101 #
b10001011 "
#524000
b100001110 #
b10001100 "
#525000
b100001111 #
b10001101 "
#526000
b100010000 #
b10001110 "
#527000
b100010001 #
b10001111 "
#528000
b100010010 #
b10010000 "
#529000
b100010011 #
b10010001 "
#530000
b100010100 #
b10010010 "
#531000
b100010101 #
b10010011 "
#532000
b100010110 #
b10010100 "
#533000
b100010111 #
b10010101 "
#534000
b100011000 #
b10010110 "
#535000
b100011001 #
b10010111 "
#536000
b100011010 #
b10011000 "
#537000
b100011011 #
b10011001 "
#538000
b100011100 #
b10011010 "
#539000
b100011101 #
b10011011 "
#540000
b100011110 #
b10011100 "
#541000
b100011111 #
b10011101 "
#542000
b100100000 #
b10011110 "
#543000
b100100001 #
b10011111 "
#544000
b100100010 #
b10100000 "
#545000
b100100011 #
b10100001 "
#546000
b100100100 #
b10100010 "
#547000
b100100101 #
b10100011 "
#548000
b100100110 #
b10100100 "
#549000
b100100111 #
b10100101 "
#550000
b100101000 #
b10100110 "
#551000
b100101001 #
b10100111 "
#552000
b100101010 #
b10101000 "
#553000
b100101011 #
b10101001 "
#554000
b100101100 #
b10101010 "
#555000
b100101101 #
b10101011 "
#556000
b100101110 #
b10101100 "
#557000
b100101111 #
b10101101 "
#558000
b100110000 #
b10101110 "
#559000
b100110001 #
b10101111 "
#560000
b100110010 #
b10110000 "
#561000
b100110011 #
b10110001 "
#562000
b100110100 #
b10110010 "
#563000
b100110101 #
b10110011 "
#564000
b100110110 #
b10110100 "
#565000
b100110111 #
b10110101 "
#566000
b100111000 #
b10110110 "
#567000
b100111001 #
b10110111 "
#568000
b100111010 #
b10111000 "
#569000
b100111011 #
b10111001 "
#570000
b100111100 #
b10111010 "
#571000
b100111101 #
b10111011 "
#572000
b100111110 #
b10111100 "
#573000
b100111111 #
b10111101 "
#574000
b101000000 #
b10111110 "
#575000
b101000001 #
b10111111 "
#576000
b101000010 #
b11000000 "
#577000
b101000011 #
b11000001 "
#578000
b101000100 #
b11000010 "
#579000
b101000101 #
b11000011 "
#580000
b101000110 #
b11000100 "
#581000
b101000111 #
b11000101 "
#582000
b101001000 #
b11000110 "
#583000
b101001001 #
b11000111 "
#584000
b101001010 #
b11001000 "
#585000
b101001011 #
b11001001 "
#586000
b101001100 #
b11001010 "
#587000
b101001101 #
b11001011 "
#588000
b101001110 #
b11001100 "
#589000
b101001111 #
b11001101 "
#590000
b101010000 #
b11001110 "
#591000
b101010001 #
b11001111 "
#592000
b101010010 #
b11010000 "
#593000
b101010011 #
b11010001 "
#594000
b101010100 #
b11010010 "
#595000
b101010101 #
b11010011 "
#596000
b101010110 #
b11010100 "
#597000
b101010111 #
b11010101 "
#598000
b101011000 #
b11010110 "
#599000
b101011001 #
b11010111 "
#600000
b101011010 #
b11011000 "
#601000
b101011011 #
b11011001 "
#602000
b101011100 #
b11011010 "
#603000
b101011101 #
b11011011 "
#604000
b101011110 #
b11011100 "
#605000
b101011111 #
b11011101 "
#606000
b101100000 #
b11011110 "
#607000
b101100001 #
b11011111 "
#608000
b101100010 #
b11100000 "
#609000
b101100011 #
b11100001 "
#610000
b101100100 #
b11100010 "
#611000
b101100101 #
b11100011 "
#612000
b101100110 #
b11100100 "
#613000
b101100111 #
b11100101 "
#614000
b101101000 #
b11100110 "
#615000
b101101001 #
b11100111 "
#616000
b101101010 #
b11101000 "
#617000
b101101011 #
b11101001 "
#618000
b101101100 #
b11101010 "
#619000
b101101101 #
b11101011 "
#620000
b101101110 #
b11101100 "
#621000
b101101111 #
b11101101 "
#622000
b101110000 #
b11101110 "
#623000
b101110001 #
b11101111 "
#624000
b101110010 #
b11110000 "
#625000
b101110011 #
b11110001 "
#626000
b101110100 #
b11110010 "
#627000
b101110101 #
b11110011 "
#628000
b101110110 #
b11110100 "
#629000
b101110111 #
b11110101 "
#630000
b101111000 #
b11110110 "
#631000
b101111001 #
b11110111 "
#632000
b101111010 #
b11111000 "
#633000
b101111011 #
b11111001 "
#634000
b101111100 #
b11111010 "
#635000
b101111101 #
b11111011 "
#636000
b101111110 #
b11111100 "
#637000
b101111111 #
b11111101 "
#638000
b110000000 #
b11111110 "
#639000
b110000001 #
b11111111 "
#640000
b110000010 #
b0 "
#641000
b110000011 #
b1 "
#642000
b110000100 #
b10 "
#643000
b110000101 #
b11 "
#644000
b110000110 #
b100 "
#645000
b110000111 #
b101 "
#646000
b110001000 #
b110 "
#647000
b110001001 #
b111 "
#648000
b110001010 #
b1000 "
#649000
b110001011 #
b1001 "
#650000
b110001100 #
b1010 "
#651000
b110001101 #
b1011 "
#652000
b110001110 #
b1100 "
#653000
b110001111 #
b1101 "
#654000
b110010000 #
b1110 "
#655000
b110010001 #
b1111 "
#656000
b110010010 #
b10000 "
#657000
b110010011 #
b10001 "
#658000
b110010100 #
b10010 "
#659000
b110010101 #
b10011 "
#660000
b110010110 #
b10100 "
#661000
b110010111 #
b10101 "
#662000
b110011000 #
b10110 "
#663000
b110011001 #
b10111 "
#664000
b110011010 #
b11000 "
#665000
b110011011 #
b11001 "
#666000
b110011100 #
b11010 "
#667000
b110011101 #
b11011 "
#668000
b110011110 #
b11100 "
#669000
b110011111 #
b11101 "
#670000
b110100000 #
b11110 "
#671000
b110100001 #
b11111 "
#672000
b110100010 #
b100000 "
#673000
b110100011 #
b100001 "
#674000
b110100100 #
b100010 "
#675000
b110100101 #
b100011 "
#676000
b110100110 #
b100100 "
#677000
b110100111 #
b100101 "
#678000
b110101000 #
b100110 "
#679000
b110101001 #
b100111 "
#680000
b110101010 #
b101000 "
#681000
b110101011 #
b101001 "
#682000
b110101100 #
b101010 "
#683000
b110101101 #
b101011 "
#684000
b110101110 #
b101100 "
#685000
b110101111 #
b101101 "
#686000
b110110000 #
b101110 "
#687000
b110110001 #
b101111 "
#688000
b110110010 #
b110000 "
#689000
b110110011 #
b110001 "
#690000
b110110100 #
b110010 "
#691000
b110110101 #
b110011 "
#692000
b110110110 #
b110100 "
#693000
b110110111 #
b110101 "
#694000
b110111000 #
b110110 "
#695000
b110111001 #
b110111 "
#696000
b110111010 #
b111000 "
#697000
b110111011 #
b111001 "
#698000
b110111100 #
b111010 "
#699000
b110111101 #
b111011 "
#700000
b110111110 #
b111100 "
#701000
b110111111 #
b111101 "
#702000
b111000000 #
b111110 "
#703000
b111000001 #
b111111 "
#704000
b111000010 #
b1000000 "
#705000
b111000011 #
b1000001 "
#706000
b111000100 #
b1000010 "
#707000
b111000101 #
b1000011 "
#708000
b111000110 #
b1000100 "
#709000
b111000111 #
b1000101 "
#710000
b111001000 #
b1000110 "
#711000
b111001001 #
b1000111 "
#712000
b111001010 #
b1001000 "
#713000
b111001011 #
b1001001 "
#714000
b111001100 #
b1001010 "
#715000
b111001101 #
b1001011 "
#716000
b111001110 #
b1001100 "
#717000
b111001111 #
b1001101 "
#718000
b111010000 #
b1001110 "
#719000
b111010001 #
b1001111 "
#720000
b111010010 #
b1010000 "
#721000
b111010011 #
b1010001 "
#722000
b111010100 #
b1010010 "
#723000
b111010101 #
b1010011 "
#724000
b111010110 #
b1010100 "
#725000
b111010111 #
b1010101 "
#726000
b111011000 #
b1010110 "
#727000
b111011001 #
b1010111 "
#728000
b111011010 #
b1011000 "
#729000
b111011011 #
b1011001 "
#730000
b111011100 #
b1011010 "
#731000
b111011101 #
b1011011 "
#732000
b111011110 #
b1011100 "
#733000
b111011111 #
b1011101 "
#734000
b111100000 #
b1011110 "
#735000
b111100001 #
b1011111 "
#736000
b111100010 #
b1100000 "
#737000
b111100011 #
b1100001 "
#738000
b111100100 #
b1100010 "
#739000
b111100101 #
b1100011 "
#740000
b111100110 #
b1100100 "
#741000
b111100111 #
b1100101 "
#742000
b111101000 #
b1100110 "
#743000
b111101001 #
b1100111 "
#744000
b111101010 #
b1101000 "
#745000
b111101011 #
b1101001 "
#746000
b111101100 #
b1101010 "
#747000
b111101101 #
b1101011 "
#748000
b111101110 #
b1101100 "
#749000
b111101111 #
b1101101 "
#750000
b111110000 #
b1101110 "
#751000
b111110001 #
b1101111 "
#752000
b111110010 #
b1110000 "
#753000
b111110011 #
b1110001 "
#754000
b111110100 #
b1110010 "
#755000
b111110101 #
b1110011 "
#756000
b111110110 #
b1110100 "
#757000
b111110111 #
b1110101 "
#758000
b111111000 #
b1110110 "
#759000
b111111001 #
b1110111 "
#760000
b111111010 #
b1111000 "
#761000
b111111011 #
b1111001 "
#762000
b111111100 #
b1111010 "
#763000
b111111101 #
b1111011 "
#764000
b111111110 #
b1111100 "
#765000
b111111111 #
b1111101 "
#766000
b0 #
b1111110 "
#767000
b1 #
b1111111 "
#768000
b10000000 "
b100000011 #
b10000011 !
#769000
b100000100 #
b10000001 "
#770000
b100000101 #
b10000010 "
#771000
b100000110 #
b10000011 "
#772000
b100000111 #
b10000100 "
#773000
b100001000 #
b10000101 "
#774000
b100001001 #
b10000110 "
#775000
b100001010 #
b10000111 "
#776000
b100001011 #
b10001000 "
#777000
b100001100 #
b10001001 "
#778000
b100001101 #
b10001010 "
#779000
b100001110 #
b10001011 "
#780000
b100001111 #
b10001100 "
#781000
b100010000 #
b10001101 "
#782000
b100010001 #
b10001110 "
#783000
b100010010 #
b10001111 "
#784000
b100010011 #
b10010000 "
#785000
b100010100 #
b10010001 "
#786000
b100010101 #
b10010010 "
#787000
b100010110 #
b10010011 "
#788000
b100010111 #
b10010100 "
#789000
b100011000 #
b10010101 "
#790000
b100011001 #
b10010110 "
#791000
b100011010 #
b10010111 "
#792000
b100011011 #
b10011000 "
#793000
b100011100 #
b10011001 "
#794000
b100011101 #
b10011010 "
#795000
b100011110 #
b10011011 "
#796000
b100011111 #
b10011100 "
#797000
b100100000 #
b10011101 "
#798000
b100100001 #
b10011110 "
#799000
b100100010 #
b10011111 "
#800000
b100100011 #
b10100000 "
#801000
b100100100 #
b10100001 "
#802000
b100100101 #
b10100010 "
#803000
b100100110 #
b10100011 "
#804000
b100100111 #
b10100100 "
#805000
b100101000 #
b10100101 "
#806000
b100101001 #
b10100110 "
#807000
b100101010 #
b10100111 "
#808000
b100101011 #
b10101000 "
#809000
b100101100 #
b10101001 "
#810000
b100101101 #
b10101010 "
#811000
b100101110 #
b10101011 "
#812000
b100101111 #
b10101100 "
#813000
b100110000 #
b10101101 "
#814000
b100110001 #
b10101110 "
#815000
b100110010 #
b10101111 "
#816000
b100110011 #
b10110000 "
#817000
b100110100 #
b10110001 "
#818000
b100110101 #
b10110010 "
#819000
b100110110 #
b10110011 "
#820000
b100110111 #
b10110100 "
#821000
b100111000 #
b10110101 "
#822000
b100111001 #
b10110110 "
#823000
b100111010 #
b10110111 "
#824000
b100111011 #
b10111000 "
