Comparator_operation/combinational_blocks.sv
// ==========================================
// 1. 2-to-4 Decoder
// ==========================================
module decoder_2to4 (
    input  logic [1:0] a,
    output logic [3:0] y
);
    always_comb begin
        case (a)
            2'b00:   y = 4'b0001;
            2'b01:   y = 4'b0010;
            2'b10:   y = 4'b0100;
            2'b11:   y = 4'b1000;
            default: y = 4'b0000;
        endcase
    end
endmodule

// ==========================================
// 2. 2-to-1 Multiplexer (using if-else)
// ==========================================
module mux_if ( 
    input  logic a, 
    input  logic b, 
    input  logic sel, 
    output logic y 
); 
    always_comb begin 
        if (sel == 1'b0) 
            y = a; 
        else 
            y = b; 
    end 
endmodule

// ==========================================
// 3. 8-bit Comparator
// ==========================================
module comparator (
    input  logic [7:0] a,
    input  logic [7:0] b,
    output logic       equal,
    output logic       greater,
    output logic       less
);
    assign equal   = (a == b);
    assign greater = (a > b);
    assign less    = (a < b);
endmodule


// ==========================================
// Testbench Wrapper for Simulation
// ==========================================
`ifndef SYNTHESIS
module tb_combinational;
    // Decoder signals
    logic [1:0] dec_a;
    logic [3:0] dec_y;

    // Mux signals
    logic m_a, m_b, m_sel, m_y;

    // Comparator signals
    logic [7:0] cmp_a, cmp_b;
    logic cmp_eq, cmp_gt, cmp_lt;

    // Instantiate modules
    decoder_2to4 u_dec (.a(dec_a), .y(dec_y));
    mux_if       u_mux (.a(m_a), .b(m_b), .sel(m_sel), .y(m_y));
    comparator   u_cmp (.a(cmp_a), .b(cmp_b), .equal(cmp_eq), .greater(cmp_gt), .less(cmp_lt));

    initial begin
        $dumpfile("combined.vcd");
        $dumpvars(0, tb_combinational);

        $display("=== Testing 2-to-4 Decoder ===");
        dec_a = 2'b00; #10; $display("a=%b -> y=%b", dec_a, dec_y);
        dec_a = 2'b01; #10; $display("a=%b -> y=%b", dec_a, dec_y);
        dec_a = 2'b10; #10; $display("a=%b -> y=%b", dec_a, dec_y);
        dec_a = 2'b11; #10; $display("a=%b -> y=%b", dec_a, dec_y);

        $display("\n=== Testing Mux (if-else) ===");
        m_a = 1'b0; m_b = 1'b1;
        m_sel = 0; #10; $display("sel=%b (a=%b, b=%b) -> y=%b", m_sel, m_a, m_b, m_y);
        m_sel = 1; #10; $display("sel=%b (a=%b, b=%b) -> y=%b", m_sel, m_a, m_b, m_y);

        $display("\n=== Testing 8-bit Comparator ===");
        cmp_a = 8'd45; cmp_b = 8'd20; #10;
        $display("a=%0d, b=%0d -> Equal=%b, Greater=%b, Less=%b", cmp_a, cmp_b, cmp_eq, cmp_gt, cmp_lt);

        cmp_a = 8'd10; cmp_b = 8'd10; #10;
        $display("a=%0d, b=%0d -> Equal=%b, Greater=%b, Less=%b", cmp_a, cmp_b, cmp_eq, cmp_gt, cmp_lt);

        $finish;
    end
endmodule
`endif

Comparator_operation/combined.vcd
$date
	Fri Aug 21 14:41:55 2026
$end
$version
	Icarus Verilog
$end
$timescale
	1s
$end
$scope module tb_combinational $end
$var wire 1 ! m_y $end
$var wire 4 " dec_y [3:0] $end
$var wire 1 # cmp_lt $end
$var wire 1 $ cmp_gt $end
$var wire 1 % cmp_eq $end
$var reg 8 & cmp_a [7:0] $end
$var reg 8 ' cmp_b [7:0] $end
$var reg 2 ( dec_a [1:0] $end
$var reg 1 ) m_a $end
$var reg 1 * m_b $end
$var reg 1 + m_sel $end
$scope module u_cmp $end
$var wire 8 , a [7:0] $end
$var wire 8 - b [7:0] $end
$var wire 1 # less $end
$var wire 1 $ greater $end
$var wire 1 % equal $end
$upscope $end
$scope module u_dec $end
$var wire 2 . a [1:0] $end
$var reg 4 / y [3:0] $end
$upscope $end
$scope module u_mux $end
$var wire 1 ) a $end
$var wire 1 * b $end
$var wire 1 + sel $end
$var reg 1 ! y $end
$upscope $end
$upscope $end
$enddefinitions $end
#0
$dumpvars
b1 /
b0 .
bx -
bx ,
x+
x*
x)
b0 (
bx '
bx &
x%
x$
x#
b1 "
x!
$end
#10
b10 "
b10 /
b1 (
b1 .
#20
b100 "
b100 /
b10 (
b10 .
#30
b1000 "
b1000 /
b11 (
b11 .
#40
0!
0+
1*
0)
#50
1!
1+
#60
0%
1$
0#
b10100 '
b10100 -
b101101 &
b101101 ,
#70
1%
b1010 '
b1010 -
0$
0#
b1010 &
b1010 ,
