day7parametercombinedgates/parameter_combinedgate.sv
module vector_gates_combined #(
    parameter WIDTH = 8
)(
    input  wire [WIDTH-1:0] a,
    input  wire [WIDTH-1:0] b,
    input  wire [2:0]       sel,

    // Every gate's result, always available
    output wire [WIDTH-1:0] y_and,
    output wire [WIDTH-1:0] y_or,
    output wire [WIDTH-1:0] y_xor,
    output wire [WIDTH-1:0] y_nand,
    output wire [WIDTH-1:0] y_nor,
    output wire [WIDTH-1:0] y_xnor,
    output wire [WIDTH-1:0] y_not_a,
    output wire [WIDTH-1:0] y_not_b,

    // Whichever single gate `sel` picks, taken from the outputs above
    output reg  [WIDTH-1:0] y_sel
);

    // Gate select encoding (used by y_sel)
    localparam GATE_AND   = 3'd0;
    localparam GATE_OR    = 3'd1;
    localparam GATE_XOR   = 3'd2;
    localparam GATE_NAND  = 3'd3;
    localparam GATE_NOR   = 3'd4;
    localparam GATE_XNOR  = 3'd5;
    localparam GATE_NOT_A = 3'd6;
    localparam GATE_NOT_B = 3'd7;

    genvar i;
    generate
        for (i = 0; i < WIDTH; i = i + 1) begin : GEN_GATES
            assign y_and[i]   = a[i] & b[i];
            assign y_or[i]    = a[i] | b[i];
            assign y_xor[i]   = a[i] ^ b[i];
            assign y_nand[i]  = ~(a[i] & b[i]);
            assign y_nor[i]   = ~(a[i] | b[i]);
            assign y_xnor[i]  = ~(a[i] ^ b[i]);
            assign y_not_a[i] = ~a[i];
            assign y_not_b[i] = ~b[i];
        end
    endgenerate

    // Single selected output, built from the results above (not
    // recomputed) so y_sel always matches whichever y_* it names.
    always @(*) begin
        case (sel)
            GATE_AND:   y_sel = y_and;
            GATE_OR:    y_sel = y_or;
            GATE_XOR:   y_sel = y_xor;
            GATE_NAND:  y_sel = y_nand;
            GATE_NOR:   y_sel = y_nor;
            GATE_XNOR:  y_sel = y_xnor;
            GATE_NOT_A: y_sel = y_not_a;
            GATE_NOT_B: y_sel = y_not_b;
            default:    y_sel = {WIDTH{1'b0}};
        endcase
    end

    initial begin
        $dumpfile("vector_gates_combined.vcd");
        $dumpvars(0, vector_gates_combined);
    end

endmodule

day7parametercombinedgates/vector_gates_combined.vcd
$date
	Wed Aug 26 16:01:25 2026
$end
$version
	Icarus Verilog
$end
$timescale
	1ps
$end
$scope module vector_gates_combined $end
$var wire 8 ! a [7:0] $end
$var wire 8 " b [7:0] $end
$var wire 3 # sel [2:0] $end
$var wire 8 $ y_xor [7:0] $end
$var wire 8 % y_xnor [7:0] $end
$var wire 8 & y_or [7:0] $end
$var wire 8 ' y_not_b [7:0] $end
$var wire 8 ( y_not_a [7:0] $end
$var wire 8 ) y_nor [7:0] $end
$var wire 8 * y_nand [7:0] $end
$var wire 8 + y_and [7:0] $end
$var reg 8 , y_sel [7:0] $end
$scope begin GEN_GATES[0] $end
$upscope $end
$scope begin GEN_GATES[1] $end
$upscope $end
$scope begin GEN_GATES[2] $end
$upscope $end
$scope begin GEN_GATES[3] $end
$upscope $end
$scope begin GEN_GATES[4] $end
$upscope $end
$scope begin GEN_GATES[5] $end
$upscope $end
$scope begin GEN_GATES[6] $end
$upscope $end
$scope begin GEN_GATES[7] $end
$upscope $end
$upscope $end
$enddefinitions $end
#0
$dumpvars
b10001000 ,
b10001000 +
b1110111 *
b10001 )
b1010101 (
b110011 '
b11101110 &
b10011001 %
b1100110 $
b0 #
b11001100 "
b10101010 !
$end
#1000
b11110000 *
b0 )
b1111 %
b1111 ,
b11110000 '
b1111 +
b11111111 &
b11110000 $
b0 (
b1111 "
b11111111 !
#2000
b11111111 *
b0 %
b0 ,
b0 '
b0 +
b11111111 $
b11111111 (
b11111111 "
b0 !
#3000
b0 *
b11111111 %
b11111111 ,
b11111111 +
b0 $
b0 (
b11111111 !
#4000
b11111111 *
b11111111 )
b0 ,
b11111111 '
b0 +
b0 &
b11111111 (
b0 "
b0 !
#5000
b0 )
b0 %
b1011010 '
b11111111 &
b11111111 $
b10100101 (
b10100101 "
b1011010 !
#6001
b11110000 *
b1111 %
b1111 ,
b11110000 '
b1111 +
b11110000 $
b0 (
b1111 "
b11111111 !
#7001
b11111111 *
b0 %
b0 ,
b0 '
b0 +
b11111111 $
b11111111 (
b11111111 "
b0 !
#8001
b0 *
b11111111 %
b11111111 ,
b11111111 +
b0 $
b0 (
b11111111 !
#9001
b11111111 *
b11111111 )
b0 ,
b11111111 '
b0 +
b0 &
b11111111 (
b0 "
b0 !
#10001
b0 )
b0 %
b1011010 '
b11111111 &
b11111111 $
b10100101 (
b10100101 "
b1011010 !
#11001
b10001 )
b1110111 *
b10011001 %
b10001000 ,
b110011 '
b11101110 &
b10001000 +
b1100110 $
b1010101 (
b11001100 "
b10101010 !
#12001
b11110000 *
b0 )
b1111 %
b11110000 '
b1111 +
b11111111 &
b11110000 $
b0 (
b11111111 ,
b1 #
b1111 "
b11111111 !
#13001
b11111111 *
b0 %
b0 '
b0 +
b11111111 $
b11111111 (
b11111111 "
b0 !
#14001
b0 *
b11111111 %
b11111111 +
b0 $
b0 (
b11111111 !
#15001
b11111111 *
b11111111 )
b0 ,
b11111111 '
b0 +
b0 &
b11111111 (
b0 "
b0 !
#16001
b0 )
b0 %
b11111111 ,
b1011010 '
b11111111 &
b11111111 $
b10100101 (
b10100101 "
b1011010 !
#17001
b10001 )
b1110111 *
b10011001 %
b11101110 ,
b110011 '
b11101110 &
b10001000 +
b1100110 $
b1010101 (
b11001100 "
b10101010 !
#18001
b11110000 *
b0 )
b1111 %
b11110000 '
b1111 +
b11111111 &
b11110000 $
b0 (
b11110000 ,
b10 #
b1111 "
b11111111 !
#19001
b11111111 *
b0 %
b11111111 ,
b0 '
b0 +
b11111111 $
b11111111 (
b11111111 "
b0 !
#20001
b0 *
b11111111 %
b0 ,
b11111111 +
b0 $
b0 (
b11111111 !
#21001
b11111111 *
b11111111 )
b11111111 '
b0 +
b0 &
b11111111 (
b0 "
b0 !
#22001
b0 )
b0 %
b11111111 ,
b1011010 '
b11111111 &
b11111111 $
b10100101 (
b10100101 "
b1011010 !
#23001
b10001 )
b1110111 *
b10011001 %
b1100110 ,
b110011 '
b11101110 &
b10001000 +
b1100110 $
b1010101 (
b11001100 "
b10101010 !
#24001
b11110000 *
b0 )
b1111 %
b11110000 '
b1111 +
b11111111 &
b11110000 $
b0 (
b11110000 ,
b11 #
b1111 "
b11111111 !
#25001
b11111111 ,
b11111111 *
b0 %
b0 '
b0 +
b11111111 $
b11111111 (
b11111111 "
b0 !
#26001
b0 ,
b0 *
b11111111 %
b11111111 +
b0 $
b0 (
b11111111 !
#27001
b11111111 ,
b11111111 *
b11111111 )
b11111111 '
b0 +
b0 &
b11111111 (
b0 "
b0 !
#28001
b0 )
b0 %
b1011010 '
b11111111 &
b11111111 $
b10100101 (
b10100101 "
b1011010 !
#29001
b1110111 ,
b10001 )
b1110111 *
b10011001 %
b110011 '
b11101110 &
b10001000 +
b1100110 $
b1010101 (
b11001100 "
b10101010 !
#30001
b11110000 *
b0 )
b1111 %
b11110000 '
b1111 +
b11111111 &
b11110000 $
b0 (
b0 ,
b100 #
b1111 "
b11111111 !
#31001
b11111111 *
b0 %
b0 '
b0 +
b11111111 $
b11111111 (
b11111111 "
b0 !
#32001
b0 *
b11111111 %
b11111111 +
b0 $
b0 (
b11111111 !
#33001
b11111111 ,
b11111111 *
b11111111 )
b11111111 '
b0 +
b0 &
b11111111 (
b0 "
b0 !
#34001
b0 ,
b0 )
b0 %
b1011010 '
b11111111 &
b11111111 $
b10100101 (
b10100101 "
b1011010 !
#35001
b10001 ,
b10001 )
b1110111 *
b10011001 %
b110011 '
b11101110 &
b10001000 +
b1100110 $
b1010101 (
b11001100 "
b10101010 !
#36001
b11110000 *
b0 )
b1111 %
b11110000 '
b1111 +
b11111111 &
b11110000 $
b0 (
b1111 ,
b101 #
b1111 "
b11111111 !
#37001
b0 ,
b11111111 *
b0 %
b0 '
b0 +
b11111111 $
b11111111 (
b11111111 "
b0 !
#38001
b11111111 ,
b0 *
b11111111 %
b11111111 +
b0 $
b0 (
b11111111 !
#39001
b11111111 *
b11111111 )
b11111111 '
b0 +
b0 &
b11111111 (
b0 "
b0 !
#40001
b0 ,
b0 )
b0 %
b1011010 '
b11111111 &
b11111111 $
b10100101 (
b10100101 "
b1011010 !
#41001
b10011001 ,
b10001 )
b1110111 *
b10011001 %
b110011 '
b11101110 &
b10001000 +
b1100110 $
b1010101 (
b11001100 "
b10101010 !
#42001
b11110000 *
b0 )
b1111 %
b11110000 '
b1111 +
b11111111 &
b11110000 $
b0 (
b0 ,
b110 #
b1111 "
b11111111 !
#43001
b11111111 *
b0 %
b11111111 ,
b0 '
b0 +
b11111111 $
b11111111 (
b11111111 "
b0 !
#44001
b0 *
b11111111 %
b0 ,
b11111111 +
b0 $
b0 (
b11111111 !
#45001
b11111111 *
b11111111 )
b11111111 ,
b11111111 '
b0 +
b0 &
b11111111 (
b0 "
b0 !
#46001
b0 )
b0 %
b10100101 ,
b1011010 '
b11111111 &
b11111111 $
b10100101 (
b10100101 "
b1011010 !
#47001
b10001 )
b1110111 *
b10011001 %
b1010101 ,
b110011 '
b11101110 &
b10001000 +
b1100110 $
b1010101 (
b11001100 "
b10101010 !
#48001
b11110000 *
b0 )
b1111 %
b11110000 '
b1111 +
b11111111 &
b11110000 $
b0 (
b11110000 ,
b111 #
b1111 "
b11111111 !
#49001
b11111111 *
b0 %
b0 ,
b0 '
b0 +
b11111111 $
b11111111 (
b11111111 "
b0 !
#50001
b0 *
b11111111 %
b11111111 +
b0 $
b0 (
b11111111 !
#51001
b11111111 *
b11111111 )
b11111111 ,
b11111111 '
b0 +
b0 &
b11111111 (
b0 "
b0 !
#52001
b0 )
b0 %
b1011010 ,
b1011010 '
b11111111 &
b11111111 $
b10100101 (
b10100101 "
b1011010 !
#53001
b10001 )
b1110111 *
b10011001 %
b110011 ,
b110011 '
b11101110 &
b10001000 +
b1100110 $
b1010101 (
b11001100 "
b10101010 !
