Logical/up_down_counter/up_down_counter.sv
module up_down_counter (
    input wire clk,
    input wire reset,
    input wire up,
    output reg [7:0] count
);

    always @(posedge clk or posedge reset) begin
        if (reset)
            count <= 8'd0;
        else if (up)
            count <= count + 1'b1;
        else
            count <= count - 1'b1;
    end

endmodule

Logical/up_down_counter/waveform_tb.sv
`timescale 1ns/1ps

module waveform_tb;
    reg clk = 0;
    reg reset = 1;
    reg up = 1;
    wire [7:0] count;

    up_down_counter dut (
        .clk(clk),
        .reset(reset),
        .up(up),
        .count(count)
    );

    always #5 clk = ~clk;

    initial begin
        $dumpfile("up_down_counter.vcd");
        $dumpvars(0, waveform_tb);
        #12 reset = 0;
        #30 up = 0;
        #30 up = 1;
        #20 reset = 1;
        #8 $finish;
    end
endmodule

Logical/up_down_counter/up_down_counter.vcd
$date
	Mon Aug 24 15:02:24 2026
$end
$version
	Icarus Verilog
$end
$timescale
	1ps
$end
$scope module waveform_tb $end
$var wire 8 ! count [7:0] $end
$var reg 1 " clk $end
$var reg 1 # reset $end
$var reg 1 $ up $end
$scope module dut $end
$var wire 1 " clk $end
$var wire 1 # reset $end
$var wire 1 $ up $end
$var reg 8 % count [7:0] $end
$upscope $end
$upscope $end
$enddefinitions $end
#0
$dumpvars
bx %
1$
1#
0"
bx !
$end
#5000
b0 !
b0 %
1"
#10000
0"
#12000
0#
#15000
b1 !
b1 %
1"
#20000
0"
#25000
b10 !
b10 %
1"
#30000
0"
#35000
b11 !
b11 %
1"
#40000
0"
#42000
0$
#45000
b10 !
b10 %
1"
#50000
0"
#55000
b1 !
b1 %
1"
#60000
0"
#65000
b0 !
b0 %
1"
#70000
0"
#72000
1$
#75000
b1 !
b1 %
1"
#80000
0"
#85000
b10 !
b10 %
1"
#90000
0"
#92000
b0 !
b0 %
1#
