d4_signed_unsigned_multiply/multiplier_signed_netlist.v
/* Generated by Yosys 0.9 (git sha1 1979e0b) */

module multiplier_signed(A, B, product);
  wire _000_;
  wire _001_;
  wire _002_;
  wire _003_;
  wire _004_;
  wire _005_;
  wire _006_;
  wire _007_;
  wire _008_;
  wire _009_;
  wire _010_;
  wire _011_;
  wire _012_;
  wire _013_;
  wire _014_;
  wire _015_;
  wire _016_;
  wire _017_;
  wire _018_;
  wire _019_;
  wire _020_;
  wire _021_;
  wire _022_;
  wire _023_;
  wire _024_;
  wire _025_;
  wire _026_;
  wire _027_;
  wire _028_;
  wire _029_;
  wire _030_;
  wire _031_;
  wire _032_;
  wire _033_;
  wire _034_;
  wire _035_;
  wire _036_;
  wire _037_;
  wire _038_;
  wire _039_;
  wire _040_;
  wire _041_;
  wire _042_;
  wire _043_;
  wire _044_;
  wire _045_;
  wire _046_;
  wire _047_;
  wire _048_;
  wire _049_;
  wire _050_;
  wire _051_;
  wire _052_;
  wire _053_;
  wire _054_;
  wire _055_;
  wire _056_;
  wire _057_;
  wire _058_;
  wire _059_;
  wire _060_;
  wire _061_;
  wire _062_;
  wire _063_;
  wire _064_;
  wire _065_;
  wire _066_;
  wire _067_;
  wire _068_;
  wire _069_;
  wire _070_;
  wire _071_;
  wire _072_;
  wire _073_;
  wire _074_;
  wire _075_;
  wire _076_;
  wire _077_;
  wire _078_;
  wire _079_;
  wire _080_;
  wire _081_;
  wire _082_;
  wire _083_;
  wire _084_;
  wire _085_;
  wire _086_;
  wire _087_;
  wire _088_;
  wire _089_;
  wire _090_;
  wire _091_;
  wire _092_;
  wire _093_;
  wire _094_;
  wire _095_;
  wire _096_;
  wire _097_;
  wire _098_;
  wire _099_;
  wire _100_;
  wire _101_;
  wire _102_;
  wire _103_;
  wire _104_;
  wire _105_;
  wire _106_;
  wire _107_;
  wire _108_;
  wire _109_;
  wire _110_;
  wire _111_;
  wire _112_;
  wire _113_;
  wire _114_;
  wire _115_;
  wire _116_;
  wire _117_;
  wire _118_;
  wire _119_;
  wire _120_;
  wire _121_;
  wire _122_;
  wire _123_;
  wire _124_;
  wire _125_;
  wire _126_;
  wire _127_;
  wire _128_;
  wire _129_;
  wire _130_;
  wire _131_;
  wire _132_;
  wire _133_;
  wire _134_;
  wire _135_;
  wire _136_;
  wire _137_;
  wire _138_;
  wire _139_;
  wire _140_;
  wire _141_;
  wire _142_;
  wire _143_;
  wire _144_;
  wire _145_;
  wire _146_;
  wire _147_;
  wire _148_;
  wire _149_;
  wire _150_;
  wire _151_;
  wire _152_;
  wire _153_;
  wire _154_;
  wire _155_;
  wire _156_;
  wire _157_;
  wire _158_;
  wire _159_;
  wire _160_;
  wire _161_;
  wire _162_;
  wire _163_;
  wire _164_;
  wire _165_;
  wire _166_;
  wire _167_;
  wire _168_;
  wire _169_;
  wire _170_;
  wire _171_;
  wire _172_;
  wire _173_;
  wire _174_;
  wire _175_;
  wire _176_;
  wire _177_;
  wire _178_;
  wire _179_;
  wire _180_;
  wire _181_;
  wire _182_;
  wire _183_;
  wire _184_;
  wire _185_;
  wire _186_;
  wire _187_;
  wire _188_;
  wire _189_;
  wire _190_;
  wire _191_;
  wire _192_;
  wire _193_;
  wire _194_;
  wire _195_;
  wire _196_;
  wire _197_;
  wire _198_;
  wire _199_;
  wire _200_;
  wire _201_;
  wire _202_;
  wire _203_;
  wire _204_;
  wire _205_;
  wire _206_;
  wire _207_;
  wire _208_;
  wire _209_;
  wire _210_;
  wire _211_;
  wire _212_;
  wire _213_;
  wire _214_;
  wire _215_;
  wire _216_;
  wire _217_;
  wire _218_;
  wire _219_;
  wire _220_;
  wire _221_;
  wire _222_;
  wire _223_;
  wire _224_;
  wire _225_;
  wire _226_;
  wire _227_;
  wire _228_;
  wire _229_;
  wire _230_;
  wire _231_;
  wire _232_;
  wire _233_;
  wire _234_;
  wire _235_;
  wire _236_;
  wire _237_;
  wire _238_;
  wire _239_;
  wire _240_;
  wire _241_;
  wire _242_;
  wire _243_;
  wire _244_;
  wire _245_;
  wire _246_;
  wire _247_;
  wire _248_;
  wire _249_;
  wire _250_;
  wire _251_;
  wire _252_;
  wire _253_;
  wire _254_;
  wire _255_;
  wire _256_;
  wire _257_;
  wire _258_;
  wire _259_;
  wire _260_;
  wire _261_;
  wire _262_;
  wire _263_;
  wire _264_;
  wire _265_;
  wire _266_;
  wire _267_;
  wire _268_;
  wire _269_;
  wire _270_;
  wire _271_;
  wire _272_;
  wire _273_;
  wire _274_;
  wire _275_;
  wire _276_;
  wire _277_;
  wire _278_;
  wire _279_;
  wire _280_;
  wire _281_;
  wire _282_;
  wire _283_;
  wire _284_;
  wire _285_;
  wire _286_;
  wire _287_;
  wire _288_;
  wire _289_;
  wire _290_;
  wire _291_;
  wire _292_;
  wire _293_;
  wire _294_;
  wire _295_;
  wire _296_;
  wire _297_;
  wire _298_;
  wire _299_;
  wire _300_;
  wire _301_;
  wire _302_;
  wire _303_;
  wire _304_;
  wire _305_;
  wire _306_;
  wire _307_;
  wire _308_;
  wire _309_;
  wire _310_;
  wire _311_;
  wire _312_;
  wire _313_;
  wire _314_;
  wire _315_;
  wire _316_;
  wire _317_;
  wire _318_;
  wire _319_;
  wire _320_;
  wire _321_;
  wire _322_;
  wire _323_;
  wire _324_;
  wire _325_;
  wire _326_;
  wire _327_;
  wire _328_;
  wire _329_;
  wire _330_;
  wire _331_;
  wire _332_;
  wire _333_;
  wire _334_;
  wire _335_;
  wire _336_;
  wire _337_;
  wire _338_;
  wire _339_;
  wire _340_;
  wire _341_;
  wire _342_;
  wire _343_;
  wire _344_;
  wire _345_;
  wire _346_;
  wire _347_;
  wire _348_;
  wire _349_;
  wire _350_;
  wire _351_;
  wire _352_;
  wire _353_;
  wire _354_;
  wire _355_;
  wire _356_;
  wire _357_;
  wire _358_;
  wire _359_;
  wire _360_;
  wire _361_;
  wire _362_;
  wire _363_;
  wire _364_;
  wire _365_;
  wire _366_;
  wire _367_;
  wire _368_;
  wire _369_;
  wire _370_;
  wire _371_;
  wire _372_;
  wire _373_;
  wire _374_;
  input [7:0] A;
  input [7:0] B;
  output [15:0] product;
  assign _234_ = ~(B[0] & A[1]);
  assign _245_ = ~(B[1] & A[0]);
  assign product[1] = _245_ ^ _234_;
  assign _265_ = ~(B[0] & A[2]);
  assign _276_ = ~(B[1] & A[1]);
  assign _286_ = _276_ ^ _265_;
  assign _297_ = _245_ | _234_;
  assign _307_ = ~(_297_ ^ _286_);
  assign _318_ = B[2] & A[0];
  assign product[2] = _318_ ^ _307_;
  assign _320_ = B[3] & A[0];
  assign _321_ = B[0] & A[3];
  assign _322_ = _321_ ^ _320_;
  assign _323_ = B[1] & A[2];
  assign _324_ = _323_ ^ _322_;
  assign _325_ = ~(_276_ | _265_);
  assign _326_ = _325_ ^ _324_;
  assign _327_ = B[2] & A[1];
  assign _328_ = ~(_327_ ^ _326_);
  assign _329_ = _286_ & ~(_297_);
  assign _330_ = ~((_318_ & _307_) | _329_);
  assign product[3] = _330_ ^ _328_;
  assign _331_ = B[3] & A[1];
  assign _332_ = B[0] & A[4];
  assign _333_ = _332_ ^ _331_;
  assign _334_ = B[1] & A[3];
  assign _335_ = _334_ ^ _333_;
  assign _336_ = _321_ & _320_;
  assign _337_ = ~((_323_ & _322_) | _336_);
  assign _338_ = ~(_337_ ^ _335_);
  assign _339_ = B[2] & A[2];
  assign _340_ = B[4] & A[0];
  assign _341_ = _340_ ^ _339_;
  assign _342_ = _341_ ^ _338_;
  assign _343_ = _325_ & _324_;
  assign _344_ = ~((_327_ & _326_) | _343_);
  assign _345_ = _344_ ^ _342_;
  assign _346_ = _330_ | _328_;
  assign product[4] = _346_ ^ _345_;
  assign _347_ = B[3] & A[3];
  assign _348_ = B[0] & A[6];
  assign _349_ = _348_ ^ _347_;
  assign _350_ = B[1] & A[5];
  assign _351_ = _350_ ^ _349_;
  assign _352_ = ~(B[3] & A[2]);
  assign _353_ = B[0] & A[5];
  assign _354_ = _353_ & ~(_352_);
  assign _355_ = B[1] & A[4];
  assign _356_ = ~(_353_ ^ _352_);
  assign _357_ = ~((_356_ & _355_) | _354_);
  assign _358_ = ~(_357_ ^ _351_);
  assign _359_ = B[2] & A[4];
  assign _360_ = B[4] & A[2];
  assign _361_ = _360_ ^ _359_;
  assign _362_ = B[5] & A[1];
  assign _363_ = _362_ ^ _361_;
  assign _364_ = _363_ ^ _358_;
  assign _365_ = _356_ ^ _355_;
  assign _366_ = _332_ & _331_;
  assign _367_ = ~((_334_ & _333_) | _366_);
  assign _368_ = _365_ & ~(_367_);
  assign _369_ = B[2] & A[3];
  assign _370_ = B[4] & A[1];
  assign _371_ = _370_ ^ _369_;
  assign _372_ = B[5] & A[0];
  assign _373_ = _372_ ^ _371_;
  assign _374_ = ~(_367_ ^ _365_);
  assign _000_ = ~((_374_ & _373_) | _368_);
  assign _001_ = ~(_000_ ^ _364_);
  assign _002_ = _370_ & _369_;
  assign _003_ = _372_ & _371_;
  assign _004_ = _003_ | _002_;
  assign _005_ = B[6] & A[0];
  assign _006_ = _005_ ^ _004_;
  assign _007_ = ~(_006_ ^ _001_);
  assign _008_ = _374_ ^ _373_;
  assign _009_ = _335_ & ~(_337_);
  assign _010_ = ~((_341_ & _338_) | _009_);
  assign _011_ = _008_ & ~(_010_);
  assign _012_ = _340_ & _339_;
  assign _013_ = ~_012_;
  assign _014_ = _010_ ^ _008_;
  assign _015_ = _014_ | _013_;
  assign _016_ = _015_ & ~(_011_);
  assign _017_ = _016_ ^ _007_;
  assign _018_ = _014_ ^ _013_;
  assign _019_ = _342_ & ~(_344_);
  assign _020_ = ~(_019_ & _018_);
  assign _021_ = ~(_020_ ^ _017_);
  assign _022_ = _019_ ^ _018_;
  assign _023_ = _346_ | _345_;
  assign _024_ = _022_ & ~(_023_);
  assign product[6] = _024_ ^ _021_;
  assign _025_ = B[3] & A[4];
  assign _026_ = _025_ ^ B[7];
  assign _027_ = B[0] & A[7];
  assign _028_ = _027_ ^ _026_;
  assign _029_ = _348_ & _347_;
  assign _030_ = ~((_350_ & _349_) | _029_);
  assign _031_ = ~(_030_ ^ _028_);
  assign _032_ = B[1] & A[6];
  assign _033_ = ~(B[2] & A[5]);
  assign _034_ = ~(_033_ ^ _032_);
  assign _035_ = ~(B[4] & A[3]);
  assign _036_ = ~(_035_ ^ _034_);
  assign _037_ = _036_ ^ _031_;
  assign _038_ = _351_ & ~(_357_);
  assign _039_ = ~((_363_ & _358_) | _038_);
  assign _040_ = ~(_039_ ^ _037_);
  assign _041_ = _360_ & _359_;
  assign _042_ = _362_ & _361_;
  assign _043_ = _042_ | _041_;
  assign _044_ = B[5] & A[2];
  assign _045_ = B[6] & A[1];
  assign _046_ = _045_ ^ _044_;
  assign _047_ = B[7] & ~(A[0]);
  assign _048_ = ~_047_;
  assign _049_ = _048_ ^ _046_;
  assign _050_ = ~(_049_ ^ _043_);
  assign _051_ = _050_ ^ _040_;
  assign _052_ = _364_ & ~(_000_);
  assign _053_ = ~((_006_ & _001_) | _052_);
  assign _054_ = ~(_053_ ^ _051_);
  assign _055_ = _005_ & _004_;
  assign _056_ = _055_ ^ _054_;
  assign _057_ = ~(_016_ | _007_);
  assign _058_ = _057_ ^ _056_;
  assign _059_ = _017_ & ~(_020_);
  assign _060_ = ~((_024_ & _021_) | _059_);
  assign product[7] = ~(_060_ ^ _058_);
  assign _061_ = B[3] & A[5];
  assign _062_ = _061_ ^ _027_;
  assign _063_ = B[1] & A[7];
  assign _064_ = _063_ ^ _062_;
  assign _065_ = ~B[7];
  assign _066_ = _025_ & ~(_065_);
  assign _067_ = ~((_027_ & _026_) | _066_);
  assign _068_ = ~(_067_ ^ _064_);
  assign _069_ = B[2] & A[6];
  assign _070_ = ~(B[4] & A[4]);
  assign _071_ = ~(_070_ ^ _069_);
  assign _072_ = ~(B[5] & A[3]);
  assign _073_ = ~(_072_ ^ _071_);
  assign _074_ = _073_ ^ _068_;
  assign _075_ = _028_ & ~(_030_);
  assign _076_ = ~((_036_ & _031_) | _075_);
  assign _077_ = ~(_076_ ^ _074_);
  assign _078_ = _032_ & ~(_033_);
  assign _079_ = _034_ & ~(_035_);
  assign _080_ = _079_ | _078_;
  assign _081_ = B[6] & A[2];
  assign _082_ = A[1] | ~(B[7]);
  assign _083_ = _082_ ^ _081_;
  assign _084_ = ~(_083_ ^ _080_);
  assign _085_ = _045_ & _044_;
  assign _086_ = ~((_047_ & _046_) | _085_);
  assign _087_ = ~(_086_ ^ _084_);
  assign _088_ = _087_ ^ _077_;
  assign _089_ = _037_ & ~(_039_);
  assign _090_ = ~((_050_ & _040_) | _089_);
  assign _091_ = ~(_090_ ^ _088_);
  assign _092_ = _043_ & ~(_049_);
  assign _093_ = _092_ ^ _091_;
  assign _094_ = _051_ & ~(_053_);
  assign _095_ = ~((_055_ & _054_) | _094_);
  assign _096_ = ~(_095_ ^ _093_);
  assign _097_ = ~_024_;
  assign _098_ = _057_ & _056_;
  assign _099_ = ~((_059_ & _058_) | _098_);
  assign _100_ = ~(_058_ & _021_);
  assign _101_ = ~((_100_ | _097_) & _099_);
  assign product[8] = _101_ ^ _096_;
  assign _102_ = B[3] & A[6];
  assign _103_ = _102_ ^ _027_;
  assign _104_ = _103_ ^ _063_;
  assign _105_ = ~(B[0] & A[7]);
  assign _106_ = _061_ & ~(_105_);
  assign _107_ = ~((_063_ & _062_) | _106_);
  assign _108_ = ~(_107_ ^ _104_);
  assign _109_ = ~(B[2] & A[7]);
  assign _110_ = ~(B[4] & A[5]);
  assign _111_ = _110_ ^ _109_;
  assign _112_ = ~(B[5] & A[4]);
  assign _113_ = ~(_112_ ^ _111_);
  assign _114_ = _113_ ^ _108_;
  assign _115_ = _064_ & ~(_067_);
  assign _116_ = ~((_073_ & _068_) | _115_);
  assign _117_ = ~(_116_ ^ _114_);
  assign _118_ = _069_ & ~(_070_);
  assign _119_ = _071_ & ~(_072_);
  assign _120_ = ~(_119_ | _118_);
  assign _121_ = B[6] & A[3];
  assign _122_ = A[2] | ~(B[7]);
  assign _123_ = _122_ ^ _121_;
  assign _124_ = _123_ ^ _120_;
  assign _125_ = _081_ & ~(_082_);
  assign _126_ = _125_ ^ _124_;
  assign _127_ = _126_ ^ _117_;
  assign _128_ = _074_ & ~(_076_);
  assign _129_ = ~((_087_ & _077_) | _128_);
  assign _130_ = ~(_129_ ^ _127_);
  assign _131_ = _080_ & ~(_083_);
  assign _132_ = _084_ & ~(_086_);
  assign _133_ = _132_ | _131_;
  assign _134_ = _133_ ^ _130_;
  assign _135_ = _088_ & ~(_090_);
  assign _136_ = ~((_092_ & _091_) | _135_);
  assign _137_ = ~(_136_ ^ _134_);
  assign _138_ = _093_ & ~(_095_);
  assign _139_ = ~((_101_ & _096_) | _138_);
  assign product[9] = ~(_139_ ^ _137_);
  assign _140_ = B[3] & A[7];
  assign _141_ = _140_ ^ _027_;
  assign _142_ = ~(_141_ ^ _063_);
  assign _143_ = _102_ & ~(_105_);
  assign _144_ = ~((_103_ & _063_) | _143_);
  assign _145_ = _144_ ^ _142_;
  assign _146_ = ~(B[4] & A[6]);
  assign _147_ = _146_ ^ _109_;
  assign _148_ = ~(B[5] & A[5]);
  assign _149_ = ~(_148_ ^ _147_);
  assign _150_ = _149_ ^ _145_;
  assign _151_ = _104_ & ~(_107_);
  assign _152_ = ~((_113_ & _108_) | _151_);
  assign _153_ = ~(_152_ ^ _150_);
  assign _154_ = B[2] & A[7];
  assign _155_ = _154_ & ~(_110_);
  assign _156_ = _111_ & ~(_112_);
  assign _157_ = ~(_156_ | _155_);
  assign _158_ = B[6] & A[4];
  assign _159_ = A[3] | ~(B[7]);
  assign _160_ = _159_ ^ _158_;
  assign _161_ = _160_ ^ _157_;
  assign _162_ = _121_ & ~(_122_);
  assign _163_ = _162_ ^ _161_;
  assign _164_ = _163_ ^ _153_;
  assign _165_ = _114_ & ~(_116_);
  assign _166_ = ~((_126_ & _117_) | _165_);
  assign _167_ = ~(_166_ ^ _164_);
  assign _168_ = ~(_125_ & _124_);
  assign _169_ = ~((_123_ | _120_) & _168_);
  assign _170_ = _169_ ^ _167_;
  assign _171_ = _127_ & ~(_129_);
  assign _172_ = ~((_133_ & _130_) | _171_);
  assign _173_ = ~(_172_ ^ _170_);
  assign _174_ = _024_ & ~(_100_);
  assign _175_ = _099_ & ~(_174_);
  assign _176_ = _134_ & ~(_136_);
  assign _177_ = ~((_138_ & _137_) | _176_);
  assign _178_ = ~(_137_ & _096_);
  assign _179_ = ~((_178_ | _175_) & _177_);
  assign product[10] = _179_ ^ _173_;
  assign _180_ = _141_ ^ _063_;
  assign _181_ = _140_ & ~(_105_);
  assign _182_ = ~((_141_ & _063_) | _181_);
  assign _183_ = _182_ ^ _180_;
  assign _184_ = B[4] & A[7];
  assign _185_ = _184_ ^ _109_;
  assign _186_ = B[5] & A[6];
  assign _187_ = _186_ ^ _185_;
  assign _188_ = _187_ ^ _183_;
  assign _189_ = _180_ & ~(_144_);
  assign _190_ = ~((_149_ & _145_) | _189_);
  assign _191_ = ~(_190_ ^ _188_);
  assign _192_ = _154_ & ~(_146_);
  assign _193_ = _147_ & ~(_148_);
  assign _194_ = ~(_193_ | _192_);
  assign _195_ = ~(B[6] & A[5]);
  assign _196_ = B[7] & ~(A[4]);
  assign _197_ = _196_ ^ _195_;
  assign _198_ = _197_ ^ _194_;
  assign _199_ = _158_ & ~(_159_);
  assign _200_ = _199_ ^ _198_;
  assign _201_ = _200_ ^ _191_;
  assign _202_ = _150_ & ~(_152_);
  assign _203_ = ~((_163_ & _153_) | _202_);
  assign _204_ = ~(_203_ ^ _201_);
  assign _205_ = ~(_162_ & _161_);
  assign _206_ = ~((_160_ | _157_) & _205_);
  assign _207_ = _206_ ^ _204_;
  assign _208_ = _164_ & ~(_166_);
  assign _209_ = ~((_169_ & _167_) | _208_);
  assign _210_ = ~(_209_ ^ _207_);
  assign _211_ = _170_ & ~(_172_);
  assign _212_ = ~((_179_ & _173_) | _211_);
  assign product[11] = ~(_212_ ^ _210_);
  assign _213_ = B[5] & A[7];
  assign _214_ = _213_ ^ _185_;
  assign _215_ = ~(_214_ ^ _183_);
  assign _216_ = _180_ & ~(_182_);
  assign _217_ = _187_ | _183_;
  assign _218_ = _217_ & ~(_216_);
  assign _219_ = _218_ ^ _215_;
  assign _220_ = _184_ & ~(_109_);
  assign _221_ = ~_220_;
  assign _222_ = _186_ & ~(_185_);
  assign _223_ = _221_ & ~(_222_);
  assign _224_ = ~(B[6] & A[6]);
  assign _225_ = B[7] & ~(A[5]);
  assign _226_ = _225_ ^ _224_;
  assign _227_ = _226_ ^ _223_;
  assign _228_ = _196_ & ~(_195_);
  assign _229_ = _228_ ^ _227_;
  assign _230_ = _229_ ^ _219_;
  assign _231_ = _188_ & ~(_190_);
  assign _232_ = ~((_200_ & _191_) | _231_);
  assign _233_ = ~(_232_ ^ _230_);
  assign _235_ = ~(_199_ & _198_);
  assign _236_ = ~((_197_ | _194_) & _235_);
  assign _237_ = _236_ ^ _233_;
  assign _238_ = _201_ & ~(_203_);
  assign _239_ = ~((_206_ & _204_) | _238_);
  assign _240_ = _239_ ^ _237_;
  assign _241_ = _207_ & ~(_209_);
  assign _242_ = ~((_211_ & _210_) | _241_);
  assign _243_ = ~(_210_ & _173_);
  assign _244_ = ~((_243_ | _177_) & _242_);
  assign _246_ = ~(_243_ | _178_);
  assign _247_ = ~((_246_ & _101_) | _244_);
  assign product[12] = _247_ ^ _240_;
  assign _248_ = _214_ ^ _183_;
  assign _249_ = _214_ | _183_;
  assign _250_ = _249_ & ~(_216_);
  assign _251_ = _250_ ^ _248_;
  assign _252_ = _213_ & ~(_185_);
  assign _253_ = _252_ | _220_;
  assign _254_ = ~(B[6] & A[7]);
  assign _255_ = B[7] & ~(A[6]);
  assign _256_ = _255_ ^ _254_;
  assign _257_ = _256_ ^ _253_;
  assign _258_ = _225_ & ~(_224_);
  assign _259_ = _258_ ^ _257_;
  assign _260_ = _259_ ^ _251_;
  assign _261_ = _248_ & ~(_218_);
  assign _262_ = ~((_229_ & _219_) | _261_);
  assign _263_ = ~(_262_ ^ _260_);
  assign _264_ = ~(_226_ | _223_);
  assign _266_ = _228_ & _227_;
  assign _267_ = ~(_266_ | _264_);
  assign _268_ = ~_267_;
  assign _269_ = _268_ ^ _263_;
  assign _270_ = _230_ & ~(_232_);
  assign _271_ = ~((_236_ & _233_) | _270_);
  assign _272_ = _271_ ^ _269_;
  assign _273_ = _237_ & ~(_239_);
  assign _274_ = ~_273_;
  assign _275_ = ~((_247_ | _240_) & _274_);
  assign product[13] = ~(_275_ ^ _272_);
  assign _277_ = ~B[6];
  assign _278_ = A[7] ? _277_ : _065_;
  assign _279_ = _278_ ^ _253_;
  assign _280_ = _255_ & ~(_254_);
  assign _281_ = _280_ ^ _279_;
  assign _282_ = _281_ ^ _251_;
  assign _283_ = _248_ & ~(_250_);
  assign _284_ = _259_ | _251_;
  assign _285_ = _284_ & ~(_283_);
  assign _287_ = ~(_285_ ^ _282_);
  assign _288_ = _253_ & ~(_256_);
  assign _289_ = _258_ & ~(_257_);
  assign _290_ = ~(_289_ | _288_);
  assign _291_ = ~_290_;
  assign _292_ = _291_ ^ _287_;
  assign _293_ = _260_ & ~(_262_);
  assign _294_ = ~((_268_ & _263_) | _293_);
  assign _295_ = ~(_294_ ^ _292_);
  assign _296_ = _269_ & ~(_271_);
  assign _298_ = _273_ & ~(_272_);
  assign _299_ = ~(_298_ | _296_);
  assign _300_ = _272_ | _240_;
  assign _301_ = ~((_300_ | _247_) & _299_);
  assign product[14] = _301_ ^ _295_;
  assign _302_ = B[7] & ~(A[7]);
  assign _303_ = _302_ & ~(_254_);
  assign _304_ = _303_ ^ _279_;
  assign _305_ = _304_ ^ _251_;
  assign _306_ = _281_ | _251_;
  assign _308_ = _306_ & ~(_283_);
  assign _309_ = _308_ ^ _305_;
  assign _310_ = _278_ | ~(_253_);
  assign _311_ = _280_ & ~(_279_);
  assign _312_ = _310_ & ~(_311_);
  assign _313_ = _312_ ^ _309_;
  assign _314_ = _282_ & ~(_285_);
  assign _315_ = ~((_291_ & _287_) | _314_);
  assign _316_ = _315_ ^ _313_;
  assign _317_ = _292_ & ~(_294_);
  assign _319_ = ~((_301_ & _295_) | _317_);
  assign product[15] = _319_ ^ _316_;
  assign product[5] = ~(_023_ ^ _022_);
  assign product[0] = B[0] & A[0];
endmodule

d4_signed_unsigned_multiply/multiplier_signed.vcd
$date
	Thu Aug 20 16:58:16 2026
$end
$version
	Icarus Verilog
$end
$timescale
	1ps
$end
$scope module multiplier_signed $end
$var wire 8 ! A [7:0] $end
$var wire 8 " B [7:0] $end
$var wire 16 # product [15:0] $end
$upscope $end
$enddefinitions $end
#0
$dumpvars
b0 #
b0 "
b0 !
$end
#1000
b1 #
b1 "
b1 !
#2000
b101 "
b110010 #
b1010 !
#3000
b1111111111001110 #
b11110110 !
#4000
b11111011 "
b1111111111001110 #
b1010 !
#5000
b110010 #
b11110110 !
#6000
b1111111 "
b11111100000001 #
b1111111 !
#7000
b1100000010000000 #
b10000000 !
#8000
b100000000000000 #
b10000000 "
#9000
b11111111 "
b1 #
b11111111 !
