d5/mux_if.sv
// 2:1 Multiplexer using if/else (procedural style)
// sel = 0 -> y = a
// sel = 1 -> y = b
module mux_if (
    input  wire a,
    input  wire b,
    input  wire sel,
    output reg  y
);
    always @(*) begin
        if (sel == 1'b0)
            y = a;
        else
            y = b;
    end

    initial begin
        $dumpfile("mux_if.vcd");
        $dumpvars(0, mux_if);
    end
endmodule

d5/mux_if.vcd
$date
	Fri Aug 21 14:58:31 2026
$end
$version
	Icarus Verilog
$end
$timescale
	1ps
$end
$scope module mux_if $end
$var wire 1 ! a $end
$var wire 1 " b $end
$var wire 1 # sel $end
$var reg 1 $ y $end
$upscope $end
$enddefinitions $end
#0
$dumpvars
0$
0#
0"
0!
$end
#1000
1#
#2000
0#
1"
#3000
1$
1#
#4000
0#
0"
1!
#5000
0$
1#
#6000
1$
0#
1"
#7000
1#
