day7simpleram16/ram16.sv
module simple_ram (
    input  wire        clk,
    input  wire        write_enable,
    input  wire [7:0]  address,
    input  wire [15:0] write_data,
    output reg  [15:0] read_data
);

    reg [15:0] memory [0:255];

    initial begin
        $dumpfile("simple_ram.vcd");
        $dumpvars(0, simple_ram);
    end

    always @(posedge clk) begin
        if (write_enable)
            memory[address] <= write_data;
        read_data <= memory[address];
    end

endmodule

day7simpleram16/ram16.vcd
$date
	Tue Aug 25 14:37:24 2026
$end
$version
	Icarus Verilog
$end
$timescale
	1ps
$end
$scope module simple_ram $end
$var wire 8 ! address [7:0] $end
$var wire 1 " clk $end
$var wire 16 # write_data [15:0] $end
$var wire 1 $ write_enable $end
$var reg 16 % read_data [15:0] $end
$upscope $end
$enddefinitions $end
#0
$dumpvars
bx %
1$
b1011111011101111 #
1"
b10000 !
$end
#5000
0"
#10000
0$
1"
#15000
0"
#20000
b1011111011101111 %
1"
#21000
b1001000110100 #
b100000 !
1$
#25000
0"
#30000
0$
bx %
1"
#35000
0"
#40000
b1001000110100 %
1"
#41000
b10000 !
#45000
0"
#50000
b1011111011101111 %
1"
#51000
b0 #
b110000 !
1$
#55000
0"
#60000
0$
bx %
1"
#65000
0"
#70000
b0 %
1"
#71000
b1111111111111111 #
b110001 !
1$
#75000
0"
#80000
0$
bx %
1"
#85000
0"
#90000
b1111111111111111 %
1"
