seq_logic_ckts/d-flipflop/dflipflop.sv
`timescale 1ns/1ps

module dff_1bit (
    input  wire clk,
    input  wire reset,
    input  wire d,
    output reg  q
);

    // Asynchronous active-high reset
    always @(posedge clk or posedge reset) begin
        if (reset)
            q <= 1'b0;
        else
            q <= d;
    end

    // Waveform generation for simulation only
`ifndef SYNTHESIS
    initial begin
        $dumpfile("dff_waveform.vcd");
        $dumpvars(0, dff_1bit);
    end
`endif

endmodule

seq_logic_ckts/d-flipflop/dff_waveform.vcd
$date
	Mon Aug 24 16:36:47 2026
$end
$version
	Icarus Verilog
$end
$timescale
	1ps
$end
$scope module dff_1bit $end
$var wire 1 ! clk $end
$var wire 1 " d $end
$var wire 1 # reset $end
$var reg 1 $ q $end
$upscope $end
$enddefinitions $end
#0
$dumpvars
0$
1#
0"
1!
$end
#2000
1"
0#
#5000
0!
#10000
1$
1!
#11000
0"
#15000
0!
#20000
0$
1!
#21000
1"
#25000
0!
#30000
1$
1!
#31000
0$
1#
